Workbook

Sheet worker file
A1: ID | B1: Dept | C1: Location | D1: State | E1: Country | F1: Level | G1: FLSA | H1: Pay Rate type | I1: Salary | J1: Hourly rate | K1: Currency | L1: Pay Group | M1: Hire Date | N1: Term Date | O1: Leave Start Date | P1: Mgr | Q1: Status | R1: Worker Type | S1: scheduled weekly hours | T1: time type | U1: time entry template | V1: time calculation group | W1: work schedule | X1: Default Shift Code | Y1: Notes
A2: E0001 | B2: GPU Cloud | C2: San Francisco | D2: CA | E2: US | F2: M5 | G2: Exempt | H2: Salary | I2: 285,000 | K2: USD | L2: US Semi-monthly | M2: 44635 | P2: E0000 | Q2: Active | R2: Employee | S2: 40 | T2: Full time | U2: =IF(AND(TRIM(E2)="US",TRIM(G2)="Non-Exempt"),"US Non-Exempt EEs","") | V2: =IF(AND(TRIM(E2)="US",TRIM(G2)="Non-Exempt"),IF(TRIM(D2)="CA","US California Non-Exempt","US Non-California Non-Exempt"),"") | W2: =_xlfn.XLOOKUP(X2,ShiftCodes[Code],ShiftCodes[Work Schedule],"Unknown code") -> Standard (Mon–Fri 9:00–17:30) | X2: STD
A3: E0004 | B3: GPU Cloud | C3: Remote-US | D3: WA | E3: US | F3: IC3 | G3: Exempt | H3: Salary | I3: 160,000 | K3: USD | L3: US Semi-monthly | M3: 45158 | N3: 46326 | P3: E0002 | Q3: Termination pending | R3: Employee | S3: 40 | T3: Full time | U3: =IF(AND(TRIM(E3)="US",TRIM(G3)="Non-Exempt"),"US Non-Exempt EEs","") | V3: =IF(AND(TRIM(E3)="US",TRIM(G3)="Non-Exempt"),IF(TRIM(D3)="CA","US California Non-Exempt","US Non-California Non-Exempt"),"") | W3: =_xlfn.XLOOKUP(X3,ShiftCodes[Code],ShiftCodes[Work Schedule],"Unknown code") -> Standard (Mon–Fri 9:00–17:30) | X3: STD | Y3: Term date = end of current pay period (US Semi-monthly Oct 16–31, 2026)
A4: E0006 | B4: On-Prem | C4: London | D4: UK | E4: UK | F4: IC4 | G4: Exempt | H4: Salary | I4: 85,000 | K4: GBP | L4: UK Monthly | M4: 45340 | N4: 46326 | P4: E0005 | Q4: Termination pending | R4: Employee | S4: 37.5 | T4: Full time | U4: =IF(AND(TRIM(E4)="US",TRIM(G4)="Non-Exempt"),"US Non-Exempt EEs","") | V4: =IF(AND(TRIM(E4)="US",TRIM(G4)="Non-Exempt"),IF(TRIM(D4)="CA","US California Non-Exempt","US Non-California Non-Exempt"),"") | W4: =_xlfn.XLOOKUP(X4,ShiftCodes[Code],ShiftCodes[Work Schedule],"Unknown code") -> Standard (Mon–Fri 9:00–17:30) | X4: STD | Y4: Term date = end of current pay period (UK Monthly Oct 1–31, 2026)
A5: E0008 | B5: Engineering | C5: Toronto | D5: Ontario | E5: CA | F5: IC5 | G5: Exempt | H5: Salary | I5: 225000 | K5: CAD | L5: Canada Monthly | M5: 45019 | P5: E0007 | Q5: Active | R5: Employee | S5: 40 | T5: Full time | U5: =IF(AND(TRIM(E5)="US",TRIM(G5)="Non-Exempt"),"US Non-Exempt EEs","") | V5: =IF(AND(TRIM(E5)="US",TRIM(G5)="Non-Exempt"),IF(TRIM(D5)="CA","US California Non-Exempt","US Non-California Non-Exempt"),"") | W5: =_xlfn.XLOOKUP(X5,ShiftCodes[Code],ShiftCodes[Work Schedule],"Unknown code") -> Standard (Mon–Fri 9:00–17:30) | X5: STD
A6: E0009 | B6: Engineering | C6: Bangalore | D6: Karnataka | E6: IN | F6: IC4 | G6: Exempt | H6: Salary | I6: 45,00,000 | K6: INR | L6: India Monthly | M6: 44948 | N6: 46310 | P6: E0007 | Q6: Termination pending | R6: Employee | S6: 40 | T6: Full time | U6: =IF(AND(TRIM(E6)="US",TRIM(G6)="Non-Exempt"),"US Non-Exempt EEs","") | V6: =IF(AND(TRIM(E6)="US",TRIM(G6)="Non-Exempt"),IF(TRIM(D6)="CA","US California Non-Exempt","US Non-California Non-Exempt"),"") | W6: =_xlfn.XLOOKUP(X6,ShiftCodes[Code],ShiftCodes[Work Schedule],"Unknown code") -> Standard (Mon–Fri 9:00–17:30) | X6: STD | Y6: Term date mid-period (India Monthly Oct 1–31, 2026)
A7: E0021 | B7: On-Prem | C7: San Jose | D7: CA | E7: US | F7: T2 | G7: Non-Exempt | H7: Hourly | J7: 42 | K7: USD | L7: US Biweekly | M7: 45418 | P7: E0005 | Q7: Active | R7: Employee | S7: 40 | T7: Full time | U7: =IF(AND(TRIM(E7)="US",TRIM(G7)="Non-Exempt"),"US Non-Exempt EEs","") -> US Non-Exempt EEs | V7: =IF(AND(TRIM(E7)="US",TRIM(G7)="Non-Exempt"),IF(TRIM(D7)="CA","US California Non-Exempt","US Non-California Non-Exempt"),"") -> US California Non-Exempt | W7: =_xlfn.XLOOKUP(X7,ShiftCodes[Code],ShiftCodes[Work Schedule],"Unknown code") -> Shift A – Day (Mon–Fri 06:00–14:30) | X7: DAY
A8: E0022 | B8: On-Prem | C8: Austin | D8: TX | E8: US | F8: T2 | G8: Non-Exempt | H8: Hourly | J8: 40 | K8: USD | L8: US Biweekly | M8: 45488 | P8: E0005 | Q8: Active | R8: Employee | S8: 40 | T8: Full time | U8: =IF(AND(TRIM(E8)="US",TRIM(G8)="Non-Exempt"),"US Non-Exempt EEs","") -> US Non-Exempt EEs | V8: =IF(AND(TRIM(E8)="US",TRIM(G8)="Non-Exempt"),IF(TRIM(D8)="CA","US California Non-Exempt","US Non-California Non-Exempt"),"") -> US Non-California Non-Exempt | W8: =_xlfn.XLOOKUP(X8,ShiftCodes[Code],ShiftCodes[Work Schedule],"Unknown code") -> Shift B – Swing (Mon–Fri 14:00–22:30) | X8: SWNG
A9: E0148 | B9: GPU Cloud | C9: San Francisco | D9: CA | E9: US | F9: IC3 | G9: Non-Exempt | H9: Hourly | J9: 80 | K9: USD | L9: US Biweekly | M9: 45545 | N9: 46312 | P9: E0002 | Q9: Termination pending | R9: Employee | S9: 40 | T9: Full time | U9: =IF(AND(TRIM(E9)="US",TRIM(G9)="Non-Exempt"),"US Non-Exempt EEs","") -> US Non-Exempt EEs | V9: =IF(AND(TRIM(E9)="US",TRIM(G9)="Non-Exempt"),IF(TRIM(D9)="CA","US California Non-Exempt","US Non-California Non-Exempt"),"") -> US California Non-Exempt | W9: =_xlfn.XLOOKUP(X9,ShiftCodes[Code],ShiftCodes[Work Schedule],"Unknown code") -> Standard (Mon–Fri 9:00–17:30) | X9: STD | Y9: Last day = end of current pay period (US Biweekly Oct 4–17, 2026)
A10: E0149 | B10: G&A | C10: Remote-US | D10: NY | E10: US | F10: IC4 | G10: Exempt | H10: Salary | I10: 180,000 | K10: USD | L10: US Semi-monthly | M10: 45383 | O10: 46297 | P10: E0010 | Q10: On Leave(unpaid) | R10: Employee | S10: 40 | T10: Full time | U10: =IF(AND(TRIM(E10)="US",TRIM(G10)="Non-Exempt"),"US Non-Exempt EEs","") | V10: =IF(AND(TRIM(E10)="US",TRIM(G10)="Non-Exempt"),IF(TRIM(D10)="CA","US California Non-Exempt","US Non-California Non-Exempt"),"") | W10: =_xlfn.XLOOKUP(X10,ShiftCodes[Code],ShiftCodes[Work Schedule],"Unknown code") -> Standard (Mon–Fri 9:00–17:30) | X10: STD
A11: E0203 | B11: Engineering | C11: San Francisco | D11: CA | E11: US | F11: IC4 | G11: Exempt | H11: Salary | I11: 190,000 | K11: USD | L11: US Semi-monthly | M11: 46316 | P11: E0007 | Q11: New Hire | R11: Employee | S11: 40 | T11: Full time | U11: =IF(AND(TRIM(E11)="US",TRIM(G11)="Non-Exempt"),"US Non-Exempt EEs","") | V11: =IF(AND(TRIM(E11)="US",TRIM(G11)="Non-Exempt"),IF(TRIM(D11)="CA","US California Non-Exempt","US Non-California Non-Exempt"),"") | W11: =_xlfn.XLOOKUP(X11,ShiftCodes[Code],ShiftCodes[Work Schedule],"Unknown code") -> Standard (Mon–Fri 9:00–17:30) | X11: STD | Y11: New hire starting mid-period (US Semi-monthly Oct 16–31, 2026)
A12: E0000 | B12: G&A | C12: San Francisco | D12: CA | E12: US | F12: M7 | G12: Exempt | H12: Salary | I12: 383000 | K12: USD | L12: US Semi-monthly | M12: 43472 | Q12: Active | R12: Employee | S12: 40 | T12: Full time | U12: =IF(AND(TRIM(E12)="US",TRIM(G12)="Non-Exempt"),"US Non-Exempt EEs","") | V12: =IF(AND(TRIM(E12)="US",TRIM(G12)="Non-Exempt"),IF(TRIM(D12)="CA","US California Non-Exempt","US Non-California Non-Exempt"),"") | W12: =_xlfn.XLOOKUP(X12,ShiftCodes[Code],ShiftCodes[Work Schedule],"Unknown code") -> Standard (Mon–Fri 9:00–17:30) | X12: STD
A13: E0002 | B13: GPU Cloud | C13: San Francisco | D13: CA | E13: US | F13: M6 | G13: Exempt | H13: Salary | I13: 370000 | K13: USD | L13: US Semi-monthly | M13: 43892 | P13: E0000 | Q13: Active | R13: Employee | S13: 40 | T13: Full time | U13: =IF(AND(TRIM(E13)="US",TRIM(G13)="Non-Exempt"),"US Non-Exempt EEs","") | V13: =IF(AND(TRIM(E13)="US",TRIM(G13)="Non-Exempt"),IF(TRIM(D13)="CA","US California Non-Exempt","US Non-California Non-Exempt"),"") | W13: =_xlfn.XLOOKUP(X13,ShiftCodes[Code],ShiftCodes[Work Schedule],"Unknown code") -> Standard (Mon–Fri 9:00–17:30) | X13: STD
A14: E0003 | B14: GPU Cloud | C14: Seattle | D14: WA | E14: US | F14: M5 | G14: Exempt | H14: Salary | I14: 295000 | K14: USD | L14: US Semi-monthly | M14: 44022 | P14: E0002 | Q14: Active | R14: Employee | S14: 40 | T14: Full time | U14: =IF(AND(TRIM(E14)="US",TRIM(G14)="Non-Exempt"),"US Non-Exempt EEs","") | V14: =IF(AND(TRIM(E14)="US",TRIM(G14)="Non-Exempt"),IF(TRIM(D14)="CA","US California Non-Exempt","US Non-California Non-Exempt"),"") | W14: =_xlfn.XLOOKUP(X14,ShiftCodes[Code],ShiftCodes[Work Schedule],"Unknown code") -> Standard (Mon–Fri 9:00–17:30) | X14: STD
A15: E0005 | B15: On-Prem | C15: Dallas | D15: TX | E15: US | F15: M6 | G15: Exempt | H15: Salary | I15: 345000 | K15: USD | L15: US Semi-monthly | M15: 43983 | P15: E0000 | Q15: Active | R15: Employee | S15: 40 | T15: Full time | U15: =IF(AND(TRIM(E15)="US",TRIM(G15)="Non-Exempt"),"US Non-Exempt EEs","") | V15: =IF(AND(TRIM(E15)="US",TRIM(G15)="Non-Exempt"),IF(TRIM(D15)="CA","US California Non-Exempt","US Non-California Non-Exempt"),"") | W15: =_xlfn.XLOOKUP(X15,ShiftCodes[Code],ShiftCodes[Work Schedule],"Unknown code") -> Standard (Mon–Fri 9:00–17:30) | X15: STD
A16: E0007 | B16: Engineering | C16: Austin | D16: TX | E16: US | F16: M6 | G16: Exempt | H16: Salary | I16: 340000 | K16: USD | L16: US Semi-monthly | M16: 43864 | P16: E0000 | Q16: Active | R16: Employee | S16: 40 | T16: Full time | U16: =IF(AND(TRIM(E16)="US",TRIM(G16)="Non-Exempt"),"US Non-Exempt EEs","") | V16: =IF(AND(TRIM(E16)="US",TRIM(G16)="Non-Exempt"),IF(TRIM(D16)="CA","US California Non-Exempt","US Non-California Non-Exempt"),"") | W16: =_xlfn.XLOOKUP(X16,ShiftCodes[Code],ShiftCodes[Work Schedule],"Unknown code") -> Standard (Mon–Fri 9:00–17:30) | X16: STD
A17: E0010 | B17: G&A | C17: San Francisco | D17: CA | E17: US | F17: M6 | G17: Exempt | H17: Salary | I17: 265000 | K17: USD | L17: US Semi-monthly | M17: 44088 | P17: E0000 | Q17: Active | R17: Employee | S17: 40 | T17: Full time | U17: =IF(AND(TRIM(E17)="US",TRIM(G17)="Non-Exempt"),"US Non-Exempt EEs","") | V17: =IF(AND(TRIM(E17)="US",TRIM(G17)="Non-Exempt"),IF(TRIM(D17)="CA","US California Non-Exempt","US Non-California Non-Exempt"),"") | W17: =_xlfn.XLOOKUP(X17,ShiftCodes[Code],ShiftCodes[Work Schedule],"Unknown code") -> Standard (Mon–Fri 9:00–17:30) | X17: STD
A18: E0011 | B18: On-Prem | C18: San Francisco | D18: CA | E18: US | F18: M5 | G18: Exempt | H18: Salary | I18: 308000 | K18: USD | L18: US Semi-monthly | M18: 44111 | P18: E0005 | Q18: Active | R18: Employee | S18: 40 | T18: Full time | U18: =IF(AND(TRIM(E18)="US",TRIM(G18)="Non-Exempt"),"US Non-Exempt EEs","") | V18: =IF(AND(TRIM(E18)="US",TRIM(G18)="Non-Exempt"),IF(TRIM(D18)="CA","US California Non-Exempt","US Non-California Non-Exempt"),"") | W18: =_xlfn.XLOOKUP(X18,ShiftCodes[Code],ShiftCodes[Work Schedule],"Unknown code") -> Standard (Mon–Fri 9:00–17:30) | X18: STD
A19: E0012 | B19: GPU Cloud | C19: San Francisco | D19: CA | E19: US | F19: M5 | G19: Exempt | H19: Salary | I19: 267000 | K19: USD | L19: US Semi-monthly | M19: 44149 | P19: E0002 | Q19: Active | R19: Employee | S19: 40 | T19: Full time | U19: =IF(AND(TRIM(E19)="US",TRIM(G19)="Non-Exempt"),"US Non-Exempt EEs","") | V19: =IF(AND(TRIM(E19)="US",TRIM(G19)="Non-Exempt"),IF(TRIM(D19)="CA","US California Non-Exempt","US Non-California Non-Exempt"),"") | W19: =_xlfn.XLOOKUP(X19,ShiftCodes[Code],ShiftCodes[Work Schedule],"Unknown code") -> Standard (Mon–Fri 9:00–17:30) | X19: STD
A20: E0013 | B20: On-Prem | C20: San Jose | D20: CA | E20: US | F20: M5 | G20: Exempt | H20: Salary | I20: 287000 | K20: USD | L20: US Semi-monthly | M20: 44210 | P20: E0005 | Q20: Active | R20: Employee | S20: 40 | T20: Full time | U20: =IF(AND(TRIM(E20)="US",TRIM(G20)="Non-Exempt"),"US Non-Exempt EEs","") | V20: =IF(AND(TRIM(E20)="US",TRIM(G20)="Non-Exempt"),IF(TRIM(D20)="CA","US California Non-Exempt","US Non-California Non-Exempt"),"") | W20: =_xlfn.XLOOKUP(X20,ShiftCodes[Code],ShiftCodes[Work Schedule],"Unknown code") -> Standard (Mon–Fri 9:00–17:30) | X20: STD
A21: E0014 | B21: On-Prem | C21: San Jose | D21: CA | E21: US | F21: M4 | G21: Exempt | H21: Salary | I21: 241000 | K21: USD | L21: US Semi-monthly | M21: 44277 | P21: E0011 | Q21: Active | R21: Employee | S21: 40 | T21: Full time | U21: =IF(AND(TRIM(E21)="US",TRIM(G21)="Non-Exempt"),"US Non-Exempt EEs","") | V21: =IF(AND(TRIM(E21)="US",TRIM(G21)="Non-Exempt"),IF(TRIM(D21)="CA","US California Non-Exempt","US Non-California Non-Exempt"),"") | W21: =_xlfn.XLOOKUP(X21,ShiftCodes[Code],ShiftCodes[Work Schedule],"Unknown code") -> Standard (Mon–Fri 9:00–17:30) | X21: STD
A22: E0015 | B22: On-Prem | C22: Austin | D22: TX | E22: US | F22: T2 | G22: Non-Exempt | H22: Hourly | J22: 35 | K22: USD | L22: US Biweekly | M22: 44305 | P22: E0014 | Q22: Active | R22: Employee | S22: 40 | T22: Full time | U22: =IF(AND(TRIM(E22)="US",TRIM(G22)="Non-Exempt"),"US Non-Exempt EEs","") -> US Non-Exempt EEs | V22: =IF(AND(TRIM(E22)="US",TRIM(G22)="Non-Exempt"),IF(TRIM(D22)="CA","US California Non-Exempt","US Non-California Non-Exempt"),"") -> US Non-California Non-Exempt | W22: =_xlfn.XLOOKUP(X22,ShiftCodes[Code],ShiftCodes[Work Schedule],"Unknown code") -> Shift B – Swing (Mon–Fri 14:00–22:30) | X22: SWNG
A23: E0016 | B23: GPU Cloud | C23: Seattle | D23: WA | E23: US | F23: M4 | G23: Exempt | H23: Salary | I23: 223000 | K23: USD | L23: US Semi-monthly | M23: 44378 | P23: E0003 | Q23: Active | R23: Employee | S23: 40 | T23: Full time | U23: =IF(AND(TRIM(E23)="US",TRIM(G23)="Non-Exempt"),"US Non-Exempt EEs","") | V23: =IF(AND(TRIM(E23)="US",TRIM(G23)="Non-Exempt"),IF(TRIM(D23)="CA","US California Non-Exempt","US Non-California Non-Exempt"),"") | W23: =_xlfn.XLOOKUP(X23,ShiftCodes[Code],ShiftCodes[Work Schedule],"Unknown code") -> Standard (Mon–Fri 9:00–17:30) | X23: STD
A24: E0017 | B24: GPU Cloud | C24: Remote-US | D24: WA | E24: US | F24: IC2 | G24: Exempt | H24: Salary | I24: 137000 | K24: USD | L24: US Semi-monthly | M24: 44440 | N24: 46318 | P24: E0016 | Q24: Termination pending | R24: Employee | S24: 40 | T24: Full time | U24: =IF(AND(TRIM(E24)="US",TRIM(G24)="Non-Exempt"),"US Non-Exempt EEs","") | V24: =IF(AND(TRIM(E24)="US",TRIM(G24)="Non-Exempt"),IF(TRIM(D24)="CA","US California Non-Exempt","US Non-California Non-Exempt"),"") | W24: =_xlfn.XLOOKUP(X24,ShiftCodes[Code],ShiftCodes[Work Schedule],"Unknown code") -> Standard (Mon–Fri 9:00–17:30) | X24: STD | Y24: Term date mid-period (US Semi-monthly Oct 16–31, 2026)
A25: E0018 | B25: G&A | C25: New York | D25: NY | E25: US | F25: M5 | G25: Exempt | H25: Salary | I25: 257000 | K25: USD | L25: US Semi-monthly | M25: 44455 | P25: E0010 | Q25: Active | R25: Employee | S25: 40 | T25: Full time | U25: =IF(AND(TRIM(E25)="US",TRIM(G25)="Non-Exempt"),"US Non-Exempt EEs","") | V25: =IF(AND(TRIM(E25)="US",TRIM(G25)="Non-Exempt"),IF(TRIM(D25)="CA","US California Non-Exempt","US Non-California Non-Exempt"),"") | W25: =_xlfn.XLOOKUP(X25,ShiftCodes[Code],ShiftCodes[Work Schedule],"Unknown code") -> Standard (Mon–Fri 9:00–17:30) | X25: STD
A26: E0019 | B26: On-Prem | C26: San Jose | D26: CA | E26: US | F26: M4 | G26: Exempt | H26: Salary | I26: 213000 | K26: USD | L26: US Semi-monthly | M26: 44461 | P26: E0011 | Q26: Active | R26: Employee | S26: 40 | T26: Full time | U26: =IF(AND(TRIM(E26)="US",TRIM(G26)="Non-Exempt"),"US Non-Exempt EEs","") | V26: =IF(AND(TRIM(E26)="US",TRIM(G26)="Non-Exempt"),IF(TRIM(D26)="CA","US California Non-Exempt","US Non-California Non-Exempt"),"") | W26: =_xlfn.XLOOKUP(X26,ShiftCodes[Code],ShiftCodes[Work Schedule],"Unknown code") -> Standard (Mon–Fri 9:00–17:30) | X26: STD
A27: E0020 | B27: On-Prem | C27: San Jose | D27: CA | E27: US | F27: T1 | G27: Non-Exempt | H27: Hourly | J27: 30 | K27: USD | L27: US Biweekly | M27: 44497 | P27: E0019 | Q27: Active | R27: Employee | S27: 40 | T27: Full time | U27: =IF(AND(TRIM(E27)="US",TRIM(G27)="Non-Exempt"),"US Non-Exempt EEs","") -> US Non-Exempt EEs | V27: =IF(AND(TRIM(E27)="US",TRIM(G27)="Non-Exempt"),IF(TRIM(D27)="CA","US California Non-Exempt","US Non-California Non-Exempt"),"") -> US California Non-Exempt | W27: =_xlfn.XLOOKUP(X27,ShiftCodes[Code],ShiftCodes[Work Schedule],"Unknown code") -> Shift A – Day (Mon–Fri 06:00–14:30) | X27: DAY
A28: E0023 | B28: On-Prem | C28: San Jose | D28: CA | E28: US | F28: T3 | G28: Non-Exempt | H28: Hourly | J28: 42.5 | K28: USD | L28: US Biweekly | M28: 44629 | P28: E0019 | Q28: Active | R28: Employee | S28: 40 | T28: Full time | U28: =IF(AND(TRIM(E28)="US",TRIM(G28)="Non-Exempt"),"US Non-Exempt EEs","") -> US Non-Exempt EEs | V28: =IF(AND(TRIM(E28)="US",TRIM(G28)="Non-Exempt"),IF(TRIM(D28)="CA","US California Non-Exempt","US Non-California Non-Exempt"),"") -> US California Non-Exempt | W28: =_xlfn.XLOOKUP(X28,ShiftCodes[Code],ShiftCodes[Work Schedule],"Unknown code") -> Shift B – Swing (Mon–Fri 14:00–22:30) | X28: SWNG
A29: E0024 | B29: Engineering | C29: San Francisco | D29: CA | E29: US | F29: M5 | G29: Exempt | H29: Salary | I29: 272000 | K29: USD | L29: US Semi-monthly | M29: 44646 | P29: E0007 | Q29: Active | R29: Employee | S29: 40 | T29: Full time | U29: =IF(AND(TRIM(E29)="US",TRIM(G29)="Non-Exempt"),"US Non-Exempt EEs","") | V29: =IF(AND(TRIM(E29)="US",TRIM(G29)="Non-Exempt"),IF(TRIM(D29)="CA","US California Non-Exempt","US Non-California Non-Exempt"),"") | W29: =_xlfn.XLOOKUP(X29,ShiftCodes[Code],ShiftCodes[Work Schedule],"Unknown code") -> Standard (Mon–Fri 9:00–17:30) | X29: STD
A30: E0025 | B30: On-Prem | C30: San Jose | D30: CA | E30: US | F30: T2 | G30: Non-Exempt | H30: Hourly | J30: 34.5 | K30: USD | L30: US Biweekly | M30: 44657 | P30: E0019 | Q30: Active | R30: Employee | S30: 40 | T30: Full time | U30: =IF(AND(TRIM(E30)="US",TRIM(G30)="Non-Exempt"),"US Non-Exempt EEs","") -> US Non-Exempt EEs | V30: =IF(AND(TRIM(E30)="US",TRIM(G30)="Non-Exempt"),IF(TRIM(D30)="CA","US California Non-Exempt","US Non-California Non-Exempt"),"") -> US California Non-Exempt | W30: =_xlfn.XLOOKUP(X30,ShiftCodes[Code],ShiftCodes[Work Schedule],"Unknown code") -> Shift B – Swing (Mon–Fri 14:00–22:30) | X30: SWNG
A31: E0026 | B31: G&A | C31: San Francisco | D31: CA | E31: US | F31: M5 | G31: Exempt | H31: Salary | I31: 246000 | K31: USD | L31: US Semi-monthly | M31: 44661 | P31: E0010 | Q31: Active | R31: Employee | S31: 40 | T31: Full time | U31: =IF(AND(TRIM(E31)="US",TRIM(G31)="Non-Exempt"),"US Non-Exempt EEs","") | V31: =IF(AND(TRIM(E31)="US",TRIM(G31)="Non-Exempt"),IF(TRIM(D31)="CA","US California Non-Exempt","US Non-California Non-Exempt"),"") | W31: =_xlfn.XLOOKUP(X31,ShiftCodes[Code],ShiftCodes[Work Schedule],"Unknown code") -> Standard (Mon–Fri 9:00–17:30) | X31: STD
A32: E0027 | B32: GPU Cloud | C32: San Francisco | D32: CA | E32: US | F32: M4 | G32: Exempt | H32: Salary | I32: 209000 | K32: USD | L32: US Semi-monthly | M32: 44684 | P32: E0012 | Q32: Active | R32: Employee | S32: 40 | T32: Full time | U32: =IF(AND(TRIM(E32)="US",TRIM(G32)="Non-Exempt"),"US Non-Exempt EEs","") | V32: =IF(AND(TRIM(E32)="US",TRIM(G32)="Non-Exempt"),IF(TRIM(D32)="CA","US California Non-Exempt","US Non-California Non-Exempt"),"") | W32: =_xlfn.XLOOKUP(X32,ShiftCodes[Code],ShiftCodes[Work Schedule],"Unknown code") -> Standard (Mon–Fri 9:00–17:30) | X32: STD
A33: E0028 | B33: On-Prem | C33: San Jose | D33: CA | E33: US | F33: T1 | G33: Non-Exempt | H33: Hourly | J33: 31.75 | K33: USD | L33: US Biweekly | M33: 44684 | N33: 46308 | P33: E0019 | Q33: Termination pending | R33: Employee | S33: 40 | T33: Full time | U33: =IF(AND(TRIM(E33)="US",TRIM(G33)="Non-Exempt"),"US Non-Exempt EEs","") -> US Non-Exempt EEs | V33: =IF(AND(TRIM(E33)="US",TRIM(G33)="Non-Exempt"),IF(TRIM(D33)="CA","US California Non-Exempt","US Non-California Non-Exempt"),"") -> US California Non-Exempt | W33: =_xlfn.XLOOKUP(X33,ShiftCodes[Code],ShiftCodes[Work Schedule],"Unknown code") -> Shift A – Day (Mon–Fri 06:00–14:30) | X33: DAY | Y33: Term date mid-period (US Biweekly Oct 4–17, 2026); timecards after Oct 13 removed (incl. Oct 14 off-schedule punch)
A34: E0029 | B34: On-Prem | C34: San Jose | D34: CA | E34: US | F34: T1 | G34: Non-Exempt | H34: Hourly | J34: 28 | K34: USD | L34: US Biweekly | M34: 44725 | N34: 46312 | P34: E0019 | Q34: Termination pending | R34: Employee | S34: 24 | T34: Part time | U34: =IF(AND(TRIM(E34)="US",TRIM(G34)="Non-Exempt"),"US Non-Exempt EEs","") -> US Non-Exempt EEs | V34: =IF(AND(TRIM(E34)="US",TRIM(G34)="Non-Exempt"),IF(TRIM(D34)="CA","US California Non-Exempt","US Non-California Non-Exempt"),"") -> US California Non-Exempt | W34: =_xlfn.XLOOKUP(X34,ShiftCodes[Code],ShiftCodes[Work Schedule],"Unknown code") -> Part-time – Day (Mon/Wed/Fri 06:00–14:30) | X34: PT | Y34: Term date = end of current pay period (US Biweekly Oct 4–17, 2026)
A35: E0030 | B35: Engineering | C35: San Francisco | D35: CA | E35: US | F35: M4 | G35: Exempt | H35: Salary | I35: 230000 | K35: USD | L35: US Semi-monthly | M35: 44734 | P35: E0024 | Q35: Active | R35: Employee | S35: 40 | T35: Full time | U35: =IF(AND(TRIM(E35)="US",TRIM(G35)="Non-Exempt"),"US Non-Exempt EEs","") | V35: =IF(AND(TRIM(E35)="US",TRIM(G35)="Non-Exempt"),IF(TRIM(D35)="CA","US California Non-Exempt","US Non-California Non-Exempt"),"") | W35: =_xlfn.XLOOKUP(X35,ShiftCodes[Code],ShiftCodes[Work Schedule],"Unknown code") -> Standard (Mon–Fri 9:00–17:30) | X35: STD
A36: E0031 | B36: Engineering | C36: San Francisco | D36: CA | E36: US | F36: IC2 | G36: Exempt | H36: Salary | I36: 143000 | K36: USD | L36: US Semi-monthly | M36: 44748 | O36: 46316 | P36: E0030 | Q36: On Leave(unpaid) | R36: Employee | S36: 40 | T36: Full time | U36: =IF(AND(TRIM(E36)="US",TRIM(G36)="Non-Exempt"),"US Non-Exempt EEs","") | V36: =IF(AND(TRIM(E36)="US",TRIM(G36)="Non-Exempt"),IF(TRIM(D36)="CA","US California Non-Exempt","US Non-California Non-Exempt"),"") | W36: =_xlfn.XLOOKUP(X36,ShiftCodes[Code],ShiftCodes[Work Schedule],"Unknown code") -> Standard (Mon–Fri 9:00–17:30) | X36: STD
A37: E0032 | B37: GPU Cloud | C37: Seattle | D37: WA | E37: US | F37: M4 | G37: Exempt | H37: Salary | I37: 223000 | K37: USD | L37: US Semi-monthly | M37: 44806 | P37: E0012 | Q37: Active | R37: Employee | S37: 40 | T37: Full time | U37: =IF(AND(TRIM(E37)="US",TRIM(G37)="Non-Exempt"),"US Non-Exempt EEs","") | V37: =IF(AND(TRIM(E37)="US",TRIM(G37)="Non-Exempt"),IF(TRIM(D37)="CA","US California Non-Exempt","US Non-California Non-Exempt"),"") | W37: =_xlfn.XLOOKUP(X37,ShiftCodes[Code],ShiftCodes[Work Schedule],"Unknown code") -> Standard (Mon–Fri 9:00–17:30) | X37: STD
A38: E0033 | B38: Engineering | C38: Seattle | D38: WA | E38: US | F38: M5 | G38: Exempt | H38: Salary | I38: 255000 | K38: USD | L38: US Semi-monthly | M38: 44816 | P38: E0007 | Q38: Active | R38: Employee | S38: 40 | T38: Full time | U38: =IF(AND(TRIM(E38)="US",TRIM(G38)="Non-Exempt"),"US Non-Exempt EEs","") | V38: =IF(AND(TRIM(E38)="US",TRIM(G38)="Non-Exempt"),IF(TRIM(D38)="CA","US California Non-Exempt","US Non-California Non-Exempt"),"") | W38: =_xlfn.XLOOKUP(X38,ShiftCodes[Code],ShiftCodes[Work Schedule],"Unknown code") -> Standard (Mon–Fri 9:00–17:30) | X38: STD
A39: E0034 | B39: On-Prem | C39: San Jose | D39: CA | E39: US | F39: T2 | G39: Non-Exempt | H39: Hourly | J39: 38.75 | K39: USD | L39: US Biweekly | M39: 44851 | P39: E0019 | Q39: Active | R39: Employee | S39: 40 | T39: Full time | U39: =IF(AND(TRIM(E39)="US",TRIM(G39)="Non-Exempt"),"US Non-Exempt EEs","") -> US Non-Exempt EEs | V39: =IF(AND(TRIM(E39)="US",TRIM(G39)="Non-Exempt"),IF(TRIM(D39)="CA","US California Non-Exempt","US Non-California Non-Exempt"),"") -> US California Non-Exempt | W39: =_xlfn.XLOOKUP(X39,ShiftCodes[Code],ShiftCodes[Work Schedule],"Unknown code") -> Shift A – Day (Mon–Fri 06:00–14:30) | X39: DAY
A40: E0035 | B40: Engineering | C40: San Francisco | D40: CA | E40: US | F40: IC1 | G40: Exempt | H40: Salary | I40: 101000 | K40: USD | L40: US Semi-monthly | M40: 44863 | P40: E0030 | Q40: Active | R40: Employee | S40: 40 | T40: Full time | U40: =IF(AND(TRIM(E40)="US",TRIM(G40)="Non-Exempt"),"US Non-Exempt EEs","") | V40: =IF(AND(TRIM(E40)="US",TRIM(G40)="Non-Exempt"),IF(TRIM(D40)="CA","US California Non-Exempt","US Non-California Non-Exempt"),"") | W40: =_xlfn.XLOOKUP(X40,ShiftCodes[Code],ShiftCodes[Work Schedule],"Unknown code") -> Standard (Mon–Fri 9:00–17:30) | X40: STD
A41: E0036 | B41: On-Prem | C41: Austin | D41: TX | E41: US | F41: T1 | G41: Non-Exempt | H41: Hourly | J41: 28.5 | K41: USD | L41: US Biweekly | M41: 44871 | P41: E0014 | Q41: Active | R41: Employee | S41: 36 | T41: Full time | U41: =IF(AND(TRIM(E41)="US",TRIM(G41)="Non-Exempt"),"US Non-Exempt EEs","") -> US Non-Exempt EEs | V41: =IF(AND(TRIM(E41)="US",TRIM(G41)="Non-Exempt"),IF(TRIM(D41)="CA","US California Non-Exempt","US Non-California Non-Exempt"),"") -> US Non-California Non-Exempt | W41: =_xlfn.XLOOKUP(X41,ShiftCodes[Code],ShiftCodes[Work Schedule],"Unknown code") -> Shift D – Weekend (Fri–Sun 06:00–18:30) | X41: WKND
A42: E0037 | B42: G&A | C42: San Francisco | D42: CA | E42: US | F42: M5 | G42: Exempt | H42: Salary | I42: 252000 | K42: USD | L42: US Semi-monthly | M42: 44887 | P42: E0010 | Q42: Active | R42: Employee | S42: 40 | T42: Full time | U42: =IF(AND(TRIM(E42)="US",TRIM(G42)="Non-Exempt"),"US Non-Exempt EEs","") | V42: =IF(AND(TRIM(E42)="US",TRIM(G42)="Non-Exempt"),IF(TRIM(D42)="CA","US California Non-Exempt","US Non-California Non-Exempt"),"") | W42: =_xlfn.XLOOKUP(X42,ShiftCodes[Code],ShiftCodes[Work Schedule],"Unknown code") -> Standard (Mon–Fri 9:00–17:30) | X42: STD
A43: E0038 | B43: GPU Cloud | C43: Remote-US | D43: MA | E43: US | F43: IC1 | G43: Exempt | H43: Salary | I43: 120000 | K43: USD | L43: US Semi-monthly | M43: 44895 | P43: E0016 | Q43: Active | R43: Employee | S43: 40 | T43: Full time | U43: =IF(AND(TRIM(E43)="US",TRIM(G43)="Non-Exempt"),"US Non-Exempt EEs","") | V43: =IF(AND(TRIM(E43)="US",TRIM(G43)="Non-Exempt"),IF(TRIM(D43)="CA","US California Non-Exempt","US Non-California Non-Exempt"),"") | W43: =_xlfn.XLOOKUP(X43,ShiftCodes[Code],ShiftCodes[Work Schedule],"Unknown code") -> Standard (Mon–Fri 9:00–17:30) | X43: STD
A44: E0039 | B44: GPU Cloud | C44: Seattle | D44: WA | E44: US | F44: IC5 | G44: Exempt | H44: Salary | I44: 244000 | K44: USD | L44: US Semi-monthly | M44: 44903 | P44: E0032 | Q44: Active | R44: Employee | S44: 40 | T44: Full time | U44: =IF(AND(TRIM(E44)="US",TRIM(G44)="Non-Exempt"),"US Non-Exempt EEs","") | V44: =IF(AND(TRIM(E44)="US",TRIM(G44)="Non-Exempt"),IF(TRIM(D44)="CA","US California Non-Exempt","US Non-California Non-Exempt"),"") | W44: =_xlfn.XLOOKUP(X44,ShiftCodes[Code],ShiftCodes[Work Schedule],"Unknown code") -> Standard (Mon–Fri 9:00–17:30) | X44: STD
A45: E0040 | B45: On-Prem | C45: San Jose | D45: CA | E45: US | F45: T1 | G45: Non-Exempt | H45: Hourly | J45: 26.75 | K45: USD | L45: US Biweekly | M45: 44904 | P45: E0019 | Q45: Active | R45: Employee | S45: 40 | T45: Full time | U45: =IF(AND(TRIM(E45)="US",TRIM(G45)="Non-Exempt"),"US Non-Exempt EEs","") -> US Non-Exempt EEs | V45: =IF(AND(TRIM(E45)="US",TRIM(G45)="Non-Exempt"),IF(TRIM(D45)="CA","US California Non-Exempt","US Non-California Non-Exempt"),"") -> US California Non-Exempt | W45: =_xlfn.XLOOKUP(X45,ShiftCodes[Code],ShiftCodes[Work Schedule],"Unknown code") -> Shift A – Day (Mon–Fri 06:00–14:30) | X45: DAY
A46: E0041 | B46: Engineering | C46: Remote-US | D46: MA | E46: US | F46: IC2 | G46: Exempt | H46: Salary | I46: 130000 | K46: USD | L46: US Semi-monthly | M46: 44920 | P46: E0030 | Q46: Active | R46: Employee | S46: 40 | T46: Full time | U46: =IF(AND(TRIM(E46)="US",TRIM(G46)="Non-Exempt"),"US Non-Exempt EEs","") | V46: =IF(AND(TRIM(E46)="US",TRIM(G46)="Non-Exempt"),IF(TRIM(D46)="CA","US California Non-Exempt","US Non-California Non-Exempt"),"") | W46: =_xlfn.XLOOKUP(X46,ShiftCodes[Code],ShiftCodes[Work Schedule],"Unknown code") -> Standard (Mon–Fri 9:00–17:30) | X46: STD
A47: E0042 | B47: G&A | C47: Remote-US | D47: CA | E47: US | F47: M4 | G47: Exempt | H47: Salary | I47: 190000 | K47: USD | L47: US Semi-monthly | M47: 44961 | P47: E0018 | Q47: Active | R47: Employee | S47: 40 | T47: Full time | U47: =IF(AND(TRIM(E47)="US",TRIM(G47)="Non-Exempt"),"US Non-Exempt EEs","") | V47: =IF(AND(TRIM(E47)="US",TRIM(G47)="Non-Exempt"),IF(TRIM(D47)="CA","US California Non-Exempt","US Non-California Non-Exempt"),"") | W47: =_xlfn.XLOOKUP(X47,ShiftCodes[Code],ShiftCodes[Work Schedule],"Unknown code") -> Standard (Mon–Fri 9:00–17:30) | X47: STD
A48: E0043 | B48: Engineering | C48: San Francisco | D48: CA | E48: US | F48: IC2 | G48: Exempt | H48: Salary | I48: 124000 | K48: USD | L48: US Semi-monthly | M48: 44987 | P48: E0030 | Q48: Active | R48: Employee | S48: 40 | T48: Full time | U48: =IF(AND(TRIM(E48)="US",TRIM(G48)="Non-Exempt"),"US Non-Exempt EEs","") | V48: =IF(AND(TRIM(E48)="US",TRIM(G48)="Non-Exempt"),IF(TRIM(D48)="CA","US California Non-Exempt","US Non-California Non-Exempt"),"") | W48: =_xlfn.XLOOKUP(X48,ShiftCodes[Code],ShiftCodes[Work Schedule],"Unknown code") -> Standard (Mon–Fri 9:00–17:30) | X48: STD
A49: E0044 | B49: On-Prem | C49: San Jose | D49: CA | E49: US | F49: M4 | G49: Exempt | H49: Salary | I49: 227000 | K49: USD | L49: US Semi-monthly | M49: 44987 | P49: E0011 | Q49: Active | R49: Employee | S49: 40 | T49: Full time | U49: =IF(AND(TRIM(E49)="US",TRIM(G49)="Non-Exempt"),"US Non-Exempt EEs","") | V49: =IF(AND(TRIM(E49)="US",TRIM(G49)="Non-Exempt"),IF(TRIM(D49)="CA","US California Non-Exempt","US Non-California Non-Exempt"),"") | W49: =_xlfn.XLOOKUP(X49,ShiftCodes[Code],ShiftCodes[Work Schedule],"Unknown code") -> Standard (Mon–Fri 9:00–17:30) | X49: STD
A50: E0045 | B50: G&A | C50: Remote-US | D50: MA | E50: US | F50: IC3 | G50: Exempt | H50: Salary | I50: 145000 | K50: USD | L50: US Semi-monthly | M50: 45004 | P50: E0042 | Q50: Active | R50: Employee | S50: 40 | T50: Full time | U50: =IF(AND(TRIM(E50)="US",TRIM(G50)="Non-Exempt"),"US Non-Exempt EEs","") | V50: =IF(AND(TRIM(E50)="US",TRIM(G50)="Non-Exempt"),IF(TRIM(D50)="CA","US California Non-Exempt","US Non-California Non-Exempt"),"") | W50: =_xlfn.XLOOKUP(X50,ShiftCodes[Code],ShiftCodes[Work Schedule],"Unknown code") -> Standard (Mon–Fri 9:00–17:30) | X50: STD
A51: E0046 | B51: GPU Cloud | C51: Remote-US | D51: TX | E51: US | F51: IC4 | G51: Exempt | H51: Salary | I51: 180000 | K51: USD | L51: US Semi-monthly | M51: 45014 | P51: E0027 | Q51: Active | R51: Employee | S51: 40 | T51: Full time | U51: =IF(AND(TRIM(E51)="US",TRIM(G51)="Non-Exempt"),"US Non-Exempt EEs","") | V51: =IF(AND(TRIM(E51)="US",TRIM(G51)="Non-Exempt"),IF(TRIM(D51)="CA","US California Non-Exempt","US Non-California Non-Exempt"),"") | W51: =_xlfn.XLOOKUP(X51,ShiftCodes[Code],ShiftCodes[Work Schedule],"Unknown code") -> Standard (Mon–Fri 9:00–17:30) | X51: STD
A52: E0047 | B52: On-Prem | C52: Austin | D52: TX | E52: US | F52: T1 | G52: Non-Exempt | H52: Hourly | J52: 24.75 | K52: USD | L52: US Biweekly | M52: 45037 | N52: 46312 | P52: E0014 | Q52: Termination pending | R52: Employee | S52: 36 | T52: Full time | U52: =IF(AND(TRIM(E52)="US",TRIM(G52)="Non-Exempt"),"US Non-Exempt EEs","") -> US Non-Exempt EEs | V52: =IF(AND(TRIM(E52)="US",TRIM(G52)="Non-Exempt"),IF(TRIM(D52)="CA","US California Non-Exempt","US Non-California Non-Exempt"),"") -> US Non-California Non-Exempt | W52: =_xlfn.XLOOKUP(X52,ShiftCodes[Code],ShiftCodes[Work Schedule],"Unknown code") -> Shift D – Weekend (Fri–Sun 06:00–18:30) | X52: WKND | Y52: Term date = end of current pay period (US Biweekly Oct 4–17, 2026)
A53: E0048 | B53: Engineering | C53: San Francisco | D53: CA | E53: US | F53: IC2 | G53: Exempt | H53: Salary | I53: 144000 | K53: USD | L53: US Semi-monthly | M53: 45038 | P53: E0030 | Q53: Active | R53: Employee | S53: 40 | T53: Full time | U53: =IF(AND(TRIM(E53)="US",TRIM(G53)="Non-Exempt"),"US Non-Exempt EEs","") | V53: =IF(AND(TRIM(E53)="US",TRIM(G53)="Non-Exempt"),IF(TRIM(D53)="CA","US California Non-Exempt","US Non-California Non-Exempt"),"") | W53: =_xlfn.XLOOKUP(X53,ShiftCodes[Code],ShiftCodes[Work Schedule],"Unknown code") -> Standard (Mon–Fri 9:00–17:30) | X53: STD
A54: E0049 | B54: On-Prem | C54: San Jose | D54: CA | E54: US | F54: T2 | G54: Non-Exempt | H54: Hourly | J54: 40 | K54: USD | L54: US Biweekly | M54: 45048 | P54: E0044 | Q54: Active | R54: Employee | S54: 36 | T54: Full time | U54: =IF(AND(TRIM(E54)="US",TRIM(G54)="Non-Exempt"),"US Non-Exempt EEs","") -> US Non-Exempt EEs | V54: =IF(AND(TRIM(E54)="US",TRIM(G54)="Non-Exempt"),IF(TRIM(D54)="CA","US California Non-Exempt","US Non-California Non-Exempt"),"") -> US California Non-Exempt | W54: =_xlfn.XLOOKUP(X54,ShiftCodes[Code],ShiftCodes[Work Schedule],"Unknown code") -> Shift D – Weekend (Fri–Sun 06:00–18:30) | X54: WKND
A55: E0050 | B55: Engineering | C55: Bangalore | D55: Karnataka | E55: IN | F55: M5 | G55: Exempt | H55: Salary | I55: 9110000 | K55: INR | L55: India Monthly | M55: 45054 | P55: E0007 | Q55: Active | R55: Employee | S55: 40 | T55: Full time | U55: =IF(AND(TRIM(E55)="US",TRIM(G55)="Non-Exempt"),"US Non-Exempt EEs","") | V55: =IF(AND(TRIM(E55)="US",TRIM(G55)="Non-Exempt"),IF(TRIM(D55)="CA","US California Non-Exempt","US Non-California Non-Exempt"),"") | W55: =_xlfn.XLOOKUP(X55,ShiftCodes[Code],ShiftCodes[Work Schedule],"Unknown code") -> Standard (Mon–Fri 9:00–17:30) | X55: STD
A56: E0051 | B56: GPU Cloud | C56: Seattle | D56: WA | E56: US | F56: IC3 | G56: Exempt | H56: Salary | I56: 163000 | K56: USD | L56: US Semi-monthly | M56: 45087 | P56: E0032 | Q56: Active | R56: Employee | S56: 40 | T56: Full time | U56: =IF(AND(TRIM(E56)="US",TRIM(G56)="Non-Exempt"),"US Non-Exempt EEs","") | V56: =IF(AND(TRIM(E56)="US",TRIM(G56)="Non-Exempt"),IF(TRIM(D56)="CA","US California Non-Exempt","US Non-California Non-Exempt"),"") | W56: =_xlfn.XLOOKUP(X56,ShiftCodes[Code],ShiftCodes[Work Schedule],"Unknown code") -> Standard (Mon–Fri 9:00–17:30) | X56: STD
A57: E0052 | B57: G&A | C57: Bangalore | D57: Karnataka | E57: IN | F57: M4 | G57: Exempt | H57: Salary | I57: 6170000 | K57: INR | L57: India Monthly | M57: 45095 | P57: E0037 | Q57: Active | R57: Employee | S57: 40 | T57: Full time | U57: =IF(AND(TRIM(E57)="US",TRIM(G57)="Non-Exempt"),"US Non-Exempt EEs","") | V57: =IF(AND(TRIM(E57)="US",TRIM(G57)="Non-Exempt"),IF(TRIM(D57)="CA","US California Non-Exempt","US Non-California Non-Exempt"),"") | W57: =_xlfn.XLOOKUP(X57,ShiftCodes[Code],ShiftCodes[Work Schedule],"Unknown code") -> Standard (Mon–Fri 9:00–17:30) | X57: STD
A58: E0053 | B58: GPU Cloud | C58: San Francisco | D58: CA | E58: US | F58: IC1 | G58: Exempt | H58: Salary | I58: 101000 | K58: USD | L58: US Semi-monthly | M58: 45108 | P58: E0027 | Q58: Active | R58: Employee | S58: 40 | T58: Full time | U58: =IF(AND(TRIM(E58)="US",TRIM(G58)="Non-Exempt"),"US Non-Exempt EEs","") | V58: =IF(AND(TRIM(E58)="US",TRIM(G58)="Non-Exempt"),IF(TRIM(D58)="CA","US California Non-Exempt","US Non-California Non-Exempt"),"") | W58: =_xlfn.XLOOKUP(X58,ShiftCodes[Code],ShiftCodes[Work Schedule],"Unknown code") -> Standard (Mon–Fri 9:00–17:30) | X58: STD
A59: E0054 | B59: G&A | C59: Remote-US | D59: CA | E59: US | F59: IC2 | G59: Exempt | H59: Salary | I59: 105000 | K59: USD | L59: US Semi-monthly | M59: 45126 | P59: E0042 | Q59: Active | R59: Employee | S59: 40 | T59: Full time | U59: =IF(AND(TRIM(E59)="US",TRIM(G59)="Non-Exempt"),"US Non-Exempt EEs","") | V59: =IF(AND(TRIM(E59)="US",TRIM(G59)="Non-Exempt"),IF(TRIM(D59)="CA","US California Non-Exempt","US Non-California Non-Exempt"),"") | W59: =_xlfn.XLOOKUP(X59,ShiftCodes[Code],ShiftCodes[Work Schedule],"Unknown code") -> Standard (Mon–Fri 9:00–17:30) | X59: STD
A60: E0055 | B60: GPU Cloud | C60: San Francisco | D60: CA | E60: US | F60: IC2 | G60: Exempt | H60: Salary | I60: 128000 | K60: USD | L60: US Semi-monthly | M60: 45127 | P60: E0027 | Q60: Active | R60: Employee | S60: 40 | T60: Full time | U60: =IF(AND(TRIM(E60)="US",TRIM(G60)="Non-Exempt"),"US Non-Exempt EEs","") | V60: =IF(AND(TRIM(E60)="US",TRIM(G60)="Non-Exempt"),IF(TRIM(D60)="CA","US California Non-Exempt","US Non-California Non-Exempt"),"") | W60: =_xlfn.XLOOKUP(X60,ShiftCodes[Code],ShiftCodes[Work Schedule],"Unknown code") -> Standard (Mon–Fri 9:00–17:30) | X60: STD
A61: E0056 | B61: GPU Cloud | C61: San Francisco | D61: CA | E61: US | F61: M4 | G61: Exempt | H61: Salary | I61: 241000 | K61: USD | L61: US Semi-monthly | M61: 45153 | P61: E0001 | Q61: Active | R61: Employee | S61: 40 | T61: Full time | U61: =IF(AND(TRIM(E61)="US",TRIM(G61)="Non-Exempt"),"US Non-Exempt EEs","") | V61: =IF(AND(TRIM(E61)="US",TRIM(G61)="Non-Exempt"),IF(TRIM(D61)="CA","US California Non-Exempt","US Non-California Non-Exempt"),"") | W61: =_xlfn.XLOOKUP(X61,ShiftCodes[Code],ShiftCodes[Work Schedule],"Unknown code") -> Standard (Mon–Fri 9:00–17:30) | X61: STD
A62: E0057 | B62: On-Prem | C62: San Jose | D62: CA | E62: US | F62: T3 | G62: Non-Exempt | H62: Hourly | J62: 43.5 | K62: USD | L62: US Biweekly | M62: 45153 | N62: 46312 | P62: E0044 | Q62: Termination pending | R62: Employee | S62: 36 | T62: Full time | U62: =IF(AND(TRIM(E62)="US",TRIM(G62)="Non-Exempt"),"US Non-Exempt EEs","") -> US Non-Exempt EEs | V62: =IF(AND(TRIM(E62)="US",TRIM(G62)="Non-Exempt"),IF(TRIM(D62)="CA","US California Non-Exempt","US Non-California Non-Exempt"),"") -> US California Non-Exempt | W62: =_xlfn.XLOOKUP(X62,ShiftCodes[Code],ShiftCodes[Work Schedule],"Unknown code") -> Shift D – Weekend (Fri–Sun 06:00–18:30) | X62: WKND | Y62: Term date = end of current pay period (US Biweekly Oct 4–17, 2026)
A63: E0058 | B63: On-Prem | C63: Austin | D63: TX | E63: US | F63: M4 | G63: Exempt | H63: Salary | I63: 218000 | K63: USD | L63: US Semi-monthly | M63: 45159 | P63: E0013 | Q63: Active | R63: Employee | S63: 40 | T63: Full time | U63: =IF(AND(TRIM(E63)="US",TRIM(G63)="Non-Exempt"),"US Non-Exempt EEs","") | V63: =IF(AND(TRIM(E63)="US",TRIM(G63)="Non-Exempt"),IF(TRIM(D63)="CA","US California Non-Exempt","US Non-California Non-Exempt"),"") | W63: =_xlfn.XLOOKUP(X63,ShiftCodes[Code],ShiftCodes[Work Schedule],"Unknown code") -> Standard (Mon–Fri 9:00–17:30) | X63: STD
A64: E0059 | B64: Engineering | C64: London | D64: UK | E64: UK | F64: M4 | G64: Exempt | H64: Salary | I64: 113000 | K64: GBP | L64: UK Monthly | M64: 45164 | P64: E0024 | Q64: Active | R64: Employee | S64: 37.5 | T64: Full time | U64: =IF(AND(TRIM(E64)="US",TRIM(G64)="Non-Exempt"),"US Non-Exempt EEs","") | V64: =IF(AND(TRIM(E64)="US",TRIM(G64)="Non-Exempt"),IF(TRIM(D64)="CA","US California Non-Exempt","US Non-California Non-Exempt"),"") | W64: =_xlfn.XLOOKUP(X64,ShiftCodes[Code],ShiftCodes[Work Schedule],"Unknown code") -> Standard (Mon–Fri 9:00–17:30) | X64: STD
A65: E0060 | B65: GPU Cloud | C65: Remote-US | D65: NY | E65: US | F65: M4 | G65: Exempt | H65: Salary | I65: 210000 | K65: USD | L65: US Semi-monthly | M65: 45168 | P65: E0003 | Q65: Active | R65: Employee | S65: 40 | T65: Full time | U65: =IF(AND(TRIM(E65)="US",TRIM(G65)="Non-Exempt"),"US Non-Exempt EEs","") | V65: =IF(AND(TRIM(E65)="US",TRIM(G65)="Non-Exempt"),IF(TRIM(D65)="CA","US California Non-Exempt","US Non-California Non-Exempt"),"") | W65: =_xlfn.XLOOKUP(X65,ShiftCodes[Code],ShiftCodes[Work Schedule],"Unknown code") -> Standard (Mon–Fri 9:00–17:30) | X65: STD
A66: E0061 | B66: Engineering | C66: Seattle | D66: WA | E66: US | F66: M4 | G66: Exempt | H66: Salary | I66: 230000 | K66: USD | L66: US Semi-monthly | M66: 45177 | P66: E0033 | Q66: Active | R66: Employee | S66: 40 | T66: Full time | U66: =IF(AND(TRIM(E66)="US",TRIM(G66)="Non-Exempt"),"US Non-Exempt EEs","") | V66: =IF(AND(TRIM(E66)="US",TRIM(G66)="Non-Exempt"),IF(TRIM(D66)="CA","US California Non-Exempt","US Non-California Non-Exempt"),"") | W66: =_xlfn.XLOOKUP(X66,ShiftCodes[Code],ShiftCodes[Work Schedule],"Unknown code") -> Standard (Mon–Fri 9:00–17:30) | X66: STD
A67: E0062 | B67: Engineering | C67: San Francisco | D67: CA | E67: US | F67: IC4 | G67: Exempt | H67: Salary | I67: 176000 | K67: USD | L67: US Semi-monthly | M67: 45179 | P67: E0030 | Q67: Active | R67: Employee | S67: 40 | T67: Full time | U67: =IF(AND(TRIM(E67)="US",TRIM(G67)="Non-Exempt"),"US Non-Exempt EEs","") | V67: =IF(AND(TRIM(E67)="US",TRIM(G67)="Non-Exempt"),IF(TRIM(D67)="CA","US California Non-Exempt","US Non-California Non-Exempt"),"") | W67: =_xlfn.XLOOKUP(X67,ShiftCodes[Code],ShiftCodes[Work Schedule],"Unknown code") -> Standard (Mon–Fri 9:00–17:30) | X67: STD
A68: E0063 | B68: G&A | C68: Remote-US | D68: GA | E68: US | F68: IC2 | G68: Exempt | H68: Salary | I68: 102000 | K68: USD | L68: US Semi-monthly | M68: 45189 | P68: E0042 | Q68: Active | R68: Employee | S68: 40 | T68: Full time | U68: =IF(AND(TRIM(E68)="US",TRIM(G68)="Non-Exempt"),"US Non-Exempt EEs","") | V68: =IF(AND(TRIM(E68)="US",TRIM(G68)="Non-Exempt"),IF(TRIM(D68)="CA","US California Non-Exempt","US Non-California Non-Exempt"),"") | W68: =_xlfn.XLOOKUP(X68,ShiftCodes[Code],ShiftCodes[Work Schedule],"Unknown code") -> Standard (Mon–Fri 9:00–17:30) | X68: STD
A69: E0064 | B69: G&A | C69: San Francisco | D69: CA | E69: US | F69: M4 | G69: Exempt | H69: Salary | I69: 192000 | K69: USD | L69: US Semi-monthly | M69: 45196 | P69: E0026 | Q69: Active | R69: Employee | S69: 40 | T69: Full time | U69: =IF(AND(TRIM(E69)="US",TRIM(G69)="Non-Exempt"),"US Non-Exempt EEs","") | V69: =IF(AND(TRIM(E69)="US",TRIM(G69)="Non-Exempt"),IF(TRIM(D69)="CA","US California Non-Exempt","US Non-California Non-Exempt"),"") | W69: =_xlfn.XLOOKUP(X69,ShiftCodes[Code],ShiftCodes[Work Schedule],"Unknown code") -> Standard (Mon–Fri 9:00–17:30) | X69: STD
A70: E0065 | B70: Engineering | C70: Seattle | D70: WA | E70: US | F70: M4 | G70: Exempt | H70: Salary | I70: 205000 | K70: USD | L70: US Semi-monthly | M70: 45201 | P70: E0024 | Q70: Active | R70: Employee | S70: 40 | T70: Full time | U70: =IF(AND(TRIM(E70)="US",TRIM(G70)="Non-Exempt"),"US Non-Exempt EEs","") | V70: =IF(AND(TRIM(E70)="US",TRIM(G70)="Non-Exempt"),IF(TRIM(D70)="CA","US California Non-Exempt","US Non-California Non-Exempt"),"") | W70: =_xlfn.XLOOKUP(X70,ShiftCodes[Code],ShiftCodes[Work Schedule],"Unknown code") -> Standard (Mon–Fri 9:00–17:30) | X70: STD
A71: E0066 | B71: GPU Cloud | C71: Remote-US | D71: IL | E71: US | F71: IC3 | G71: Exempt | H71: Salary | I71: 174000 | K71: USD | L71: US Semi-monthly | M71: 45211 | P71: E0060 | Q71: Active | R71: Employee | S71: 40 | T71: Full time | U71: =IF(AND(TRIM(E71)="US",TRIM(G71)="Non-Exempt"),"US Non-Exempt EEs","") | V71: =IF(AND(TRIM(E71)="US",TRIM(G71)="Non-Exempt"),IF(TRIM(D71)="CA","US California Non-Exempt","US Non-California Non-Exempt"),"") | W71: =_xlfn.XLOOKUP(X71,ShiftCodes[Code],ShiftCodes[Work Schedule],"Unknown code") -> Standard (Mon–Fri 9:00–17:30) | X71: STD
A72: E0067 | B72: Engineering | C72: Seattle | D72: WA | E72: US | F72: IC4 | G72: Exempt | H72: Salary | I72: 198000 | K72: USD | L72: US Semi-monthly | M72: 45213 | P72: E0065 | Q72: Active | R72: Employee | S72: 40 | T72: Full time | U72: =IF(AND(TRIM(E72)="US",TRIM(G72)="Non-Exempt"),"US Non-Exempt EEs","") | V72: =IF(AND(TRIM(E72)="US",TRIM(G72)="Non-Exempt"),IF(TRIM(D72)="CA","US California Non-Exempt","US Non-California Non-Exempt"),"") | W72: =_xlfn.XLOOKUP(X72,ShiftCodes[Code],ShiftCodes[Work Schedule],"Unknown code") -> Standard (Mon–Fri 9:00–17:30) | X72: STD
A73: E0068 | B73: G&A | C73: London | D73: UK | E73: UK | F73: M4 | G73: Exempt | H73: Salary | I73: 108000 | K73: GBP | L73: UK Monthly | M73: 45219 | P73: E0026 | Q73: Active | R73: Employee | S73: 37.5 | T73: Full time | U73: =IF(AND(TRIM(E73)="US",TRIM(G73)="Non-Exempt"),"US Non-Exempt EEs","") | V73: =IF(AND(TRIM(E73)="US",TRIM(G73)="Non-Exempt"),IF(TRIM(D73)="CA","US California Non-Exempt","US Non-California Non-Exempt"),"") | W73: =_xlfn.XLOOKUP(X73,ShiftCodes[Code],ShiftCodes[Work Schedule],"Unknown code") -> Standard (Mon–Fri 9:00–17:30) | X73: STD
A74: E0069 | B74: On-Prem | C74: Austin | D74: TX | E74: US | F74: IC3 | G74: Exempt | H74: Salary | I74: 158000 | K74: USD | L74: US Semi-monthly | M74: 45240 | P74: E0058 | Q74: Active | R74: Employee | S74: 40 | T74: Full time | U74: =IF(AND(TRIM(E74)="US",TRIM(G74)="Non-Exempt"),"US Non-Exempt EEs","") | V74: =IF(AND(TRIM(E74)="US",TRIM(G74)="Non-Exempt"),IF(TRIM(D74)="CA","US California Non-Exempt","US Non-California Non-Exempt"),"") | W74: =_xlfn.XLOOKUP(X74,ShiftCodes[Code],ShiftCodes[Work Schedule],"Unknown code") -> Standard (Mon–Fri 9:00–17:30) | X74: STD
A75: E0070 | B75: Engineering | C75: London | D75: UK | E75: UK | F75: IC2 | G75: Exempt | H75: Salary | I75: 73000 | K75: GBP | L75: UK Monthly | M75: 45247 | O75: 46314 | P75: E0059 | Q75: On Leave(unpaid) | R75: Employee | S75: 37.5 | T75: Full time | U75: =IF(AND(TRIM(E75)="US",TRIM(G75)="Non-Exempt"),"US Non-Exempt EEs","") | V75: =IF(AND(TRIM(E75)="US",TRIM(G75)="Non-Exempt"),IF(TRIM(D75)="CA","US California Non-Exempt","US Non-California Non-Exempt"),"") | W75: =_xlfn.XLOOKUP(X75,ShiftCodes[Code],ShiftCodes[Work Schedule],"Unknown code") -> Standard (Mon–Fri 9:00–17:30) | X75: STD
A76: E0071 | B76: On-Prem | C76: San Jose | D76: CA | E76: US | F76: T1 | G76: Non-Exempt | H76: Hourly | J76: 30 | K76: USD | L76: US Biweekly | M76: 45253 | P76: E0019 | Q76: Active | R76: Employee | S76: 40 | T76: Full time | U76: =IF(AND(TRIM(E76)="US",TRIM(G76)="Non-Exempt"),"US Non-Exempt EEs","") -> US Non-Exempt EEs | V76: =IF(AND(TRIM(E76)="US",TRIM(G76)="Non-Exempt"),IF(TRIM(D76)="CA","US California Non-Exempt","US Non-California Non-Exempt"),"") -> US California Non-Exempt | W76: =_xlfn.XLOOKUP(X76,ShiftCodes[Code],ShiftCodes[Work Schedule],"Unknown code") -> Shift A – Day (Mon–Fri 06:00–14:30) | X76: DAY
A77: E0072 | B77: GPU Cloud | C77: San Francisco | D77: CA | E77: US | F77: IC3 | G77: Exempt | H77: Salary | I77: 142000 | K77: USD | L77: US Semi-monthly | M77: 45268 | P77: E0056 | Q77: Active | R77: Employee | S77: 40 | T77: Full time | U77: =IF(AND(TRIM(E77)="US",TRIM(G77)="Non-Exempt"),"US Non-Exempt EEs","") | V77: =IF(AND(TRIM(E77)="US",TRIM(G77)="Non-Exempt"),IF(TRIM(D77)="CA","US California Non-Exempt","US Non-California Non-Exempt"),"") | W77: =_xlfn.XLOOKUP(X77,ShiftCodes[Code],ShiftCodes[Work Schedule],"Unknown code") -> Standard (Mon–Fri 9:00–17:30) | X77: STD
A78: E0073 | B78: On-Prem | C78: Austin | D78: TX | E78: US | F78: T3 | G78: Non-Exempt | H78: Hourly | J78: 42.5 | K78: USD | L78: US Biweekly | M78: 45276 | P78: E0014 | Q78: Active | R78: Employee | S78: 24 | T78: Part time | U78: =IF(AND(TRIM(E78)="US",TRIM(G78)="Non-Exempt"),"US Non-Exempt EEs","") -> US Non-Exempt EEs | V78: =IF(AND(TRIM(E78)="US",TRIM(G78)="Non-Exempt"),IF(TRIM(D78)="CA","US California Non-Exempt","US Non-California Non-Exempt"),"") -> US Non-California Non-Exempt | W78: =_xlfn.XLOOKUP(X78,ShiftCodes[Code],ShiftCodes[Work Schedule],"Unknown code") -> Part-time – Day (Mon/Wed/Fri 06:00–14:30) | X78: PT
A79: E0074 | B79: On-Prem | C79: San Jose | D79: CA | E79: US | F79: T2 | G79: Non-Exempt | H79: Hourly | J79: 36.5 | K79: USD | L79: US Biweekly | M79: 45282 | P79: E0044 | Q79: Active | R79: Employee | S79: 40 | T79: Full time | U79: =IF(AND(TRIM(E79)="US",TRIM(G79)="Non-Exempt"),"US Non-Exempt EEs","") -> US Non-Exempt EEs | V79: =IF(AND(TRIM(E79)="US",TRIM(G79)="Non-Exempt"),IF(TRIM(D79)="CA","US California Non-Exempt","US Non-California Non-Exempt"),"") -> US California Non-Exempt | W79: =_xlfn.XLOOKUP(X79,ShiftCodes[Code],ShiftCodes[Work Schedule],"Unknown code") -> Shift B – Swing (Mon–Fri 14:00–22:30) | X79: SWNG
A80: E0075 | B80: G&A | C80: San Francisco | D80: CA | E80: US | F80: IC4 | G80: Exempt | H80: Salary | I80: 152000 | K80: USD | L80: US Semi-monthly | M80: 45285 | P80: E0064 | Q80: Active | R80: Employee | S80: 40 | T80: Full time | U80: =IF(AND(TRIM(E80)="US",TRIM(G80)="Non-Exempt"),"US Non-Exempt EEs","") | V80: =IF(AND(TRIM(E80)="US",TRIM(G80)="Non-Exempt"),IF(TRIM(D80)="CA","US California Non-Exempt","US Non-California Non-Exempt"),"") | W80: =_xlfn.XLOOKUP(X80,ShiftCodes[Code],ShiftCodes[Work Schedule],"Unknown code") -> Standard (Mon–Fri 9:00–17:30) | X80: STD
A81: E0076 | B81: Engineering | C81: Seattle | D81: WA | E81: US | F81: IC3 | G81: Exempt | H81: Salary | I81: 168000 | K81: USD | L81: US Semi-monthly | M81: 45289 | P81: E0065 | Q81: Active | R81: Employee | S81: 40 | T81: Full time | U81: =IF(AND(TRIM(E81)="US",TRIM(G81)="Non-Exempt"),"US Non-Exempt EEs","") | V81: =IF(AND(TRIM(E81)="US",TRIM(G81)="Non-Exempt"),IF(TRIM(D81)="CA","US California Non-Exempt","US Non-California Non-Exempt"),"") | W81: =_xlfn.XLOOKUP(X81,ShiftCodes[Code],ShiftCodes[Work Schedule],"Unknown code") -> Standard (Mon–Fri 9:00–17:30) | X81: STD
A82: E0077 | B82: On-Prem | C82: San Jose | D82: CA | E82: US | F82: M4 | G82: Exempt | H82: Salary | I82: 224000 | K82: USD | L82: US Semi-monthly | M82: 45292 | P82: E0013 | Q82: Active | R82: Employee | S82: 40 | T82: Full time | U82: =IF(AND(TRIM(E82)="US",TRIM(G82)="Non-Exempt"),"US Non-Exempt EEs","") | V82: =IF(AND(TRIM(E82)="US",TRIM(G82)="Non-Exempt"),IF(TRIM(D82)="CA","US California Non-Exempt","US Non-California Non-Exempt"),"") | W82: =_xlfn.XLOOKUP(X82,ShiftCodes[Code],ShiftCodes[Work Schedule],"Unknown code") -> Standard (Mon–Fri 9:00–17:30) | X82: STD
A83: E0078 | B83: On-Prem | C83: San Jose | D83: CA | E83: US | F83: T1 | G83: Non-Exempt | H83: Hourly | J83: 31 | K83: USD | L83: US Biweekly | M83: 45293 | P83: E0044 | Q83: Active | R83: Employee | S83: 40 | T83: Full time | U83: =IF(AND(TRIM(E83)="US",TRIM(G83)="Non-Exempt"),"US Non-Exempt EEs","") -> US Non-Exempt EEs | V83: =IF(AND(TRIM(E83)="US",TRIM(G83)="Non-Exempt"),IF(TRIM(D83)="CA","US California Non-Exempt","US Non-California Non-Exempt"),"") -> US California Non-Exempt | W83: =_xlfn.XLOOKUP(X83,ShiftCodes[Code],ShiftCodes[Work Schedule],"Unknown code") -> Shift A – Day (Mon–Fri 06:00–14:30) | X83: DAY
A84: E0079 | B84: On-Prem | C84: Austin | D84: TX | E84: US | F84: M4 | G84: Exempt | H84: Salary | I84: 244000 | K84: USD | L84: US Semi-monthly | M84: 45294 | P84: E0011 | Q84: Active | R84: Employee | S84: 40 | T84: Full time | U84: =IF(AND(TRIM(E84)="US",TRIM(G84)="Non-Exempt"),"US Non-Exempt EEs","") | V84: =IF(AND(TRIM(E84)="US",TRIM(G84)="Non-Exempt"),IF(TRIM(D84)="CA","US California Non-Exempt","US Non-California Non-Exempt"),"") | W84: =_xlfn.XLOOKUP(X84,ShiftCodes[Code],ShiftCodes[Work Schedule],"Unknown code") -> Standard (Mon–Fri 9:00–17:30) | X84: STD
A85: E0080 | B85: GPU Cloud | C85: Seattle | D85: WA | E85: US | F85: IC4 | G85: Exempt | H85: Salary | I85: 189000 | K85: USD | L85: US Semi-monthly | M85: 45295 | P85: E0032 | Q85: Active | R85: Employee | S85: 40 | T85: Full time | U85: =IF(AND(TRIM(E85)="US",TRIM(G85)="Non-Exempt"),"US Non-Exempt EEs","") | V85: =IF(AND(TRIM(E85)="US",TRIM(G85)="Non-Exempt"),IF(TRIM(D85)="CA","US California Non-Exempt","US Non-California Non-Exempt"),"") | W85: =_xlfn.XLOOKUP(X85,ShiftCodes[Code],ShiftCodes[Work Schedule],"Unknown code") -> Standard (Mon–Fri 9:00–17:30) | X85: STD
A86: E0081 | B86: Engineering | C86: San Francisco | D86: CA | E86: US | F86: M4 | G86: Exempt | H86: Salary | I86: 234000 | K86: USD | L86: US Semi-monthly | M86: 45297 | P86: E0050 | Q86: Active | R86: Employee | S86: 40 | T86: Full time | U86: =IF(AND(TRIM(E86)="US",TRIM(G86)="Non-Exempt"),"US Non-Exempt EEs","") | V86: =IF(AND(TRIM(E86)="US",TRIM(G86)="Non-Exempt"),IF(TRIM(D86)="CA","US California Non-Exempt","US Non-California Non-Exempt"),"") | W86: =_xlfn.XLOOKUP(X86,ShiftCodes[Code],ShiftCodes[Work Schedule],"Unknown code") -> Standard (Mon–Fri 9:00–17:30) | X86: STD
A87: E0082 | B87: On-Prem | C87: San Jose | D87: CA | E87: US | F87: IC3 | G87: Exempt | H87: Salary | I87: 157000 | K87: USD | L87: US Semi-monthly | M87: 45307 | P87: E0077 | Q87: Active | R87: Employee | S87: 40 | T87: Full time | U87: =IF(AND(TRIM(E87)="US",TRIM(G87)="Non-Exempt"),"US Non-Exempt EEs","") | V87: =IF(AND(TRIM(E87)="US",TRIM(G87)="Non-Exempt"),IF(TRIM(D87)="CA","US California Non-Exempt","US Non-California Non-Exempt"),"") | W87: =_xlfn.XLOOKUP(X87,ShiftCodes[Code],ShiftCodes[Work Schedule],"Unknown code") -> Standard (Mon–Fri 9:00–17:30) | X87: STD
A88: E0083 | B88: GPU Cloud | C88: Remote-US | D88: WA | E88: US | F88: IC5 | G88: Exempt | H88: Salary | I88: 233000 | K88: USD | L88: US Semi-monthly | M88: 45320 | P88: E0060 | Q88: Active | R88: Employee | S88: 40 | T88: Full time | U88: =IF(AND(TRIM(E88)="US",TRIM(G88)="Non-Exempt"),"US Non-Exempt EEs","") | V88: =IF(AND(TRIM(E88)="US",TRIM(G88)="Non-Exempt"),IF(TRIM(D88)="CA","US California Non-Exempt","US Non-California Non-Exempt"),"") | W88: =_xlfn.XLOOKUP(X88,ShiftCodes[Code],ShiftCodes[Work Schedule],"Unknown code") -> Standard (Mon–Fri 9:00–17:30) | X88: STD
A89: E0084 | B89: G&A | C89: London | D89: UK | E89: UK | F89: IC3 | G89: Exempt | H89: Salary | I89: 88000 | K89: GBP | L89: UK Monthly | M89: 45322 | P89: E0068 | Q89: Active | R89: Employee | S89: 37.5 | T89: Full time | U89: =IF(AND(TRIM(E89)="US",TRIM(G89)="Non-Exempt"),"US Non-Exempt EEs","") | V89: =IF(AND(TRIM(E89)="US",TRIM(G89)="Non-Exempt"),IF(TRIM(D89)="CA","US California Non-Exempt","US Non-California Non-Exempt"),"") | W89: =_xlfn.XLOOKUP(X89,ShiftCodes[Code],ShiftCodes[Work Schedule],"Unknown code") -> Standard (Mon–Fri 9:00–17:30) | X89: STD
A90: E0085 | B90: Engineering | C90: San Francisco | D90: CA | E90: US | F90: M4 | G90: Exempt | H90: Salary | I90: 215000 | K90: USD | L90: US Semi-monthly | M90: 45323 | P90: E0033 | Q90: Active | R90: Employee | S90: 40 | T90: Full time | U90: =IF(AND(TRIM(E90)="US",TRIM(G90)="Non-Exempt"),"US Non-Exempt EEs","") | V90: =IF(AND(TRIM(E90)="US",TRIM(G90)="Non-Exempt"),IF(TRIM(D90)="CA","US California Non-Exempt","US Non-California Non-Exempt"),"") | W90: =_xlfn.XLOOKUP(X90,ShiftCodes[Code],ShiftCodes[Work Schedule],"Unknown code") -> Standard (Mon–Fri 9:00–17:30) | X90: STD
A91: E0086 | B91: Engineering | C91: Bangalore | D91: Karnataka | E91: IN | F91: M4 | G91: Exempt | H91: Salary | I91: 7300000 | K91: INR | L91: India Monthly | M91: 45331 | P91: E0050 | Q91: Active | R91: Employee | S91: 40 | T91: Full time | U91: =IF(AND(TRIM(E91)="US",TRIM(G91)="Non-Exempt"),"US Non-Exempt EEs","") | V91: =IF(AND(TRIM(E91)="US",TRIM(G91)="Non-Exempt"),IF(TRIM(D91)="CA","US California Non-Exempt","US Non-California Non-Exempt"),"") | W91: =_xlfn.XLOOKUP(X91,ShiftCodes[Code],ShiftCodes[Work Schedule],"Unknown code") -> Standard (Mon–Fri 9:00–17:30) | X91: STD
A92: E0087 | B92: GPU Cloud | C92: San Francisco | D92: CA | E92: US | F92: IC5 | G92: Exempt | H92: Salary | I92: 217000 | K92: USD | L92: US Semi-monthly | M92: 45334 | P92: E0056 | Q92: Active | R92: Employee | S92: 40 | T92: Full time | U92: =IF(AND(TRIM(E92)="US",TRIM(G92)="Non-Exempt"),"US Non-Exempt EEs","") | V92: =IF(AND(TRIM(E92)="US",TRIM(G92)="Non-Exempt"),IF(TRIM(D92)="CA","US California Non-Exempt","US Non-California Non-Exempt"),"") | W92: =_xlfn.XLOOKUP(X92,ShiftCodes[Code],ShiftCodes[Work Schedule],"Unknown code") -> Standard (Mon–Fri 9:00–17:30) | X92: STD
A93: E0088 | B93: On-Prem | C93: San Jose | D93: CA | E93: US | F93: T2 | G93: Non-Exempt | H93: Hourly | J93: 39 | K93: USD | L93: US Biweekly | M93: 45343 | P93: E0019 | Q93: Active | R93: Employee | S93: 36 | T93: Full time | U93: =IF(AND(TRIM(E93)="US",TRIM(G93)="Non-Exempt"),"US Non-Exempt EEs","") -> US Non-Exempt EEs | V93: =IF(AND(TRIM(E93)="US",TRIM(G93)="Non-Exempt"),IF(TRIM(D93)="CA","US California Non-Exempt","US Non-California Non-Exempt"),"") -> US California Non-Exempt | W93: =_xlfn.XLOOKUP(X93,ShiftCodes[Code],ShiftCodes[Work Schedule],"Unknown code") -> Shift D – Weekend (Fri–Sun 06:00–18:30) | X93: WKND
A94: E0089 | B94: On-Prem | C94: San Jose | D94: CA | E94: US | F94: IC2 | G94: Exempt | H94: Salary | I94: 115000 | K94: USD | L94: US Semi-monthly | M94: 45354 | P94: E0077 | Q94: Active | R94: Employee | S94: 40 | T94: Full time | U94: =IF(AND(TRIM(E94)="US",TRIM(G94)="Non-Exempt"),"US Non-Exempt EEs","") | V94: =IF(AND(TRIM(E94)="US",TRIM(G94)="Non-Exempt"),IF(TRIM(D94)="CA","US California Non-Exempt","US Non-California Non-Exempt"),"") | W94: =_xlfn.XLOOKUP(X94,ShiftCodes[Code],ShiftCodes[Work Schedule],"Unknown code") -> Standard (Mon–Fri 9:00–17:30) | X94: STD
A95: E0090 | B95: On-Prem | C95: San Jose | D95: CA | E95: US | F95: M4 | G95: Exempt | H95: Salary | I95: 205000 | K95: USD | L95: US Semi-monthly | M95: 45355 | P95: E0013 | Q95: Active | R95: Employee | S95: 40 | T95: Full time | U95: =IF(AND(TRIM(E95)="US",TRIM(G95)="Non-Exempt"),"US Non-Exempt EEs","") | V95: =IF(AND(TRIM(E95)="US",TRIM(G95)="Non-Exempt"),IF(TRIM(D95)="CA","US California Non-Exempt","US Non-California Non-Exempt"),"") | W95: =_xlfn.XLOOKUP(X95,ShiftCodes[Code],ShiftCodes[Work Schedule],"Unknown code") -> Standard (Mon–Fri 9:00–17:30) | X95: STD
A96: E0091 | B96: Engineering | C96: Bangalore | D96: Karnataka | E96: IN | F96: IC4 | G96: Exempt | H96: Salary | I96: 5500000 | K96: INR | L96: India Monthly | M96: 45357 | P96: E0086 | Q96: Active | R96: Employee | S96: 40 | T96: Full time | U96: =IF(AND(TRIM(E96)="US",TRIM(G96)="Non-Exempt"),"US Non-Exempt EEs","") | V96: =IF(AND(TRIM(E96)="US",TRIM(G96)="Non-Exempt"),IF(TRIM(D96)="CA","US California Non-Exempt","US Non-California Non-Exempt"),"") | W96: =_xlfn.XLOOKUP(X96,ShiftCodes[Code],ShiftCodes[Work Schedule],"Unknown code") -> Standard (Mon–Fri 9:00–17:30) | X96: STD
A97: E0092 | B97: GPU Cloud | C97: Remote-US | D97: IL | E97: US | F97: IC4 | G97: Exempt | H97: Salary | I97: 202000 | K97: USD | L97: US Semi-monthly | M97: 45360 | P97: E0056 | Q97: Active | R97: Employee | S97: 40 | T97: Full time | U97: =IF(AND(TRIM(E97)="US",TRIM(G97)="Non-Exempt"),"US Non-Exempt EEs","") | V97: =IF(AND(TRIM(E97)="US",TRIM(G97)="Non-Exempt"),IF(TRIM(D97)="CA","US California Non-Exempt","US Non-California Non-Exempt"),"") | W97: =_xlfn.XLOOKUP(X97,ShiftCodes[Code],ShiftCodes[Work Schedule],"Unknown code") -> Standard (Mon–Fri 9:00–17:30) | X97: STD
A98: E0093 | B98: Engineering | C98: Seattle | D98: WA | E98: US | F98: IC3 | G98: Exempt | H98: Salary | I98: 167000 | K98: USD | L98: US Semi-monthly | M98: 45363 | P98: E0065 | Q98: Active | R98: Employee | S98: 40 | T98: Full time | U98: =IF(AND(TRIM(E98)="US",TRIM(G98)="Non-Exempt"),"US Non-Exempt EEs","") | V98: =IF(AND(TRIM(E98)="US",TRIM(G98)="Non-Exempt"),IF(TRIM(D98)="CA","US California Non-Exempt","US Non-California Non-Exempt"),"") | W98: =_xlfn.XLOOKUP(X98,ShiftCodes[Code],ShiftCodes[Work Schedule],"Unknown code") -> Standard (Mon–Fri 9:00–17:30) | X98: STD
A99: E0094 | B99: G&A | C99: Bangalore | D99: Karnataka | E99: IN | F99: IC2 | G99: Exempt | H99: Salary | I99: 2260000 | K99: INR | L99: India Monthly | M99: 45363 | P99: E0052 | Q99: Active | R99: Employee | S99: 40 | T99: Full time | U99: =IF(AND(TRIM(E99)="US",TRIM(G99)="Non-Exempt"),"US Non-Exempt EEs","") | V99: =IF(AND(TRIM(E99)="US",TRIM(G99)="Non-Exempt"),IF(TRIM(D99)="CA","US California Non-Exempt","US Non-California Non-Exempt"),"") | W99: =_xlfn.XLOOKUP(X99,ShiftCodes[Code],ShiftCodes[Work Schedule],"Unknown code") -> Standard (Mon–Fri 9:00–17:30) | X99: STD
A100: E0095 | B100: GPU Cloud | C100: London | D100: UK | E100: UK | F100: M4 | G100: Exempt | H100: Salary | I100: 133000 | K100: GBP | L100: UK Monthly | M100: 45365 | P100: E0003 | Q100: Active | R100: Employee | S100: 37.5 | T100: Full time | U100: =IF(AND(TRIM(E100)="US",TRIM(G100)="Non-Exempt"),"US Non-Exempt EEs","") | V100: =IF(AND(TRIM(E100)="US",TRIM(G100)="Non-Exempt"),IF(TRIM(D100)="CA","US California Non-Exempt","US Non-California Non-Exempt"),"") | W100: =_xlfn.XLOOKUP(X100,ShiftCodes[Code],ShiftCodes[Work Schedule],"Unknown code") -> Standard (Mon–Fri 9:00–17:30) | X100: STD
...

Sheet absence balance
A1: Employee ID | B1: Plan | C1: Balance (hours or days) | D1: Last Accrual Date | E1: Notes | F1: Unit | H1: Balance As-Of Dates
A2: E0001 | B2: US Flexible PTO | C2: n/a (unlimited) | D2: {=IF(F2="n/a","—",IF(_xlfn.XLOOKUP(TRIM(SUBSTITUTE(A2,_xlfn.UNICHAR(160)," ")),TRIM(SUBSTITUTE('worker file'!$A$2:$A$406,_xlfn.UNICHAR(160)," ")),'worker file'!$L$2:$L$406,"")="US Biweekly",$I$3,$I$2))} -> — | F2: n/a | H2: Monthly & semi-monthly pay groups | I2: 46295
A3: E0021 | B3: US Hourly Vacation | C3: 46.5 | D3: {=IF(F3="n/a","—",IF(_xlfn.XLOOKUP(TRIM(SUBSTITUTE(A3,_xlfn.UNICHAR(160)," ")),TRIM(SUBSTITUTE('worker file'!$A$2:$A$406,_xlfn.UNICHAR(160)," ")),'worker file'!$L$2:$L$406,"")="US Biweekly",$I$3,$I$2))} -> 46298 | E3: Accrues per hour worked | F3: hrs | H3: US Biweekly (hourly US) | I3: 46298
A4: E0021 | B4: CA Paid Sick Leave | C4: 28 | D4: {=IF(F4="n/a","—",IF(_xlfn.XLOOKUP(TRIM(SUBSTITUTE(A4,_xlfn.UNICHAR(160)," ")),TRIM(SUBSTITUTE('worker file'!$A$2:$A$406,_xlfn.UNICHAR(160)," ")),'worker file'!$L$2:$L$406,"")="US Biweekly",$I$3,$I$2))} -> 46298 | F4: hrs
A5: E0006 | B5: UK Annual Leave | C5: 14.5 | D5: {=IF(F5="n/a","—",IF(_xlfn.XLOOKUP(TRIM(SUBSTITUTE(A5,_xlfn.UNICHAR(160)," ")),TRIM(SUBSTITUTE('worker file'!$A$2:$A$406,_xlfn.UNICHAR(160)," ")),'worker file'!$L$2:$L$406,"")="US Biweekly",$I$3,$I$2))} -> 46295 | E5: Holiday year Jan–Dec; Payout on termination | F5: days
A6: E0008 | B6: Canada Vacation | C6: 9 | D6: {=IF(F6="n/a","—",IF(_xlfn.XLOOKUP(TRIM(SUBSTITUTE(A6,_xlfn.UNICHAR(160)," ")),TRIM(SUBSTITUTE('worker file'!$A$2:$A$406,_xlfn.UNICHAR(160)," ")),'worker file'!$L$2:$L$406,"")="US Biweekly",$I$3,$I$2))} -> 46295 | E6: Ontario, 3 weeks/year | F6: days
A7: E0009 | B7: India Earned Leave | C7: 11 | D7: {=IF(F7="n/a","—",IF(_xlfn.XLOOKUP(TRIM(SUBSTITUTE(A7,_xlfn.UNICHAR(160)," ")),TRIM(SUBSTITUTE('worker file'!$A$2:$A$406,_xlfn.UNICHAR(160)," ")),'worker file'!$L$2:$L$406,"")="US Biweekly",$I$3,$I$2))} -> 46295 | E7: Karnataka S&E Act; Payout on termination | F7: days
A8: E0148 | B8: US Hourly Vacation | C8: 31 | D8: {=IF(F8="n/a","—",IF(_xlfn.XLOOKUP(TRIM(SUBSTITUTE(A8,_xlfn.UNICHAR(160)," ")),TRIM(SUBSTITUTE('worker file'!$A$2:$A$406,_xlfn.UNICHAR(160)," ")),'worker file'!$L$2:$L$406,"")="US Biweekly",$I$3,$I$2))} -> 46298 | E8: Payout on termination | F8: hrs
A9: E0148 | B9: CA Paid Sick Leave | D9: {=IF(F9="n/a","—",IF(_xlfn.XLOOKUP(TRIM(SUBSTITUTE(A9,_xlfn.UNICHAR(160)," ")),TRIM(SUBSTITUTE('worker file'!$A$2:$A$406,_xlfn.UNICHAR(160)," ")),'worker file'!$L$2:$L$406,"")="US Biweekly",$I$3,$I$2))} -> 46298 | E9: CA Labor Code 246; accrual cap 80 hrs; no payout on termination – balance needed | F9: hrs
A10: E0000 | B10: US Flexible PTO | C10: n/a (unlimited) | D10: {=IF(F10="n/a","—",IF(_xlfn.XLOOKUP(TRIM(SUBSTITUTE(A10,_xlfn.UNICHAR(160)," ")),TRIM(SUBSTITUTE('worker file'!$A$2:$A$406,_xlfn.UNICHAR(160)," ")),'worker file'!$L$2:$L$406,"")="US Biweekly",$I$3,$I$2))} -> — | E10: No accrual | F10: n/a
A11: E0000 | B11: CA Paid Sick Leave | C11: 67.75 | D11: {=IF(F11="n/a","—",IF(_xlfn.XLOOKUP(TRIM(SUBSTITUTE(A11,_xlfn.UNICHAR(160)," ")),TRIM(SUBSTITUTE('worker file'!$A$2:$A$406,_xlfn.UNICHAR(160)," ")),'worker file'!$L$2:$L$406,"")="US Biweekly",$I$3,$I$2))} -> 46295 | E11: CA Labor Code 246; accrual cap 80 hrs | F11: hrs
A12: E0002 | B12: US Flexible PTO | C12: n/a (unlimited) | D12: {=IF(F12="n/a","—",IF(_xlfn.XLOOKUP(TRIM(SUBSTITUTE(A12,_xlfn.UNICHAR(160)," ")),TRIM(SUBSTITUTE('worker file'!$A$2:$A$406,_xlfn.UNICHAR(160)," ")),'worker file'!$L$2:$L$406,"")="US Biweekly",$I$3,$I$2))} -> — | E12: No accrual | F12: n/a
A13: E0002 | B13: CA Paid Sick Leave | C13: 24.25 | D13: {=IF(F13="n/a","—",IF(_xlfn.XLOOKUP(TRIM(SUBSTITUTE(A13,_xlfn.UNICHAR(160)," ")),TRIM(SUBSTITUTE('worker file'!$A$2:$A$406,_xlfn.UNICHAR(160)," ")),'worker file'!$L$2:$L$406,"")="US Biweekly",$I$3,$I$2))} -> 46295 | E13: CA Labor Code 246; accrual cap 80 hrs | F13: hrs
A14: E0003 | B14: US Flexible PTO | C14: n/a (unlimited) | D14: {=IF(F14="n/a","—",IF(_xlfn.XLOOKUP(TRIM(SUBSTITUTE(A14,_xlfn.UNICHAR(160)," ")),TRIM(SUBSTITUTE('worker file'!$A$2:$A$406,_xlfn.UNICHAR(160)," ")),'worker file'!$L$2:$L$406,"")="US Biweekly",$I$3,$I$2))} -> — | E14: No accrual | F14: n/a
A15: E0004 | B15: US Flexible PTO | C15: n/a (unlimited) | D15: {=IF(F15="n/a","—",IF(_xlfn.XLOOKUP(TRIM(SUBSTITUTE(A15,_xlfn.UNICHAR(160)," ")),TRIM(SUBSTITUTE('worker file'!$A$2:$A$406,_xlfn.UNICHAR(160)," ")),'worker file'!$L$2:$L$406,"")="US Biweekly",$I$3,$I$2))} -> — | E15: No accrual | F15: n/a
A16: E0005 | B16: US Flexible PTO | C16: n/a (unlimited) | D16: {=IF(F16="n/a","—",IF(_xlfn.XLOOKUP(TRIM(SUBSTITUTE(A16,_xlfn.UNICHAR(160)," ")),TRIM(SUBSTITUTE('worker file'!$A$2:$A$406,_xlfn.UNICHAR(160)," ")),'worker file'!$L$2:$L$406,"")="US Biweekly",$I$3,$I$2))} -> — | E16: No accrual | F16: n/a
A17: E0005 | B17: CA Paid Sick Leave | C17: 63.5 | D17: {=IF(F17="n/a","—",IF(_xlfn.XLOOKUP(TRIM(SUBSTITUTE(A17,_xlfn.UNICHAR(160)," ")),TRIM(SUBSTITUTE('worker file'!$A$2:$A$406,_xlfn.UNICHAR(160)," ")),'worker file'!$L$2:$L$406,"")="US Biweekly",$I$3,$I$2))} -> 46295 | E17: CA Labor Code 246; accrual cap 80 hrs | F17: hrs
A18: E0007 | B18: US Flexible PTO | C18: n/a (unlimited) | D18: {=IF(F18="n/a","—",IF(_xlfn.XLOOKUP(TRIM(SUBSTITUTE(A18,_xlfn.UNICHAR(160)," ")),TRIM(SUBSTITUTE('worker file'!$A$2:$A$406,_xlfn.UNICHAR(160)," ")),'worker file'!$L$2:$L$406,"")="US Biweekly",$I$3,$I$2))} -> — | E18: No accrual | F18: n/a
A19: E0007 | B19: CA Paid Sick Leave | C19: 68 | D19: {=IF(F19="n/a","—",IF(_xlfn.XLOOKUP(TRIM(SUBSTITUTE(A19,_xlfn.UNICHAR(160)," ")),TRIM(SUBSTITUTE('worker file'!$A$2:$A$406,_xlfn.UNICHAR(160)," ")),'worker file'!$L$2:$L$406,"")="US Biweekly",$I$3,$I$2))} -> 46295 | E19: CA Labor Code 246; accrual cap 80 hrs | F19: hrs
A20: E0010 | B20: US Flexible PTO | C20: n/a (unlimited) | D20: {=IF(F20="n/a","—",IF(_xlfn.XLOOKUP(TRIM(SUBSTITUTE(A20,_xlfn.UNICHAR(160)," ")),TRIM(SUBSTITUTE('worker file'!$A$2:$A$406,_xlfn.UNICHAR(160)," ")),'worker file'!$L$2:$L$406,"")="US Biweekly",$I$3,$I$2))} -> — | E20: No accrual | F20: n/a
A21: E0010 | B21: CA Paid Sick Leave | C21: 61.75 | D21: {=IF(F21="n/a","—",IF(_xlfn.XLOOKUP(TRIM(SUBSTITUTE(A21,_xlfn.UNICHAR(160)," ")),TRIM(SUBSTITUTE('worker file'!$A$2:$A$406,_xlfn.UNICHAR(160)," ")),'worker file'!$L$2:$L$406,"")="US Biweekly",$I$3,$I$2))} -> 46295 | E21: CA Labor Code 246; accrual cap 80 hrs | F21: hrs
A22: E0011 | B22: US Flexible PTO | C22: n/a (unlimited) | D22: {=IF(F22="n/a","—",IF(_xlfn.XLOOKUP(TRIM(SUBSTITUTE(A22,_xlfn.UNICHAR(160)," ")),TRIM(SUBSTITUTE('worker file'!$A$2:$A$406,_xlfn.UNICHAR(160)," ")),'worker file'!$L$2:$L$406,"")="US Biweekly",$I$3,$I$2))} -> — | E22: No accrual | F22: n/a
A23: E0011 | B23: CA Paid Sick Leave | C23: 63 | D23: {=IF(F23="n/a","—",IF(_xlfn.XLOOKUP(TRIM(SUBSTITUTE(A23,_xlfn.UNICHAR(160)," ")),TRIM(SUBSTITUTE('worker file'!$A$2:$A$406,_xlfn.UNICHAR(160)," ")),'worker file'!$L$2:$L$406,"")="US Biweekly",$I$3,$I$2))} -> 46295 | E23: CA Labor Code 246; accrual cap 80 hrs | F23: hrs
A24: E0012 | B24: US Flexible PTO | C24: n/a (unlimited) | D24: {=IF(F24="n/a","—",IF(_xlfn.XLOOKUP(TRIM(SUBSTITUTE(A24,_xlfn.UNICHAR(160)," ")),TRIM(SUBSTITUTE('worker file'!$A$2:$A$406,_xlfn.UNICHAR(160)," ")),'worker file'!$L$2:$L$406,"")="US Biweekly",$I$3,$I$2))} -> — | E24: No accrual | F24: n/a
A25: E0012 | B25: CA Paid Sick Leave | C25: 54.25 | D25: {=IF(F25="n/a","—",IF(_xlfn.XLOOKUP(TRIM(SUBSTITUTE(A25,_xlfn.UNICHAR(160)," ")),TRIM(SUBSTITUTE('worker file'!$A$2:$A$406,_xlfn.UNICHAR(160)," ")),'worker file'!$L$2:$L$406,"")="US Biweekly",$I$3,$I$2))} -> 46295 | E25: CA Labor Code 246; accrual cap 80 hrs | F25: hrs
A26: E0013 | B26: US Flexible PTO | C26: n/a (unlimited) | D26: {=IF(F26="n/a","—",IF(_xlfn.XLOOKUP(TRIM(SUBSTITUTE(A26,_xlfn.UNICHAR(160)," ")),TRIM(SUBSTITUTE('worker file'!$A$2:$A$406,_xlfn.UNICHAR(160)," ")),'worker file'!$L$2:$L$406,"")="US Biweekly",$I$3,$I$2))} -> — | E26: No accrual | F26: n/a
A27: E0013 | B27: CA Paid Sick Leave | C27: 73.5 | D27: {=IF(F27="n/a","—",IF(_xlfn.XLOOKUP(TRIM(SUBSTITUTE(A27,_xlfn.UNICHAR(160)," ")),TRIM(SUBSTITUTE('worker file'!$A$2:$A$406,_xlfn.UNICHAR(160)," ")),'worker file'!$L$2:$L$406,"")="US Biweekly",$I$3,$I$2))} -> 46295 | E27: CA Labor Code 246; accrual cap 80 hrs | F27: hrs
A28: E0014 | B28: US Flexible PTO | C28: n/a (unlimited) | D28: {=IF(F28="n/a","—",IF(_xlfn.XLOOKUP(TRIM(SUBSTITUTE(A28,_xlfn.UNICHAR(160)," ")),TRIM(SUBSTITUTE('worker file'!$A$2:$A$406,_xlfn.UNICHAR(160)," ")),'worker file'!$L$2:$L$406,"")="US Biweekly",$I$3,$I$2))} -> — | E28: No accrual | F28: n/a
A29: E0015 | B29: US Hourly Vacation | C29: 120 | D29: {=IF(F29="n/a","—",IF(_xlfn.XLOOKUP(TRIM(SUBSTITUTE(A29,_xlfn.UNICHAR(160)," ")),TRIM(SUBSTITUTE('worker file'!$A$2:$A$406,_xlfn.UNICHAR(160)," ")),'worker file'!$L$2:$L$406,"")="US Biweekly",$I$3,$I$2))} -> 46298 | E29: Accrues per hour worked; cap 120 hrs | F29: hrs
A30: E0015 | B30: TX Hourly Sick (company) | C30: 6.5 | D30: {=IF(F30="n/a","—",IF(_xlfn.XLOOKUP(TRIM(SUBSTITUTE(A30,_xlfn.UNICHAR(160)," ")),TRIM(SUBSTITUTE('worker file'!$A$2:$A$406,_xlfn.UNICHAR(160)," ")),'worker file'!$L$2:$L$406,"")="US Biweekly",$I$3,$I$2))} -> 46298 | E30: Company policy; 40 hrs/yr | F30: hrs
A31: E0016 | B31: US Flexible PTO | C31: n/a (unlimited) | D31: {=IF(F31="n/a","—",IF(_xlfn.XLOOKUP(TRIM(SUBSTITUTE(A31,_xlfn.UNICHAR(160)," ")),TRIM(SUBSTITUTE('worker file'!$A$2:$A$406,_xlfn.UNICHAR(160)," ")),'worker file'!$L$2:$L$406,"")="US Biweekly",$I$3,$I$2))} -> — | E31: No accrual | F31: n/a
A32: E0017 | B32: US Flexible PTO | C32: n/a (unlimited) | D32: {=IF(F32="n/a","—",IF(_xlfn.XLOOKUP(TRIM(SUBSTITUTE(A32,_xlfn.UNICHAR(160)," ")),TRIM(SUBSTITUTE('worker file'!$A$2:$A$406,_xlfn.UNICHAR(160)," ")),'worker file'!$L$2:$L$406,"")="US Biweekly",$I$3,$I$2))} -> — | E32: No accrual | F32: n/a
A33: E0018 | B33: US Flexible PTO | C33: n/a (unlimited) | D33: {=IF(F33="n/a","—",IF(_xlfn.XLOOKUP(TRIM(SUBSTITUTE(A33,_xlfn.UNICHAR(160)," ")),TRIM(SUBSTITUTE('worker file'!$A$2:$A$406,_xlfn.UNICHAR(160)," ")),'worker file'!$L$2:$L$406,"")="US Biweekly",$I$3,$I$2))} -> — | E33: No accrual | F33: n/a
A34: E0018 | B34: NY Paid Sick Leave | C34: 47.25 | D34: {=IF(F34="n/a","—",IF(_xlfn.XLOOKUP(TRIM(SUBSTITUTE(A34,_xlfn.UNICHAR(160)," ")),TRIM(SUBSTITUTE('worker file'!$A$2:$A$406,_xlfn.UNICHAR(160)," ")),'worker file'!$L$2:$L$406,"")="US Biweekly",$I$3,$I$2))} -> 46295 | E34: NY Labor Law 196-b; 56 hrs/yr | F34: hrs
A35: E0019 | B35: US Flexible PTO | C35: n/a (unlimited) | D35: {=IF(F35="n/a","—",IF(_xlfn.XLOOKUP(TRIM(SUBSTITUTE(A35,_xlfn.UNICHAR(160)," ")),TRIM(SUBSTITUTE('worker file'!$A$2:$A$406,_xlfn.UNICHAR(160)," ")),'worker file'!$L$2:$L$406,"")="US Biweekly",$I$3,$I$2))} -> — | E35: No accrual | F35: n/a
A36: E0019 | B36: CA Paid Sick Leave | C36: 47.5 | D36: {=IF(F36="n/a","—",IF(_xlfn.XLOOKUP(TRIM(SUBSTITUTE(A36,_xlfn.UNICHAR(160)," ")),TRIM(SUBSTITUTE('worker file'!$A$2:$A$406,_xlfn.UNICHAR(160)," ")),'worker file'!$L$2:$L$406,"")="US Biweekly",$I$3,$I$2))} -> 46295 | E36: CA Labor Code 246; accrual cap 80 hrs | F36: hrs
A37: E0020 | B37: US Hourly Vacation | C37: 120 | D37: {=IF(F37="n/a","—",IF(_xlfn.XLOOKUP(TRIM(SUBSTITUTE(A37,_xlfn.UNICHAR(160)," ")),TRIM(SUBSTITUTE('worker file'!$A$2:$A$406,_xlfn.UNICHAR(160)," ")),'worker file'!$L$2:$L$406,"")="US Biweekly",$I$3,$I$2))} -> 46298 | E37: Accrues per hour worked; cap 120 hrs | F37: hrs
A38: E0020 | B38: CA Paid Sick Leave | C38: 31.75 | D38: {=IF(F38="n/a","—",IF(_xlfn.XLOOKUP(TRIM(SUBSTITUTE(A38,_xlfn.UNICHAR(160)," ")),TRIM(SUBSTITUTE('worker file'!$A$2:$A$406,_xlfn.UNICHAR(160)," ")),'worker file'!$L$2:$L$406,"")="US Biweekly",$I$3,$I$2))} -> 46298 | E38: CA Labor Code 246; accrual cap 80 hrs | F38: hrs
A39: E0022 | B39: US Hourly Vacation | C39: 77.25 | D39: {=IF(F39="n/a","—",IF(_xlfn.XLOOKUP(TRIM(SUBSTITUTE(A39,_xlfn.UNICHAR(160)," ")),TRIM(SUBSTITUTE('worker file'!$A$2:$A$406,_xlfn.UNICHAR(160)," ")),'worker file'!$L$2:$L$406,"")="US Biweekly",$I$3,$I$2))} -> 46298 | E39: Accrues per hour worked; cap 120 hrs | F39: hrs
A40: E0022 | B40: TX Hourly Sick (company) | C40: 28 | D40: {=IF(F40="n/a","—",IF(_xlfn.XLOOKUP(TRIM(SUBSTITUTE(A40,_xlfn.UNICHAR(160)," ")),TRIM(SUBSTITUTE('worker file'!$A$2:$A$406,_xlfn.UNICHAR(160)," ")),'worker file'!$L$2:$L$406,"")="US Biweekly",$I$3,$I$2))} -> 46298 | E40: Company policy; 40 hrs/yr | F40: hrs
A41: E0023 | B41: US Hourly Vacation | C41: 120 | D41: {=IF(F41="n/a","—",IF(_xlfn.XLOOKUP(TRIM(SUBSTITUTE(A41,_xlfn.UNICHAR(160)," ")),TRIM(SUBSTITUTE('worker file'!$A$2:$A$406,_xlfn.UNICHAR(160)," ")),'worker file'!$L$2:$L$406,"")="US Biweekly",$I$3,$I$2))} -> 46298 | E41: At 120-hr cap – accrual paused | F41: hrs
A42: E0023 | B42: CA Paid Sick Leave | C42: 35.5 | D42: {=IF(F42="n/a","—",IF(_xlfn.XLOOKUP(TRIM(SUBSTITUTE(A42,_xlfn.UNICHAR(160)," ")),TRIM(SUBSTITUTE('worker file'!$A$2:$A$406,_xlfn.UNICHAR(160)," ")),'worker file'!$L$2:$L$406,"")="US Biweekly",$I$3,$I$2))} -> 46298 | E42: CA Labor Code 246; accrual cap 80 hrs | F42: hrs
A43: E0024 | B43: US Flexible PTO | C43: n/a (unlimited) | D43: {=IF(F43="n/a","—",IF(_xlfn.XLOOKUP(TRIM(SUBSTITUTE(A43,_xlfn.UNICHAR(160)," ")),TRIM(SUBSTITUTE('worker file'!$A$2:$A$406,_xlfn.UNICHAR(160)," ")),'worker file'!$L$2:$L$406,"")="US Biweekly",$I$3,$I$2))} -> — | E43: No accrual | F43: n/a
A44: E0024 | B44: CA Paid Sick Leave | C44: 46.75 | D44: {=IF(F44="n/a","—",IF(_xlfn.XLOOKUP(TRIM(SUBSTITUTE(A44,_xlfn.UNICHAR(160)," ")),TRIM(SUBSTITUTE('worker file'!$A$2:$A$406,_xlfn.UNICHAR(160)," ")),'worker file'!$L$2:$L$406,"")="US Biweekly",$I$3,$I$2))} -> 46295 | E44: CA Labor Code 246; accrual cap 80 hrs | F44: hrs
A45: E0025 | B45: US Hourly Vacation | C45: 120 | D45: {=IF(F45="n/a","—",IF(_xlfn.XLOOKUP(TRIM(SUBSTITUTE(A45,_xlfn.UNICHAR(160)," ")),TRIM(SUBSTITUTE('worker file'!$A$2:$A$406,_xlfn.UNICHAR(160)," ")),'worker file'!$L$2:$L$406,"")="US Biweekly",$I$3,$I$2))} -> 46298 | E45: Accrues per hour worked; cap 120 hrs | F45: hrs
A46: E0025 | B46: CA Paid Sick Leave | C46: 46.5 | D46: {=IF(F46="n/a","—",IF(_xlfn.XLOOKUP(TRIM(SUBSTITUTE(A46,_xlfn.UNICHAR(160)," ")),TRIM(SUBSTITUTE('worker file'!$A$2:$A$406,_xlfn.UNICHAR(160)," ")),'worker file'!$L$2:$L$406,"")="US Biweekly",$I$3,$I$2))} -> 46298 | E46: CA Labor Code 246; accrual cap 80 hrs | F46: hrs
A47: E0026 | B47: US Flexible PTO | C47: n/a (unlimited) | D47: {=IF(F47="n/a","—",IF(_xlfn.XLOOKUP(TRIM(SUBSTITUTE(A47,_xlfn.UNICHAR(160)," ")),TRIM(SUBSTITUTE('worker file'!$A$2:$A$406,_xlfn.UNICHAR(160)," ")),'worker file'!$L$2:$L$406,"")="US Biweekly",$I$3,$I$2))} -> — | E47: No accrual | F47: n/a
A48: E0026 | B48: CA Paid Sick Leave | C48: 65.75 | D48: {=IF(F48="n/a","—",IF(_xlfn.XLOOKUP(TRIM(SUBSTITUTE(A48,_xlfn.UNICHAR(160)," ")),TRIM(SUBSTITUTE('worker file'!$A$2:$A$406,_xlfn.UNICHAR(160)," ")),'worker file'!$L$2:$L$406,"")="US Biweekly",$I$3,$I$2))} -> 46295 | E48: CA Labor Code 246; accrual cap 80 hrs | F48: hrs
A49: E0027 | B49: US Flexible PTO | C49: n/a (unlimited) | D49: {=IF(F49="n/a","—",IF(_xlfn.XLOOKUP(TRIM(SUBSTITUTE(A49,_xlfn.UNICHAR(160)," ")),TRIM(SUBSTITUTE('worker file'!$A$2:$A$406,_xlfn.UNICHAR(160)," ")),'worker file'!$L$2:$L$406,"")="US Biweekly",$I$3,$I$2))} -> — | E49: No accrual | F49: n/a
A50: E0027 | B50: CA Paid Sick Leave | C50: 28.75 | D50: {=IF(F50="n/a","—",IF(_xlfn.XLOOKUP(TRIM(SUBSTITUTE(A50,_xlfn.UNICHAR(160)," ")),TRIM(SUBSTITUTE('worker file'!$A$2:$A$406,_xlfn.UNICHAR(160)," ")),'worker file'!$L$2:$L$406,"")="US Biweekly",$I$3,$I$2))} -> 46295 | E50: CA Labor Code 246; accrual cap 80 hrs | F50: hrs
A51: E0028 | B51: US Hourly Vacation | C51: 120 | D51: {=IF(F51="n/a","—",IF(_xlfn.XLOOKUP(TRIM(SUBSTITUTE(A51,_xlfn.UNICHAR(160)," ")),TRIM(SUBSTITUTE('worker file'!$A$2:$A$406,_xlfn.UNICHAR(160)," ")),'worker file'!$L$2:$L$406,"")="US Biweekly",$I$3,$I$2))} -> 46298 | E51: Accrues per hour worked; cap 120 hrs; Payout on termination | F51: hrs
A52: E0028 | B52: CA Paid Sick Leave | C52: 11 | D52: {=IF(F52="n/a","—",IF(_xlfn.XLOOKUP(TRIM(SUBSTITUTE(A52,_xlfn.UNICHAR(160)," ")),TRIM(SUBSTITUTE('worker file'!$A$2:$A$406,_xlfn.UNICHAR(160)," ")),'worker file'!$L$2:$L$406,"")="US Biweekly",$I$3,$I$2))} -> 46298 | E52: CA Labor Code 246; accrual cap 80 hrs | F52: hrs
A53: E0029 | B53: US Hourly Vacation | C53: 74.5 | D53: {=IF(F53="n/a","—",IF(_xlfn.XLOOKUP(TRIM(SUBSTITUTE(A53,_xlfn.UNICHAR(160)," ")),TRIM(SUBSTITUTE('worker file'!$A$2:$A$406,_xlfn.UNICHAR(160)," ")),'worker file'!$L$2:$L$406,"")="US Biweekly",$I$3,$I$2))} -> 46298 | E53: Accrues per hour worked; cap 120 hrs; Payout on termination | F53: hrs
A54: E0029 | B54: CA Paid Sick Leave | C54: 0 | D54: {=IF(F54="n/a","—",IF(_xlfn.XLOOKUP(TRIM(SUBSTITUTE(A54,_xlfn.UNICHAR(160)," ")),TRIM(SUBSTITUTE('worker file'!$A$2:$A$406,_xlfn.UNICHAR(160)," ")),'worker file'!$L$2:$L$406,"")="US Biweekly",$I$3,$I$2))} -> 46298 | E54: CA Labor Code 246; accrual cap 80 hrs | F54: hrs
A55: E0030 | B55: US Flexible PTO | C55: n/a (unlimited) | D55: {=IF(F55="n/a","—",IF(_xlfn.XLOOKUP(TRIM(SUBSTITUTE(A55,_xlfn.UNICHAR(160)," ")),TRIM(SUBSTITUTE('worker file'!$A$2:$A$406,_xlfn.UNICHAR(160)," ")),'worker file'!$L$2:$L$406,"")="US Biweekly",$I$3,$I$2))} -> — | E55: No accrual | F55: n/a
A56: E0030 | B56: CA Paid Sick Leave | C56: 33.5 | D56: {=IF(F56="n/a","—",IF(_xlfn.XLOOKUP(TRIM(SUBSTITUTE(A56,_xlfn.UNICHAR(160)," ")),TRIM(SUBSTITUTE('worker file'!$A$2:$A$406,_xlfn.UNICHAR(160)," ")),'worker file'!$L$2:$L$406,"")="US Biweekly",$I$3,$I$2))} -> 46295 | E56: CA Labor Code 246; accrual cap 80 hrs | F56: hrs
A57: E0031 | B57: US Flexible PTO | C57: n/a (unlimited) | D57: {=IF(F57="n/a","—",IF(_xlfn.XLOOKUP(TRIM(SUBSTITUTE(A57,_xlfn.UNICHAR(160)," ")),TRIM(SUBSTITUTE('worker file'!$A$2:$A$406,_xlfn.UNICHAR(160)," ")),'worker file'!$L$2:$L$406,"")="US Biweekly",$I$3,$I$2))} -> — | E57: No accrual | F57: n/a
A58: E0031 | B58: CA Paid Sick Leave | C58: 25.5 | D58: {=IF(F58="n/a","—",IF(_xlfn.XLOOKUP(TRIM(SUBSTITUTE(A58,_xlfn.UNICHAR(160)," ")),TRIM(SUBSTITUTE('worker file'!$A$2:$A$406,_xlfn.UNICHAR(160)," ")),'worker file'!$L$2:$L$406,"")="US Biweekly",$I$3,$I$2))} -> 46295 | E58: CA Labor Code 246; accrual cap 80 hrs | F58: hrs
A59: E0032 | B59: US Flexible PTO | C59: n/a (unlimited) | D59: {=IF(F59="n/a","—",IF(_xlfn.XLOOKUP(TRIM(SUBSTITUTE(A59,_xlfn.UNICHAR(160)," ")),TRIM(SUBSTITUTE('worker file'!$A$2:$A$406,_xlfn.UNICHAR(160)," ")),'worker file'!$L$2:$L$406,"")="US Biweekly",$I$3,$I$2))} -> — | E59: No accrual | F59: n/a
A60: E0033 | B60: US Flexible PTO | C60: n/a (unlimited) | D60: {=IF(F60="n/a","—",IF(_xlfn.XLOOKUP(TRIM(SUBSTITUTE(A60,_xlfn.UNICHAR(160)," ")),TRIM(SUBSTITUTE('worker file'!$A$2:$A$406,_xlfn.UNICHAR(160)," ")),'worker file'!$L$2:$L$406,"")="US Biweekly",$I$3,$I$2))} -> — | E60: No accrual | F60: n/a
A61: E0034 | B61: US Hourly Vacation | C61: 93.75 | D61: {=IF(F61="n/a","—",IF(_xlfn.XLOOKUP(TRIM(SUBSTITUTE(A61,_xlfn.UNICHAR(160)," ")),TRIM(SUBSTITUTE('worker file'!$A$2:$A$406,_xlfn.UNICHAR(160)," ")),'worker file'!$L$2:$L$406,"")="US Biweekly",$I$3,$I$2))} -> 46298 | E61: Accrues per hour worked; cap 120 hrs | F61: hrs
A62: E0034 | B62: CA Paid Sick Leave | C62: 28.5 | D62: {=IF(F62="n/a","—",IF(_xlfn.XLOOKUP(TRIM(SUBSTITUTE(A62,_xlfn.UNICHAR(160)," ")),TRIM(SUBSTITUTE('worker file'!$A$2:$A$406,_xlfn.UNICHAR(160)," ")),'worker file'!$L$2:$L$406,"")="US Biweekly",$I$3,$I$2))} -> 46298 | E62: CA Labor Code 246; accrual cap 80 hrs | F62: hrs
A63: E0035 | B63: US Flexible PTO | C63: n/a (unlimited) | D63: {=IF(F63="n/a","—",IF(_xlfn.XLOOKUP(TRIM(SUBSTITUTE(A63,_xlfn.UNICHAR(160)," ")),TRIM(SUBSTITUTE('worker file'!$A$2:$A$406,_xlfn.UNICHAR(160)," ")),'worker file'!$L$2:$L$406,"")="US Biweekly",$I$3,$I$2))} -> — | E63: No accrual | F63: n/a
A64: E0035 | B64: CA Paid Sick Leave | C64: 54.75 | D64: {=IF(F64="n/a","—",IF(_xlfn.XLOOKUP(TRIM(SUBSTITUTE(A64,_xlfn.UNICHAR(160)," ")),TRIM(SUBSTITUTE('worker file'!$A$2:$A$406,_xlfn.UNICHAR(160)," ")),'worker file'!$L$2:$L$406,"")="US Biweekly",$I$3,$I$2))} -> 46295 | E64: CA Labor Code 246; accrual cap 80 hrs | F64: hrs
A65: E0036 | B65: US Hourly Vacation | C65: 120 | D65: {=IF(F65="n/a","—",IF(_xlfn.XLOOKUP(TRIM(SUBSTITUTE(A65,_xlfn.UNICHAR(160)," ")),TRIM(SUBSTITUTE('worker file'!$A$2:$A$406,_xlfn.UNICHAR(160)," ")),'worker file'!$L$2:$L$406,"")="US Biweekly",$I$3,$I$2))} -> 46298 | E65: Accrues per hour worked; cap 120 hrs | F65: hrs
A66: E0036 | B66: TX Hourly Sick (company) | C66: 14 | D66: {=IF(F66="n/a","—",IF(_xlfn.XLOOKUP(TRIM(SUBSTITUTE(A66,_xlfn.UNICHAR(160)," ")),TRIM(SUBSTITUTE('worker file'!$A$2:$A$406,_xlfn.UNICHAR(160)," ")),'worker file'!$L$2:$L$406,"")="US Biweekly",$I$3,$I$2))} -> 46298 | E66: Company policy; 40 hrs/yr | F66: hrs
A67: E0037 | B67: US Flexible PTO | C67: n/a (unlimited) | D67: {=IF(F67="n/a","—",IF(_xlfn.XLOOKUP(TRIM(SUBSTITUTE(A67,_xlfn.UNICHAR(160)," ")),TRIM(SUBSTITUTE('worker file'!$A$2:$A$406,_xlfn.UNICHAR(160)," ")),'worker file'!$L$2:$L$406,"")="US Biweekly",$I$3,$I$2))} -> — | E67: No accrual | F67: n/a
A68: E0037 | B68: CA Paid Sick Leave | C68: 67.25 | D68: {=IF(F68="n/a","—",IF(_xlfn.XLOOKUP(TRIM(SUBSTITUTE(A68,_xlfn.UNICHAR(160)," ")),TRIM(SUBSTITUTE('worker file'!$A$2:$A$406,_xlfn.UNICHAR(160)," ")),'worker file'!$L$2:$L$406,"")="US Biweekly",$I$3,$I$2))} -> 46295 | E68: CA Labor Code 246; accrual cap 80 hrs | F68: hrs
A69: E0038 | B69: US Flexible PTO | C69: n/a (unlimited) | D69: {=IF(F69="n/a","—",IF(_xlfn.XLOOKUP(TRIM(SUBSTITUTE(A69,_xlfn.UNICHAR(160)," ")),TRIM(SUBSTITUTE('worker file'!$A$2:$A$406,_xlfn.UNICHAR(160)," ")),'worker file'!$L$2:$L$406,"")="US Biweekly",$I$3,$I$2))} -> — | E69: No accrual | F69: n/a
A70: E0038 | B70: MA Earned Sick Time | C70: 23.5 | D70: {=IF(F70="n/a","—",IF(_xlfn.XLOOKUP(TRIM(SUBSTITUTE(A70,_xlfn.UNICHAR(160)," ")),TRIM(SUBSTITUTE('worker file'!$A$2:$A$406,_xlfn.UNICHAR(160)," ")),'worker file'!$L$2:$L$406,"")="US Biweekly",$I$3,$I$2))} -> 46295 | E70: MA ESTL; 40 hrs/yr | F70: hrs
A71: E0039 | B71: US Flexible PTO | C71: n/a (unlimited) | D71: {=IF(F71="n/a","—",IF(_xlfn.XLOOKUP(TRIM(SUBSTITUTE(A71,_xlfn.UNICHAR(160)," ")),TRIM(SUBSTITUTE('worker file'!$A$2:$A$406,_xlfn.UNICHAR(160)," ")),'worker file'!$L$2:$L$406,"")="US Biweekly",$I$3,$I$2))} -> — | E71: No accrual | F71: n/a
A72: E0040 | B72: US Hourly Vacation | C72: 120 | D72: {=IF(F72="n/a","—",IF(_xlfn.XLOOKUP(TRIM(SUBSTITUTE(A72,_xlfn.UNICHAR(160)," ")),TRIM(SUBSTITUTE('worker file'!$A$2:$A$406,_xlfn.UNICHAR(160)," ")),'worker file'!$L$2:$L$406,"")="US Biweekly",$I$3,$I$2))} -> 46298 | E72: Accrues per hour worked; cap 120 hrs | F72: hrs
A73: E0040 | B73: CA Paid Sick Leave | C73: 39.75 | D73: {=IF(F73="n/a","—",IF(_xlfn.XLOOKUP(TRIM(SUBSTITUTE(A73,_xlfn.UNICHAR(160)," ")),TRIM(SUBSTITUTE('worker file'!$A$2:$A$406,_xlfn.UNICHAR(160)," ")),'worker file'!$L$2:$L$406,"")="US Biweekly",$I$3,$I$2))} -> 46298 | E73: CA Labor Code 246; accrual cap 80 hrs | F73: hrs
A74: E0041 | B74: US Flexible PTO | C74: n/a (unlimited) | D74: {=IF(F74="n/a","—",IF(_xlfn.XLOOKUP(TRIM(SUBSTITUTE(A74,_xlfn.UNICHAR(160)," ")),TRIM(SUBSTITUTE('worker file'!$A$2:$A$406,_xlfn.UNICHAR(160)," ")),'worker file'!$L$2:$L$406,"")="US Biweekly",$I$3,$I$2))} -> — | E74: No accrual | F74: n/a
A75: E0041 | B75: MA Earned Sick Time | C75: 36.5 | D75: {=IF(F75="n/a","—",IF(_xlfn.XLOOKUP(TRIM(SUBSTITUTE(A75,_xlfn.UNICHAR(160)," ")),TRIM(SUBSTITUTE('worker file'!$A$2:$A$406,_xlfn.UNICHAR(160)," ")),'worker file'!$L$2:$L$406,"")="US Biweekly",$I$3,$I$2))} -> 46295 | E75: MA ESTL; 40 hrs/yr | F75: hrs
A76: E0042 | B76: US Flexible PTO | C76: n/a (unlimited) | D76: {=IF(F76="n/a","—",IF(_xlfn.XLOOKUP(TRIM(SUBSTITUTE(A76,_xlfn.UNICHAR(160)," ")),TRIM(SUBSTITUTE('worker file'!$A$2:$A$406,_xlfn.UNICHAR(160)," ")),'worker file'!$L$2:$L$406,"")="US Biweekly",$I$3,$I$2))} -> — | E76: No accrual | F76: n/a
A77: E0042 | B77: CA Paid Sick Leave | C77: 65 | D77: {=IF(F77="n/a","—",IF(_xlfn.XLOOKUP(TRIM(SUBSTITUTE(A77,_xlfn.UNICHAR(160)," ")),TRIM(SUBSTITUTE('worker file'!$A$2:$A$406,_xlfn.UNICHAR(160)," ")),'worker file'!$L$2:$L$406,"")="US Biweekly",$I$3,$I$2))} -> 46295 | E77: CA Labor Code 246; accrual cap 80 hrs | F77: hrs
A78: E0043 | B78: US Flexible PTO | C78: n/a (unlimited) | D78: {=IF(F78="n/a","—",IF(_xlfn.XLOOKUP(TRIM(SUBSTITUTE(A78,_xlfn.UNICHAR(160)," ")),TRIM(SUBSTITUTE('worker file'!$A$2:$A$406,_xlfn.UNICHAR(160)," ")),'worker file'!$L$2:$L$406,"")="US Biweekly",$I$3,$I$2))} -> — | E78: No accrual | F78: n/a
A79: E0043 | B79: CA Paid Sick Leave | C79: 79 | D79: {=IF(F79="n/a","—",IF(_xlfn.XLOOKUP(TRIM(SUBSTITUTE(A79,_xlfn.UNICHAR(160)," ")),TRIM(SUBSTITUTE('worker file'!$A$2:$A$406,_xlfn.UNICHAR(160)," ")),'worker file'!$L$2:$L$406,"")="US Biweekly",$I$3,$I$2))} -> 46295 | E79: CA Labor Code 246; accrual cap 80 hrs | F79: hrs
A80: E0044 | B80: US Flexible PTO | C80: n/a (unlimited) | D80: {=IF(F80="n/a","—",IF(_xlfn.XLOOKUP(TRIM(SUBSTITUTE(A80,_xlfn.UNICHAR(160)," ")),TRIM(SUBSTITUTE('worker file'!$A$2:$A$406,_xlfn.UNICHAR(160)," ")),'worker file'!$L$2:$L$406,"")="US Biweekly",$I$3,$I$2))} -> — | E80: No accrual | F80: n/a
A81: E0044 | B81: CA Paid Sick Leave | C81: 31.25 | D81: {=IF(F81="n/a","—",IF(_xlfn.XLOOKUP(TRIM(SUBSTITUTE(A81,_xlfn.UNICHAR(160)," ")),TRIM(SUBSTITUTE('worker file'!$A$2:$A$406,_xlfn.UNICHAR(160)," ")),'worker file'!$L$2:$L$406,"")="US Biweekly",$I$3,$I$2))} -> 46295 | E81: CA Labor Code 246; accrual cap 80 hrs | F81: hrs
A82: E0045 | B82: US Flexible PTO | C82: n/a (unlimited) | D82: {=IF(F82="n/a","—",IF(_xlfn.XLOOKUP(TRIM(SUBSTITUTE(A82,_xlfn.UNICHAR(160)," ")),TRIM(SUBSTITUTE('worker file'!$A$2:$A$406,_xlfn.UNICHAR(160)," ")),'worker file'!$L$2:$L$406,"")="US Biweekly",$I$3,$I$2))} -> — | E82: No accrual | F82: n/a
A83: E0045 | B83: MA Earned Sick Time | C83: 36.5 | D83: {=IF(F83="n/a","—",IF(_xlfn.XLOOKUP(TRIM(SUBSTITUTE(A83,_xlfn.UNICHAR(160)," ")),TRIM(SUBSTITUTE('worker file'!$A$2:$A$406,_xlfn.UNICHAR(160)," ")),'worker file'!$L$2:$L$406,"")="US Biweekly",$I$3,$I$2))} -> 46295 | E83: MA ESTL; 40 hrs/yr | F83: hrs
A84: E0046 | B84: US Flexible PTO | C84: n/a (unlimited) | D84: {=IF(F84="n/a","—",IF(_xlfn.XLOOKUP(TRIM(SUBSTITUTE(A84,_xlfn.UNICHAR(160)," ")),TRIM(SUBSTITUTE('worker file'!$A$2:$A$406,_xlfn.UNICHAR(160)," ")),'worker file'!$L$2:$L$406,"")="US Biweekly",$I$3,$I$2))} -> — | E84: No accrual | F84: n/a
A85: E0047 | B85: US Hourly Vacation | C85: 93.5 | D85: {=IF(F85="n/a","—",IF(_xlfn.XLOOKUP(TRIM(SUBSTITUTE(A85,_xlfn.UNICHAR(160)," ")),TRIM(SUBSTITUTE('worker file'!$A$2:$A$406,_xlfn.UNICHAR(160)," ")),'worker file'!$L$2:$L$406,"")="US Biweekly",$I$3,$I$2))} -> 46298 | E85: Accrues per hour worked; cap 120 hrs; Payout on termination | F85: hrs
A86: E0047 | B86: TX Hourly Sick (company) | C86: 5.5 | D86: {=IF(F86="n/a","—",IF(_xlfn.XLOOKUP(TRIM(SUBSTITUTE(A86,_xlfn.UNICHAR(160)," ")),TRIM(SUBSTITUTE('worker file'!$A$2:$A$406,_xlfn.UNICHAR(160)," ")),'worker file'!$L$2:$L$406,"")="US Biweekly",$I$3,$I$2))} -> 46298 | E86: Company policy; 40 hrs/yr | F86: hrs
A87: E0048 | B87: US Flexible PTO | C87: n/a (unlimited) | D87: {=IF(F87="n/a","—",IF(_xlfn.XLOOKUP(TRIM(SUBSTITUTE(A87,_xlfn.UNICHAR(160)," ")),TRIM(SUBSTITUTE('worker file'!$A$2:$A$406,_xlfn.UNICHAR(160)," ")),'worker file'!$L$2:$L$406,"")="US Biweekly",$I$3,$I$2))} -> — | E87: No accrual | F87: n/a
A88: E0048 | B88: CA Paid Sick Leave | C88: 31 | D88: {=IF(F88="n/a","—",IF(_xlfn.XLOOKUP(TRIM(SUBSTITUTE(A88,_xlfn.UNICHAR(160)," ")),TRIM(SUBSTITUTE('worker file'!$A$2:$A$406,_xlfn.UNICHAR(160)," ")),'worker file'!$L$2:$L$406,"")="US Biweekly",$I$3,$I$2))} -> 46295 | E88: CA Labor Code 246; accrual cap 80 hrs | F88: hrs
A89: E0049 | B89: US Hourly Vacation | C89: 61.5 | D89: {=IF(F89="n/a","—",IF(_xlfn.XLOOKUP(TRIM(SUBSTITUTE(A89,_xlfn.UNICHAR(160)," ")),TRIM(SUBSTITUTE('worker file'!$A$2:$A$406,_xlfn.UNICHAR(160)," ")),'worker file'!$L$2:$L$406,"")="US Biweekly",$I$3,$I$2))} -> 46298 | E89: Accrues per hour worked; cap 120 hrs | F89: hrs
A90: E0049 | B90: CA Paid Sick Leave | C90: 23.75 | D90: {=IF(F90="n/a","—",IF(_xlfn.XLOOKUP(TRIM(SUBSTITUTE(A90,_xlfn.UNICHAR(160)," ")),TRIM(SUBSTITUTE('worker file'!$A$2:$A$406,_xlfn.UNICHAR(160)," ")),'worker file'!$L$2:$L$406,"")="US Biweekly",$I$3,$I$2))} -> 46298 | E90: CA Labor Code 246; accrual cap 80 hrs | F90: hrs
A91: E0050 | B91: India Earned Leave | C91: 21.5 | D91: {=IF(F91="n/a","—",IF(_xlfn.XLOOKUP(TRIM(SUBSTITUTE(A91,_xlfn.UNICHAR(160)," ")),TRIM(SUBSTITUTE('worker file'!$A$2:$A$406,_xlfn.UNICHAR(160)," ")),'worker file'!$L$2:$L$406,"")="US Biweekly",$I$3,$I$2))} -> 46295 | E91: Karnataka S&E Act; 1.5 days/month | F91: days
A92: E0050 | B92: India Sick/Casual Leave | C92: 1 | D92: {=IF(F92="n/a","—",IF(_xlfn.XLOOKUP(TRIM(SUBSTITUTE(A92,_xlfn.UNICHAR(160)," ")),TRIM(SUBSTITUTE('worker file'!$A$2:$A$406,_xlfn.UNICHAR(160)," ")),'worker file'!$L$2:$L$406,"")="US Biweekly",$I$3,$I$2))} -> 46295 | E92: 12 days/yr; no carry-forward | F92: days
A93: E0051 | B93: US Flexible PTO | C93: n/a (unlimited) | D93: {=IF(F93="n/a","—",IF(_xlfn.XLOOKUP(TRIM(SUBSTITUTE(A93,_xlfn.UNICHAR(160)," ")),TRIM(SUBSTITUTE('worker file'!$A$2:$A$406,_xlfn.UNICHAR(160)," ")),'worker file'!$L$2:$L$406,"")="US Biweekly",$I$3,$I$2))} -> — | E93: No accrual | F93: n/a
A94: E0052 | B94: India Earned Leave | C94: 14 | D94: {=IF(F94="n/a","—",IF(_xlfn.XLOOKUP(TRIM(SUBSTITUTE(A94,_xlfn.UNICHAR(160)," ")),TRIM(SUBSTITUTE('worker file'!$A$2:$A$406,_xlfn.UNICHAR(160)," ")),'worker file'!$L$2:$L$406,"")="US Biweekly",$I$3,$I$2))} -> 46295 | E94: Karnataka S&E Act; 1.5 days/month | F94: days
A95: E0052 | B95: India Sick/Casual Leave | C95: 7 | D95: {=IF(F95="n/a","—",IF(_xlfn.XLOOKUP(TRIM(SUBSTITUTE(A95,_xlfn.UNICHAR(160)," ")),TRIM(SUBSTITUTE('worker file'!$A$2:$A$406,_xlfn.UNICHAR(160)," ")),'worker file'!$L$2:$L$406,"")="US Biweekly",$I$3,$I$2))} -> 46295 | E95: 12 days/yr; no carry-forward | F95: days
A96: E0053 | B96: US Flexible PTO | C96: n/a (unlimited) | D96: {=IF(F96="n/a","—",IF(_xlfn.XLOOKUP(TRIM(SUBSTITUTE(A96,_xlfn.UNICHAR(160)," ")),TRIM(SUBSTITUTE('worker file'!$A$2:$A$406,_xlfn.UNICHAR(160)," ")),'worker file'!$L$2:$L$406,"")="US Biweekly",$I$3,$I$2))} -> — | E96: No accrual | F96: n/a
A97: E0053 | B97: CA Paid Sick Leave | C97: 55.25 | D97: {=IF(F97="n/a","—",IF(_xlfn.XLOOKUP(TRIM(SUBSTITUTE(A97,_xlfn.UNICHAR(160)," ")),TRIM(SUBSTITUTE('worker file'!$A$2:$A$406,_xlfn.UNICHAR(160)," ")),'worker file'!$L$2:$L$406,"")="US Biweekly",$I$3,$I$2))} -> 46295 | E97: CA Labor Code 246; accrual cap 80 hrs | F97: hrs
A98: E0054 | B98: US Flexible PTO | C98: n/a (unlimited) | D98: {=IF(F98="n/a","—",IF(_xlfn.XLOOKUP(TRIM(SUBSTITUTE(A98,_xlfn.UNICHAR(160)," ")),TRIM(SUBSTITUTE('worker file'!$A$2:$A$406,_xlfn.UNICHAR(160)," ")),'worker file'!$L$2:$L$406,"")="US Biweekly",$I$3,$I$2))} -> — | E98: No accrual | F98: n/a
A99: E0054 | B99: CA Paid Sick Leave | C99: 64.75 | D99: {=IF(F99="n/a","—",IF(_xlfn.XLOOKUP(TRIM(SUBSTITUTE(A99,_xlfn.UNICHAR(160)," ")),TRIM(SUBSTITUTE('worker file'!$A$2:$A$406,_xlfn.UNICHAR(160)," ")),'worker file'!$L$2:$L$406,"")="US Biweekly",$I$3,$I$2))} -> 46295 | E99: CA Labor Code 246; accrual cap 80 hrs | F99: hrs
A100: E0055 | B100: US Flexible PTO | C100: n/a (unlimited) | D100: {=IF(F100="n/a","—",IF(_xlfn.XLOOKUP(TRIM(SUBSTITUTE(A100,_xlfn.UNICHAR(160)," ")),TRIM(SUBSTITUTE('worker file'!$A$2:$A$406,_xlfn.UNICHAR(160)," ")),'worker file'!$L$2:$L$406,"")="US Biweekly",$I$3,$I$2))} -> — | E100: No accrual | F100: n/a
...

Sheet Payroll inputs
A1: Payroll Inputs – Ongoing Employee Deductions (US)
A2: Deduction codes & default rates (blue = editable input). Benefits are flat $ per pay period (Medical $200, Dental $44, Vision $30); 401(k) % set per employee in the table below.
F3: Default Rate / Amount
A4: Code | B4: Description | C4: Deduction Type | D4: Tax Treatment | E4: Calc Method | F4: Default Rate | G4: Basis | H4: Frequency
A5: 401K_EE | B5: 401(k) Employee Deferral | C5: Retirement | D5: Pre-tax (exempt from FIT/SIT; subject to FICA) | E5: Percent | F5: Per employee | G5: Gross pay | H5: Every pay period (ongoing)
A6: MED_EE | B6: Medical (Health) – Employee | C6: Benefits | D6: Pre-tax Section 125 (exempt from FIT/SIT/FICA) | E6: Flat | F6: 200 | G6: Per pay period | H6: Every pay period (ongoing)
A7: DEN_EE | B7: Dental – Employee | C7: Benefits | D7: Pre-tax Section 125 (exempt from FIT/SIT/FICA) | E7: Flat | F7: 44 | G7: Per pay period | H7: Every pay period (ongoing)
A8: VIS_EE | B8: Vision – Employee | C8: Benefits | D8: Pre-tax Section 125 (exempt from FIT/SIT/FICA) | E8: Flat | F8: 30 | G8: Per pay period | H8: Every pay period (ongoing)
B9: Total benefits (Health + Dental + Vision) | F9: =SUM(F6:F8) -> 274
A11: Employee ID | B11: Pay Group | C11: State | D11: Worker Status | E11: Deduction Code | F11: Description | G11: Tax Treatment | H11: Calc Method | I11: Rate (%) | J11: Flat Amount | K11: Basis | L11: Frequency | M11: Effective Start | N11: Effective End | O11: Notes
A12: E0001 | B12: {=_xlfn.XLOOKUP($A12,TRIM(SUBSTITUTE('worker file'!$A$2:$A$406,_xlfn.UNICHAR(160)," ")),'worker file'!$L$2:$L$406,"Not found")} -> US Semi-monthly | C12: {=_xlfn.XLOOKUP($A12,TRIM(SUBSTITUTE('worker file'!$A$2:$A$406,_xlfn.UNICHAR(160)," ")),'worker file'!$D$2:$D$406,"Not found")} -> CA | D12: {=_xlfn.XLOOKUP($A12,TRIM(SUBSTITUTE('worker file'!$A$2:$A$406,_xlfn.UNICHAR(160)," ")),'worker file'!$Q$2:$Q$406,"Not found")} -> Active | E12: 401K_EE | F12: =_xlfn.XLOOKUP($E12,$A$5:$A$8,$B$5:$B$8,"") -> 401(k) Employee Deferral | G12: =_xlfn.XLOOKUP($E12,$A$5:$A$8,$D$5:$D$8,"") -> Pre-tax (exempt from FIT/SIT; subject to FICA) | H12: =_xlfn.XLOOKUP($E12,$A$5:$A$8,$E$5:$E$8,"") -> Percent | I12: 0.03 | J12: =IF($H12="Flat",_xlfn.XLOOKUP($E12,$A$5:$A$8,$F$5:$F$8,""),"") | K12: =_xlfn.XLOOKUP($E12,$A$5:$A$8,$G$5:$G$8,"") -> Gross pay | L12: =_xlfn.XLOOKUP($E12,$A$5:$A$8,$H$5:$H$8,"") -> Every pay period (ongoing) | M12: {=MAX(_xlfn.XLOOKUP($A12,TRIM(SUBSTITUTE('worker file'!$A$2:$A$406,_xlfn.UNICHAR(160)," ")),'worker file'!$M$2:$M$406,0),_xlfn.XLOOKUP($B12,TRIM('pay group & schedule'!$A$2:$A$6),'pay group & schedule'!$D$2:$D$6,0))} -> 46311 | N12: {=_xlfn.LET(_xlpm.t,_xlfn.XLOOKUP($A12,TRIM(SUBSTITUTE('worker file'!$A$2:$A$406,_xlfn.UNICHAR(160)," ")),'worker file'!$N$2:$N$406,""),IF(N(_xlpm.t)=0,"",_xlpm.t))}
A13: E0001 | B13: {=_xlfn.XLOOKUP($A13,TRIM(SUBSTITUTE('worker file'!$A$2:$A$406,_xlfn.UNICHAR(160)," ")),'worker file'!$L$2:$L$406,"Not found")} -> US Semi-monthly | C13: {=_xlfn.XLOOKUP($A13,TRIM(SUBSTITUTE('worker file'!$A$2:$A$406,_xlfn.UNICHAR(160)," ")),'worker file'!$D$2:$D$406,"Not found")} -> CA | D13: {=_xlfn.XLOOKUP($A13,TRIM(SUBSTITUTE('worker file'!$A$2:$A$406,_xlfn.UNICHAR(160)," ")),'worker file'!$Q$2:$Q$406,"Not found")} -> Active | E13: MED_EE | F13: =_xlfn.XLOOKUP($E13,$A$5:$A$8,$B$5:$B$8,"") -> Medical (Health) – Employee | G13: =_xlfn.XLOOKUP($E13,$A$5:$A$8,$D$5:$D$8,"") -> Pre-tax Section 125 (exempt from FIT/SIT/FICA) | H13: =_xlfn.XLOOKUP($E13,$A$5:$A$8,$E$5:$E$8,"") -> Flat | I13: =IF($H13="Percent",_xlfn.XLOOKUP($E13,$A$5:$A$8,$F$5:$F$8,""),"") | J13: =IF($H13="Flat",_xlfn.XLOOKUP($E13,$A$5:$A$8,$F$5:$F$8,""),"") -> 200 | K13: =_xlfn.XLOOKUP($E13,$A$5:$A$8,$G$5:$G$8,"") -> Per pay period | L13: =_xlfn.XLOOKUP($E13,$A$5:$A$8,$H$5:$H$8,"") -> Every pay period (ongoing) | M13: {=MAX(_xlfn.XLOOKUP($A13,TRIM(SUBSTITUTE('worker file'!$A$2:$A$406,_xlfn.UNICHAR(160)," ")),'worker file'!$M$2:$M$406,0),_xlfn.XLOOKUP($B13,TRIM('pay group & schedule'!$A$2:$A$6),'pay group & schedule'!$D$2:$D$6,0))} -> 46311 | N13: {=_xlfn.LET(_xlpm.t,_xlfn.XLOOKUP($A13,TRIM(SUBSTITUTE('worker file'!$A$2:$A$406,_xlfn.UNICHAR(160)," ")),'worker file'!$N$2:$N$406,""),IF(N(_xlpm.t)=0,"",_xlpm.t))}
A14: E0001 | B14: {=_xlfn.XLOOKUP($A14,TRIM(SUBSTITUTE('worker file'!$A$2:$A$406,_xlfn.UNICHAR(160)," ")),'worker file'!$L$2:$L$406,"Not found")} -> US Semi-monthly | C14: {=_xlfn.XLOOKUP($A14,TRIM(SUBSTITUTE('worker file'!$A$2:$A$406,_xlfn.UNICHAR(160)," ")),'worker file'!$D$2:$D$406,"Not found")} -> CA | D14: {=_xlfn.XLOOKUP($A14,TRIM(SUBSTITUTE('worker file'!$A$2:$A$406,_xlfn.UNICHAR(160)," ")),'worker file'!$Q$2:$Q$406,"Not found")} -> Active | E14: DEN_EE | F14: =_xlfn.XLOOKUP($E14,$A$5:$A$8,$B$5:$B$8,"") -> Dental – Employee | G14: =_xlfn.XLOOKUP($E14,$A$5:$A$8,$D$5:$D$8,"") -> Pre-tax Section 125 (exempt from FIT/SIT/FICA) | H14: =_xlfn.XLOOKUP($E14,$A$5:$A$8,$E$5:$E$8,"") -> Flat | I14: =IF($H14="Percent",_xlfn.XLOOKUP($E14,$A$5:$A$8,$F$5:$F$8,""),"") | J14: =IF($H14="Flat",_xlfn.XLOOKUP($E14,$A$5:$A$8,$F$5:$F$8,""),"") -> 44 | K14: =_xlfn.XLOOKUP($E14,$A$5:$A$8,$G$5:$G$8,"") -> Per pay period | L14: =_xlfn.XLOOKUP($E14,$A$5:$A$8,$H$5:$H$8,"") -> Every pay period (ongoing) | M14: {=MAX(_xlfn.XLOOKUP($A14,TRIM(SUBSTITUTE('worker file'!$A$2:$A$406,_xlfn.UNICHAR(160)," ")),'worker file'!$M$2:$M$406,0),_xlfn.XLOOKUP($B14,TRIM('pay group & schedule'!$A$2:$A$6),'pay group & schedule'!$D$2:$D$6,0))} -> 46311 | N14: {=_xlfn.LET(_xlpm.t,_xlfn.XLOOKUP($A14,TRIM(SUBSTITUTE('worker file'!$A$2:$A$406,_xlfn.UNICHAR(160)," ")),'worker file'!$N$2:$N$406,""),IF(N(_xlpm.t)=0,"",_xlpm.t))}
A15: E0001 | B15: {=_xlfn.XLOOKUP($A15,TRIM(SUBSTITUTE('worker file'!$A$2:$A$406,_xlfn.UNICHAR(160)," ")),'worker file'!$L$2:$L$406,"Not found")} -> US Semi-monthly | C15: {=_xlfn.XLOOKUP($A15,TRIM(SUBSTITUTE('worker file'!$A$2:$A$406,_xlfn.UNICHAR(160)," ")),'worker file'!$D$2:$D$406,"Not found")} -> CA | D15: {=_xlfn.XLOOKUP($A15,TRIM(SUBSTITUTE('worker file'!$A$2:$A$406,_xlfn.UNICHAR(160)," ")),'worker file'!$Q$2:$Q$406,"Not found")} -> Active | E15: VIS_EE | F15: =_xlfn.XLOOKUP($E15,$A$5:$A$8,$B$5:$B$8,"") -> Vision – Employee | G15: =_xlfn.XLOOKUP($E15,$A$5:$A$8,$D$5:$D$8,"") -> Pre-tax Section 125 (exempt from FIT/SIT/FICA) | H15: =_xlfn.XLOOKUP($E15,$A$5:$A$8,$E$5:$E$8,"") -> Flat | I15: =IF($H15="Percent",_xlfn.XLOOKUP($E15,$A$5:$A$8,$F$5:$F$8,""),"") | J15: =IF($H15="Flat",_xlfn.XLOOKUP($E15,$A$5:$A$8,$F$5:$F$8,""),"") -> 30 | K15: =_xlfn.XLOOKUP($E15,$A$5:$A$8,$G$5:$G$8,"") -> Per pay period | L15: =_xlfn.XLOOKUP($E15,$A$5:$A$8,$H$5:$H$8,"") -> Every pay period (ongoing) | M15: {=MAX(_xlfn.XLOOKUP($A15,TRIM(SUBSTITUTE('worker file'!$A$2:$A$406,_xlfn.UNICHAR(160)," ")),'worker file'!$M$2:$M$406,0),_xlfn.XLOOKUP($B15,TRIM('pay group & schedule'!$A$2:$A$6),'pay group & schedule'!$D$2:$D$6,0))} -> 46311 | N15: {=_xlfn.LET(_xlpm.t,_xlfn.XLOOKUP($A15,TRIM(SUBSTITUTE('worker file'!$A$2:$A$406,_xlfn.UNICHAR(160)," ")),'worker file'!$N$2:$N$406,""),IF(N(_xlpm.t)=0,"",_xlpm.t))}
A16: E0004 | B16: {=_xlfn.XLOOKUP($A16,TRIM(SUBSTITUTE('worker file'!$A$2:$A$406,_xlfn.UNICHAR(160)," ")),'worker file'!$L$2:$L$406,"Not found")} -> US Semi-monthly | C16: {=_xlfn.XLOOKUP($A16,TRIM(SUBSTITUTE('worker file'!$A$2:$A$406,_xlfn.UNICHAR(160)," ")),'worker file'!$D$2:$D$406,"Not found")} -> WA | D16: {=_xlfn.XLOOKUP($A16,TRIM(SUBSTITUTE('worker file'!$A$2:$A$406,_xlfn.UNICHAR(160)," ")),'worker file'!$Q$2:$Q$406,"Not found")} -> Termination pending | E16: MED_EE | F16: =_xlfn.XLOOKUP($E16,$A$5:$A$8,$B$5:$B$8,"") -> Medical (Health) – Employee | G16: =_xlfn.XLOOKUP($E16,$A$5:$A$8,$D$5:$D$8,"") -> Pre-tax Section 125 (exempt from FIT/SIT/FICA) | H16: =_xlfn.XLOOKUP($E16,$A$5:$A$8,$E$5:$E$8,"") -> Flat | I16: =IF($H16="Percent",_xlfn.XLOOKUP($E16,$A$5:$A$8,$F$5:$F$8,""),"") | J16: =IF($H16="Flat",_xlfn.XLOOKUP($E16,$A$5:$A$8,$F$5:$F$8,""),"") -> 200 | K16: =_xlfn.XLOOKUP($E16,$A$5:$A$8,$G$5:$G$8,"") -> Per pay period | L16: =_xlfn.XLOOKUP($E16,$A$5:$A$8,$H$5:$H$8,"") -> Every pay period (ongoing) | M16: {=MAX(_xlfn.XLOOKUP($A16,TRIM(SUBSTITUTE('worker file'!$A$2:$A$406,_xlfn.UNICHAR(160)," ")),'worker file'!$M$2:$M$406,0),_xlfn.XLOOKUP($B16,TRIM('pay group & schedule'!$A$2:$A$6),'pay group & schedule'!$D$2:$D$6,0))} -> 46311 | N16: {=_xlfn.LET(_xlpm.t,_xlfn.XLOOKUP($A16,TRIM(SUBSTITUTE('worker file'!$A$2:$A$406,_xlfn.UNICHAR(160)," ")),'worker file'!$N$2:$N$406,""),IF(N(_xlpm.t)=0,"",_xlpm.t))} -> 46326 | O16: Ongoing until term date; stop after final pay
A17: E0004 | B17: {=_xlfn.XLOOKUP($A17,TRIM(SUBSTITUTE('worker file'!$A$2:$A$406,_xlfn.UNICHAR(160)," ")),'worker file'!$L$2:$L$406,"Not found")} -> US Semi-monthly | C17: {=_xlfn.XLOOKUP($A17,TRIM(SUBSTITUTE('worker file'!$A$2:$A$406,_xlfn.UNICHAR(160)," ")),'worker file'!$D$2:$D$406,"Not found")} -> WA | D17: {=_xlfn.XLOOKUP($A17,TRIM(SUBSTITUTE('worker file'!$A$2:$A$406,_xlfn.UNICHAR(160)," ")),'worker file'!$Q$2:$Q$406,"Not found")} -> Termination pending | E17: DEN_EE | F17: =_xlfn.XLOOKUP($E17,$A$5:$A$8,$B$5:$B$8,"") -> Dental – Employee | G17: =_xlfn.XLOOKUP($E17,$A$5:$A$8,$D$5:$D$8,"") -> Pre-tax Section 125 (exempt from FIT/SIT/FICA) | H17: =_xlfn.XLOOKUP($E17,$A$5:$A$8,$E$5:$E$8,"") -> Flat | I17: =IF($H17="Percent",_xlfn.XLOOKUP($E17,$A$5:$A$8,$F$5:$F$8,""),"") | J17: =IF($H17="Flat",_xlfn.XLOOKUP($E17,$A$5:$A$8,$F$5:$F$8,""),"") -> 44 | K17: =_xlfn.XLOOKUP($E17,$A$5:$A$8,$G$5:$G$8,"") -> Per pay period | L17: =_xlfn.XLOOKUP($E17,$A$5:$A$8,$H$5:$H$8,"") -> Every pay period (ongoing) | M17: {=MAX(_xlfn.XLOOKUP($A17,TRIM(SUBSTITUTE('worker file'!$A$2:$A$406,_xlfn.UNICHAR(160)," ")),'worker file'!$M$2:$M$406,0),_xlfn.XLOOKUP($B17,TRIM('pay group & schedule'!$A$2:$A$6),'pay group & schedule'!$D$2:$D$6,0))} -> 46311 | N17: {=_xlfn.LET(_xlpm.t,_xlfn.XLOOKUP($A17,TRIM(SUBSTITUTE('worker file'!$A$2:$A$406,_xlfn.UNICHAR(160)," ")),'worker file'!$N$2:$N$406,""),IF(N(_xlpm.t)=0,"",_xlpm.t))} -> 46326 | O17: Ongoing until term date; stop after final pay
A18: E0004 | B18: {=_xlfn.XLOOKUP($A18,TRIM(SUBSTITUTE('worker file'!$A$2:$A$406,_xlfn.UNICHAR(160)," ")),'worker file'!$L$2:$L$406,"Not found")} -> US Semi-monthly | C18: {=_xlfn.XLOOKUP($A18,TRIM(SUBSTITUTE('worker file'!$A$2:$A$406,_xlfn.UNICHAR(160)," ")),'worker file'!$D$2:$D$406,"Not found")} -> WA | D18: {=_xlfn.XLOOKUP($A18,TRIM(SUBSTITUTE('worker file'!$A$2:$A$406,_xlfn.UNICHAR(160)," ")),'worker file'!$Q$2:$Q$406,"Not found")} -> Termination pending | E18: VIS_EE | F18: =_xlfn.XLOOKUP($E18,$A$5:$A$8,$B$5:$B$8,"") -> Vision – Employee | G18: =_xlfn.XLOOKUP($E18,$A$5:$A$8,$D$5:$D$8,"") -> Pre-tax Section 125 (exempt from FIT/SIT/FICA) | H18: =_xlfn.XLOOKUP($E18,$A$5:$A$8,$E$5:$E$8,"") -> Flat | I18: =IF($H18="Percent",_xlfn.XLOOKUP($E18,$A$5:$A$8,$F$5:$F$8,""),"") | J18: =IF($H18="Flat",_xlfn.XLOOKUP($E18,$A$5:$A$8,$F$5:$F$8,""),"") -> 30 | K18: =_xlfn.XLOOKUP($E18,$A$5:$A$8,$G$5:$G$8,"") -> Per pay period | L18: =_xlfn.XLOOKUP($E18,$A$5:$A$8,$H$5:$H$8,"") -> Every pay period (ongoing) | M18: {=MAX(_xlfn.XLOOKUP($A18,TRIM(SUBSTITUTE('worker file'!$A$2:$A$406,_xlfn.UNICHAR(160)," ")),'worker file'!$M$2:$M$406,0),_xlfn.XLOOKUP($B18,TRIM('pay group & schedule'!$A$2:$A$6),'pay group & schedule'!$D$2:$D$6,0))} -> 46311 | N18: {=_xlfn.LET(_xlpm.t,_xlfn.XLOOKUP($A18,TRIM(SUBSTITUTE('worker file'!$A$2:$A$406,_xlfn.UNICHAR(160)," ")),'worker file'!$N$2:$N$406,""),IF(N(_xlpm.t)=0,"",_xlpm.t))} -> 46326 | O18: Ongoing until term date; stop after final pay
A19: E0021 | B19: {=_xlfn.XLOOKUP($A19,TRIM(SUBSTITUTE('worker file'!$A$2:$A$406,_xlfn.UNICHAR(160)," ")),'worker file'!$L$2:$L$406,"Not found")} -> US Biweekly | C19: {=_xlfn.XLOOKUP($A19,TRIM(SUBSTITUTE('worker file'!$A$2:$A$406,_xlfn.UNICHAR(160)," ")),'worker file'!$D$2:$D$406,"Not found")} -> CA | D19: {=_xlfn.XLOOKUP($A19,TRIM(SUBSTITUTE('worker file'!$A$2:$A$406,_xlfn.UNICHAR(160)," ")),'worker file'!$Q$2:$Q$406,"Not found")} -> Active | E19: 401K_EE | F19: =_xlfn.XLOOKUP($E19,$A$5:$A$8,$B$5:$B$8,"") -> 401(k) Employee Deferral | G19: =_xlfn.XLOOKUP($E19,$A$5:$A$8,$D$5:$D$8,"") -> Pre-tax (exempt from FIT/SIT; subject to FICA) | H19: =_xlfn.XLOOKUP($E19,$A$5:$A$8,$E$5:$E$8,"") -> Percent | I19: 0.05 | J19: =IF($H19="Flat",_xlfn.XLOOKUP($E19,$A$5:$A$8,$F$5:$F$8,""),"") | K19: =_xlfn.XLOOKUP($E19,$A$5:$A$8,$G$5:$G$8,"") -> Gross pay | L19: =_xlfn.XLOOKUP($E19,$A$5:$A$8,$H$5:$H$8,"") -> Every pay period (ongoing) | M19: {=MAX(_xlfn.XLOOKUP($A19,TRIM(SUBSTITUTE('worker file'!$A$2:$A$406,_xlfn.UNICHAR(160)," ")),'worker file'!$M$2:$M$406,0),_xlfn.XLOOKUP($B19,TRIM('pay group & schedule'!$A$2:$A$6),'pay group & schedule'!$D$2:$D$6,0))} -> 46299 | N19: {=_xlfn.LET(_xlpm.t,_xlfn.XLOOKUP($A19,TRIM(SUBSTITUTE('worker file'!$A$2:$A$406,_xlfn.UNICHAR(160)," ")),'worker file'!$N$2:$N$406,""),IF(N(_xlpm.t)=0,"",_xlpm.t))}
A20: E0021 | B20: {=_xlfn.XLOOKUP($A20,TRIM(SUBSTITUTE('worker file'!$A$2:$A$406,_xlfn.UNICHAR(160)," ")),'worker file'!$L$2:$L$406,"Not found")} -> US Biweekly | C20: {=_xlfn.XLOOKUP($A20,TRIM(SUBSTITUTE('worker file'!$A$2:$A$406,_xlfn.UNICHAR(160)," ")),'worker file'!$D$2:$D$406,"Not found")} -> CA | D20: {=_xlfn.XLOOKUP($A20,TRIM(SUBSTITUTE('worker file'!$A$2:$A$406,_xlfn.UNICHAR(160)," ")),'worker file'!$Q$2:$Q$406,"Not found")} -> Active | E20: MED_EE | F20: =_xlfn.XLOOKUP($E20,$A$5:$A$8,$B$5:$B$8,"") -> Medical (Health) – Employee | G20: =_xlfn.XLOOKUP($E20,$A$5:$A$8,$D$5:$D$8,"") -> Pre-tax Section 125 (exempt from FIT/SIT/FICA) | H20: =_xlfn.XLOOKUP($E20,$A$5:$A$8,$E$5:$E$8,"") -> Flat | I20: =IF($H20="Percent",_xlfn.XLOOKUP($E20,$A$5:$A$8,$F$5:$F$8,""),"") | J20: =IF($H20="Flat",_xlfn.XLOOKUP($E20,$A$5:$A$8,$F$5:$F$8,""),"") -> 200 | K20: =_xlfn.XLOOKUP($E20,$A$5:$A$8,$G$5:$G$8,"") -> Per pay period | L20: =_xlfn.XLOOKUP($E20,$A$5:$A$8,$H$5:$H$8,"") -> Every pay period (ongoing) | M20: {=MAX(_xlfn.XLOOKUP($A20,TRIM(SUBSTITUTE('worker file'!$A$2:$A$406,_xlfn.UNICHAR(160)," ")),'worker file'!$M$2:$M$406,0),_xlfn.XLOOKUP($B20,TRIM('pay group & schedule'!$A$2:$A$6),'pay group & schedule'!$D$2:$D$6,0))} -> 46299 | N20: {=_xlfn.LET(_xlpm.t,_xlfn.XLOOKUP($A20,TRIM(SUBSTITUTE('worker file'!$A$2:$A$406,_xlfn.UNICHAR(160)," ")),'worker file'!$N$2:$N$406,""),IF(N(_xlpm.t)=0,"",_xlpm.t))}
A21: E0021 | B21: {=_xlfn.XLOOKUP($A21,TRIM(SUBSTITUTE('worker file'!$A$2:$A$406,_xlfn.UNICHAR(160)," ")),'worker file'!$L$2:$L$406,"Not found")} -> US Biweekly | C21: {=_xlfn.XLOOKUP($A21,TRIM(SUBSTITUTE('worker file'!$A$2:$A$406,_xlfn.UNICHAR(160)," ")),'worker file'!$D$2:$D$406,"Not found")} -> CA | D21: {=_xlfn.XLOOKUP($A21,TRIM(SUBSTITUTE('worker file'!$A$2:$A$406,_xlfn.UNICHAR(160)," ")),'worker file'!$Q$2:$Q$406,"Not found")} -> Active | E21: DEN_EE | F21: =_xlfn.XLOOKUP($E21,$A$5:$A$8,$B$5:$B$8,"") -> Dental – Employee | G21: =_xlfn.XLOOKUP($E21,$A$5:$A$8,$D$5:$D$8,"") -> Pre-tax Section 125 (exempt from FIT/SIT/FICA) | H21: =_xlfn.XLOOKUP($E21,$A$5:$A$8,$E$5:$E$8,"") -> Flat | I21: =IF($H21="Percent",_xlfn.XLOOKUP($E21,$A$5:$A$8,$F$5:$F$8,""),"") | J21: =IF($H21="Flat",_xlfn.XLOOKUP($E21,$A$5:$A$8,$F$5:$F$8,""),"") -> 44 | K21: =_xlfn.XLOOKUP($E21,$A$5:$A$8,$G$5:$G$8,"") -> Per pay period | L21: =_xlfn.XLOOKUP($E21,$A$5:$A$8,$H$5:$H$8,"") -> Every pay period (ongoing) | M21: {=MAX(_xlfn.XLOOKUP($A21,TRIM(SUBSTITUTE('worker file'!$A$2:$A$406,_xlfn.UNICHAR(160)," ")),'worker file'!$M$2:$M$406,0),_xlfn.XLOOKUP($B21,TRIM('pay group & schedule'!$A$2:$A$6),'pay group & schedule'!$D$2:$D$6,0))} -> 46299 | N21: {=_xlfn.LET(_xlpm.t,_xlfn.XLOOKUP($A21,TRIM(SUBSTITUTE('worker file'!$A$2:$A$406,_xlfn.UNICHAR(160)," ")),'worker file'!$N$2:$N$406,""),IF(N(_xlpm.t)=0,"",_xlpm.t))}
A22: E0021 | B22: {=_xlfn.XLOOKUP($A22,TRIM(SUBSTITUTE('worker file'!$A$2:$A$406,_xlfn.UNICHAR(160)," ")),'worker file'!$L$2:$L$406,"Not found")} -> US Biweekly | C22: {=_xlfn.XLOOKUP($A22,TRIM(SUBSTITUTE('worker file'!$A$2:$A$406,_xlfn.UNICHAR(160)," ")),'worker file'!$D$2:$D$406,"Not found")} -> CA | D22: {=_xlfn.XLOOKUP($A22,TRIM(SUBSTITUTE('worker file'!$A$2:$A$406,_xlfn.UNICHAR(160)," ")),'worker file'!$Q$2:$Q$406,"Not found")} -> Active | E22: VIS_EE | F22: =_xlfn.XLOOKUP($E22,$A$5:$A$8,$B$5:$B$8,"") -> Vision – Employee | G22: =_xlfn.XLOOKUP($E22,$A$5:$A$8,$D$5:$D$8,"") -> Pre-tax Section 125 (exempt from FIT/SIT/FICA) | H22: =_xlfn.XLOOKUP($E22,$A$5:$A$8,$E$5:$E$8,"") -> Flat | I22: =IF($H22="Percent",_xlfn.XLOOKUP($E22,$A$5:$A$8,$F$5:$F$8,""),"") | J22: =IF($H22="Flat",_xlfn.XLOOKUP($E22,$A$5:$A$8,$F$5:$F$8,""),"") -> 30 | K22: =_xlfn.XLOOKUP($E22,$A$5:$A$8,$G$5:$G$8,"") -> Per pay period | L22: =_xlfn.XLOOKUP($E22,$A$5:$A$8,$H$5:$H$8,"") -> Every pay period (ongoing) | M22: {=MAX(_xlfn.XLOOKUP($A22,TRIM(SUBSTITUTE('worker file'!$A$2:$A$406,_xlfn.UNICHAR(160)," ")),'worker file'!$M$2:$M$406,0),_xlfn.XLOOKUP($B22,TRIM('pay group & schedule'!$A$2:$A$6),'pay group & schedule'!$D$2:$D$6,0))} -> 46299 | N22: {=_xlfn.LET(_xlpm.t,_xlfn.XLOOKUP($A22,TRIM(SUBSTITUTE('worker file'!$A$2:$A$406,_xlfn.UNICHAR(160)," ")),'worker file'!$N$2:$N$406,""),IF(N(_xlpm.t)=0,"",_xlpm.t))}
A23: E0022 | B23: {=_xlfn.XLOOKUP($A23,TRIM(SUBSTITUTE('worker file'!$A$2:$A$406,_xlfn.UNICHAR(160)," ")),'worker file'!$L$2:$L$406,"Not found")} -> US Biweekly | C23: {=_xlfn.XLOOKUP($A23,TRIM(SUBSTITUTE('worker file'!$A$2:$A$406,_xlfn.UNICHAR(160)," ")),'worker file'!$D$2:$D$406,"Not found")} -> TX | D23: {=_xlfn.XLOOKUP($A23,TRIM(SUBSTITUTE('worker file'!$A$2:$A$406,_xlfn.UNICHAR(160)," ")),'worker file'!$Q$2:$Q$406,"Not found")} -> Active | E23: 401K_EE | F23: =_xlfn.XLOOKUP($E23,$A$5:$A$8,$B$5:$B$8,"") -> 401(k) Employee Deferral | G23: =_xlfn.XLOOKUP($E23,$A$5:$A$8,$D$5:$D$8,"") -> Pre-tax (exempt from FIT/SIT; subject to FICA) | H23: =_xlfn.XLOOKUP($E23,$A$5:$A$8,$E$5:$E$8,"") -> Percent | I23: 0.02 | J23: =IF($H23="Flat",_xlfn.XLOOKUP($E23,$A$5:$A$8,$F$5:$F$8,""),"") | K23: =_xlfn.XLOOKUP($E23,$A$5:$A$8,$G$5:$G$8,"") -> Gross pay | L23: =_xlfn.XLOOKUP($E23,$A$5:$A$8,$H$5:$H$8,"") -> Every pay period (ongoing) | M23: {=MAX(_xlfn.XLOOKUP($A23,TRIM(SUBSTITUTE('worker file'!$A$2:$A$406,_xlfn.UNICHAR(160)," ")),'worker file'!$M$2:$M$406,0),_xlfn.XLOOKUP($B23,TRIM('pay group & schedule'!$A$2:$A$6),'pay group & schedule'!$D$2:$D$6,0))} -> 46299 | N23: {=_xlfn.LET(_xlpm.t,_xlfn.XLOOKUP($A23,TRIM(SUBSTITUTE('worker file'!$A$2:$A$406,_xlfn.UNICHAR(160)," ")),'worker file'!$N$2:$N$406,""),IF(N(_xlpm.t)=0,"",_xlpm.t))}
A24: E0022 | B24: {=_xlfn.XLOOKUP($A24,TRIM(SUBSTITUTE('worker file'!$A$2:$A$406,_xlfn.UNICHAR(160)," ")),'worker file'!$L$2:$L$406,"Not found")} -> US Biweekly | C24: {=_xlfn.XLOOKUP($A24,TRIM(SUBSTITUTE('worker file'!$A$2:$A$406,_xlfn.UNICHAR(160)," ")),'worker file'!$D$2:$D$406,"Not found")} -> TX | D24: {=_xlfn.XLOOKUP($A24,TRIM(SUBSTITUTE('worker file'!$A$2:$A$406,_xlfn.UNICHAR(160)," ")),'worker file'!$Q$2:$Q$406,"Not found")} -> Active | E24: MED_EE | F24: =_xlfn.XLOOKUP($E24,$A$5:$A$8,$B$5:$B$8,"") -> Medical (Health) – Employee | G24: =_xlfn.XLOOKUP($E24,$A$5:$A$8,$D$5:$D$8,"") -> Pre-tax Section 125 (exempt from FIT/SIT/FICA) | H24: =_xlfn.XLOOKUP($E24,$A$5:$A$8,$E$5:$E$8,"") -> Flat | I24: =IF($H24="Percent",_xlfn.XLOOKUP($E24,$A$5:$A$8,$F$5:$F$8,""),"") | J24: =IF($H24="Flat",_xlfn.XLOOKUP($E24,$A$5:$A$8,$F$5:$F$8,""),"") -> 200 | K24: =_xlfn.XLOOKUP($E24,$A$5:$A$8,$G$5:$G$8,"") -> Per pay period | L24: =_xlfn.XLOOKUP($E24,$A$5:$A$8,$H$5:$H$8,"") -> Every pay period (ongoing) | M24: {=MAX(_xlfn.XLOOKUP($A24,TRIM(SUBSTITUTE('worker file'!$A$2:$A$406,_xlfn.UNICHAR(160)," ")),'worker file'!$M$2:$M$406,0),_xlfn.XLOOKUP($B24,TRIM('pay group & schedule'!$A$2:$A$6),'pay group & schedule'!$D$2:$D$6,0))} -> 46299 | N24: {=_xlfn.LET(_xlpm.t,_xlfn.XLOOKUP($A24,TRIM(SUBSTITUTE('worker file'!$A$2:$A$406,_xlfn.UNICHAR(160)," ")),'worker file'!$N$2:$N$406,""),IF(N(_xlpm.t)=0,"",_xlpm.t))}
A25: E0022 | B25: {=_xlfn.XLOOKUP($A25,TRIM(SUBSTITUTE('worker file'!$A$2:$A$406,_xlfn.UNICHAR(160)," ")),'worker file'!$L$2:$L$406,"Not found")} -> US Biweekly | C25: {=_xlfn.XLOOKUP($A25,TRIM(SUBSTITUTE('worker file'!$A$2:$A$406,_xlfn.UNICHAR(160)," ")),'worker file'!$D$2:$D$406,"Not found")} -> TX | D25: {=_xlfn.XLOOKUP($A25,TRIM(SUBSTITUTE('worker file'!$A$2:$A$406,_xlfn.UNICHAR(160)," ")),'worker file'!$Q$2:$Q$406,"Not found")} -> Active | E25: DEN_EE | F25: =_xlfn.XLOOKUP($E25,$A$5:$A$8,$B$5:$B$8,"") -> Dental – Employee | G25: =_xlfn.XLOOKUP($E25,$A$5:$A$8,$D$5:$D$8,"") -> Pre-tax Section 125 (exempt from FIT/SIT/FICA) | H25: =_xlfn.XLOOKUP($E25,$A$5:$A$8,$E$5:$E$8,"") -> Flat | I25: =IF($H25="Percent",_xlfn.XLOOKUP($E25,$A$5:$A$8,$F$5:$F$8,""),"") | J25: =IF($H25="Flat",_xlfn.XLOOKUP($E25,$A$5:$A$8,$F$5:$F$8,""),"") -> 44 | K25: =_xlfn.XLOOKUP($E25,$A$5:$A$8,$G$5:$G$8,"") -> Per pay period | L25: =_xlfn.XLOOKUP($E25,$A$5:$A$8,$H$5:$H$8,"") -> Every pay period (ongoing) | M25: {=MAX(_xlfn.XLOOKUP($A25,TRIM(SUBSTITUTE('worker file'!$A$2:$A$406,_xlfn.UNICHAR(160)," ")),'worker file'!$M$2:$M$406,0),_xlfn.XLOOKUP($B25,TRIM('pay group & schedule'!$A$2:$A$6),'pay group & schedule'!$D$2:$D$6,0))} -> 46299 | N25: {=_xlfn.LET(_xlpm.t,_xlfn.XLOOKUP($A25,TRIM(SUBSTITUTE('worker file'!$A$2:$A$406,_xlfn.UNICHAR(160)," ")),'worker file'!$N$2:$N$406,""),IF(N(_xlpm.t)=0,"",_xlpm.t))}
A26: E0022 | B26: {=_xlfn.XLOOKUP($A26,TRIM(SUBSTITUTE('worker file'!$A$2:$A$406,_xlfn.UNICHAR(160)," ")),'worker file'!$L$2:$L$406,"Not found")} -> US Biweekly | C26: {=_xlfn.XLOOKUP($A26,TRIM(SUBSTITUTE('worker file'!$A$2:$A$406,_xlfn.UNICHAR(160)," ")),'worker file'!$D$2:$D$406,"Not found")} -> TX | D26: {=_xlfn.XLOOKUP($A26,TRIM(SUBSTITUTE('worker file'!$A$2:$A$406,_xlfn.UNICHAR(160)," ")),'worker file'!$Q$2:$Q$406,"Not found")} -> Active | E26: VIS_EE | F26: =_xlfn.XLOOKUP($E26,$A$5:$A$8,$B$5:$B$8,"") -> Vision – Employee | G26: =_xlfn.XLOOKUP($E26,$A$5:$A$8,$D$5:$D$8,"") -> Pre-tax Section 125 (exempt from FIT/SIT/FICA) | H26: =_xlfn.XLOOKUP($E26,$A$5:$A$8,$E$5:$E$8,"") -> Flat | I26: =IF($H26="Percent",_xlfn.XLOOKUP($E26,$A$5:$A$8,$F$5:$F$8,""),"") | J26: =IF($H26="Flat",_xlfn.XLOOKUP($E26,$A$5:$A$8,$F$5:$F$8,""),"") -> 30 | K26: =_xlfn.XLOOKUP($E26,$A$5:$A$8,$G$5:$G$8,"") -> Per pay period | L26: =_xlfn.XLOOKUP($E26,$A$5:$A$8,$H$5:$H$8,"") -> Every pay period (ongoing) | M26: {=MAX(_xlfn.XLOOKUP($A26,TRIM(SUBSTITUTE('worker file'!$A$2:$A$406,_xlfn.UNICHAR(160)," ")),'worker file'!$M$2:$M$406,0),_xlfn.XLOOKUP($B26,TRIM('pay group & schedule'!$A$2:$A$6),'pay group & schedule'!$D$2:$D$6,0))} -> 46299 | N26: {=_xlfn.LET(_xlpm.t,_xlfn.XLOOKUP($A26,TRIM(SUBSTITUTE('worker file'!$A$2:$A$406,_xlfn.UNICHAR(160)," ")),'worker file'!$N$2:$N$406,""),IF(N(_xlpm.t)=0,"",_xlpm.t))}
A27: E0148 | B27: {=_xlfn.XLOOKUP($A27,TRIM(SUBSTITUTE('worker file'!$A$2:$A$406,_xlfn.UNICHAR(160)," ")),'worker file'!$L$2:$L$406,"Not found")} -> US Biweekly | C27: {=_xlfn.XLOOKUP($A27,TRIM(SUBSTITUTE('worker file'!$A$2:$A$406,_xlfn.UNICHAR(160)," ")),'worker file'!$D$2:$D$406,"Not found")} -> CA | D27: {=_xlfn.XLOOKUP($A27,TRIM(SUBSTITUTE('worker file'!$A$2:$A$406,_xlfn.UNICHAR(160)," ")),'worker file'!$Q$2:$Q$406,"Not found")} -> Termination pending | E27: 401K_EE | F27: =_xlfn.XLOOKUP($E27,$A$5:$A$8,$B$5:$B$8,"") -> 401(k) Employee Deferral | G27: =_xlfn.XLOOKUP($E27,$A$5:$A$8,$D$5:$D$8,"") -> Pre-tax (exempt from FIT/SIT; subject to FICA) | H27: =_xlfn.XLOOKUP($E27,$A$5:$A$8,$E$5:$E$8,"") -> Percent | I27: 0.07 | J27: =IF($H27="Flat",_xlfn.XLOOKUP($E27,$A$5:$A$8,$F$5:$F$8,""),"") | K27: =_xlfn.XLOOKUP($E27,$A$5:$A$8,$G$5:$G$8,"") -> Gross pay | L27: =_xlfn.XLOOKUP($E27,$A$5:$A$8,$H$5:$H$8,"") -> Every pay period (ongoing) | M27: {=MAX(_xlfn.XLOOKUP($A27,TRIM(SUBSTITUTE('worker file'!$A$2:$A$406,_xlfn.UNICHAR(160)," ")),'worker file'!$M$2:$M$406,0),_xlfn.XLOOKUP($B27,TRIM('pay group & schedule'!$A$2:$A$6),'pay group & schedule'!$D$2:$D$6,0))} -> 46299 | N27: {=_xlfn.LET(_xlpm.t,_xlfn.XLOOKUP($A27,TRIM(SUBSTITUTE('worker file'!$A$2:$A$406,_xlfn.UNICHAR(160)," ")),'worker file'!$N$2:$N$406,""),IF(N(_xlpm.t)=0,"",_xlpm.t))} -> 46312 | O27: Ongoing until term date; stop after final pay
A28: E0148 | B28: {=_xlfn.XLOOKUP($A28,TRIM(SUBSTITUTE('worker file'!$A$2:$A$406,_xlfn.UNICHAR(160)," ")),'worker file'!$L$2:$L$406,"Not found")} -> US Biweekly | C28: {=_xlfn.XLOOKUP($A28,TRIM(SUBSTITUTE('worker file'!$A$2:$A$406,_xlfn.UNICHAR(160)," ")),'worker file'!$D$2:$D$406,"Not found")} -> CA | D28: {=_xlfn.XLOOKUP($A28,TRIM(SUBSTITUTE('worker file'!$A$2:$A$406,_xlfn.UNICHAR(160)," ")),'worker file'!$Q$2:$Q$406,"Not found")} -> Termination pending | E28: MED_EE | F28: =_xlfn.XLOOKUP($E28,$A$5:$A$8,$B$5:$B$8,"") -> Medical (Health) – Employee | G28: =_xlfn.XLOOKUP($E28,$A$5:$A$8,$D$5:$D$8,"") -> Pre-tax Section 125 (exempt from FIT/SIT/FICA) | H28: =_xlfn.XLOOKUP($E28,$A$5:$A$8,$E$5:$E$8,"") -> Flat | I28: =IF($H28="Percent",_xlfn.XLOOKUP($E28,$A$5:$A$8,$F$5:$F$8,""),"") | J28: =IF($H28="Flat",_xlfn.XLOOKUP($E28,$A$5:$A$8,$F$5:$F$8,""),"") -> 200 | K28: =_xlfn.XLOOKUP($E28,$A$5:$A$8,$G$5:$G$8,"") -> Per pay period | L28: =_xlfn.XLOOKUP($E28,$A$5:$A$8,$H$5:$H$8,"") -> Every pay period (ongoing) | M28: {=MAX(_xlfn.XLOOKUP($A28,TRIM(SUBSTITUTE('worker file'!$A$2:$A$406,_xlfn.UNICHAR(160)," ")),'worker file'!$M$2:$M$406,0),_xlfn.XLOOKUP($B28,TRIM('pay group & schedule'!$A$2:$A$6),'pay group & schedule'!$D$2:$D$6,0))} -> 46299 | N28: {=_xlfn.LET(_xlpm.t,_xlfn.XLOOKUP($A28,TRIM(SUBSTITUTE('worker file'!$A$2:$A$406,_xlfn.UNICHAR(160)," ")),'worker file'!$N$2:$N$406,""),IF(N(_xlpm.t)=0,"",_xlpm.t))} -> 46312 | O28: Ongoing until term date; stop after final pay
A29: E0148 | B29: {=_xlfn.XLOOKUP($A29,TRIM(SUBSTITUTE('worker file'!$A$2:$A$406,_xlfn.UNICHAR(160)," ")),'worker file'!$L$2:$L$406,"Not found")} -> US Biweekly | C29: {=_xlfn.XLOOKUP($A29,TRIM(SUBSTITUTE('worker file'!$A$2:$A$406,_xlfn.UNICHAR(160)," ")),'worker file'!$D$2:$D$406,"Not found")} -> CA | D29: {=_xlfn.XLOOKUP($A29,TRIM(SUBSTITUTE('worker file'!$A$2:$A$406,_xlfn.UNICHAR(160)," ")),'worker file'!$Q$2:$Q$406,"Not found")} -> Termination pending | E29: DEN_EE | F29: =_xlfn.XLOOKUP($E29,$A$5:$A$8,$B$5:$B$8,"") -> Dental – Employee | G29: =_xlfn.XLOOKUP($E29,$A$5:$A$8,$D$5:$D$8,"") -> Pre-tax Section 125 (exempt from FIT/SIT/FICA) | H29: =_xlfn.XLOOKUP($E29,$A$5:$A$8,$E$5:$E$8,"") -> Flat | I29: =IF($H29="Percent",_xlfn.XLOOKUP($E29,$A$5:$A$8,$F$5:$F$8,""),"") | J29: =IF($H29="Flat",_xlfn.XLOOKUP($E29,$A$5:$A$8,$F$5:$F$8,""),"") -> 44 | K29: =_xlfn.XLOOKUP($E29,$A$5:$A$8,$G$5:$G$8,"") -> Per pay period | L29: =_xlfn.XLOOKUP($E29,$A$5:$A$8,$H$5:$H$8,"") -> Every pay period (ongoing) | M29: {=MAX(_xlfn.XLOOKUP($A29,TRIM(SUBSTITUTE('worker file'!$A$2:$A$406,_xlfn.UNICHAR(160)," ")),'worker file'!$M$2:$M$406,0),_xlfn.XLOOKUP($B29,TRIM('pay group & schedule'!$A$2:$A$6),'pay group & schedule'!$D$2:$D$6,0))} -> 46299 | N29: {=_xlfn.LET(_xlpm.t,_xlfn.XLOOKUP($A29,TRIM(SUBSTITUTE('worker file'!$A$2:$A$406,_xlfn.UNICHAR(160)," ")),'worker file'!$N$2:$N$406,""),IF(N(_xlpm.t)=0,"",_xlpm.t))} -> 46312 | O29: Ongoing until term date; stop after final pay
A30: E0148 | B30: {=_xlfn.XLOOKUP($A30,TRIM(SUBSTITUTE('worker file'!$A$2:$A$406,_xlfn.UNICHAR(160)," ")),'worker file'!$L$2:$L$406,"Not found")} -> US Biweekly | C30: {=_xlfn.XLOOKUP($A30,TRIM(SUBSTITUTE('worker file'!$A$2:$A$406,_xlfn.UNICHAR(160)," ")),'worker file'!$D$2:$D$406,"Not found")} -> CA | D30: {=_xlfn.XLOOKUP($A30,TRIM(SUBSTITUTE('worker file'!$A$2:$A$406,_xlfn.UNICHAR(160)," ")),'worker file'!$Q$2:$Q$406,"Not found")} -> Termination pending | E30: VIS_EE | F30: =_xlfn.XLOOKUP($E30,$A$5:$A$8,$B$5:$B$8,"") -> Vision – Employee | G30: =_xlfn.XLOOKUP($E30,$A$5:$A$8,$D$5:$D$8,"") -> Pre-tax Section 125 (exempt from FIT/SIT/FICA) | H30: =_xlfn.XLOOKUP($E30,$A$5:$A$8,$E$5:$E$8,"") -> Flat | I30: =IF($H30="Percent",_xlfn.XLOOKUP($E30,$A$5:$A$8,$F$5:$F$8,""),"") | J30: =IF($H30="Flat",_xlfn.XLOOKUP($E30,$A$5:$A$8,$F$5:$F$8,""),"") -> 30 | K30: =_xlfn.XLOOKUP($E30,$A$5:$A$8,$G$5:$G$8,"") -> Per pay period | L30: =_xlfn.XLOOKUP($E30,$A$5:$A$8,$H$5:$H$8,"") -> Every pay period (ongoing) | M30: {=MAX(_xlfn.XLOOKUP($A30,TRIM(SUBSTITUTE('worker file'!$A$2:$A$406,_xlfn.UNICHAR(160)," ")),'worker file'!$M$2:$M$406,0),_xlfn.XLOOKUP($B30,TRIM('pay group & schedule'!$A$2:$A$6),'pay group & schedule'!$D$2:$D$6,0))} -> 46299 | N30: {=_xlfn.LET(_xlpm.t,_xlfn.XLOOKUP($A30,TRIM(SUBSTITUTE('worker file'!$A$2:$A$406,_xlfn.UNICHAR(160)," ")),'worker file'!$N$2:$N$406,""),IF(N(_xlpm.t)=0,"",_xlpm.t))} -> 46312 | O30: Ongoing until term date; stop after final pay
A31: E0149 | B31: {=_xlfn.XLOOKUP($A31,TRIM(SUBSTITUTE('worker file'!$A$2:$A$406,_xlfn.UNICHAR(160)," ")),'worker file'!$L$2:$L$406,"Not found")} -> US Semi-monthly | C31: {=_xlfn.XLOOKUP($A31,TRIM(SUBSTITUTE('worker file'!$A$2:$A$406,_xlfn.UNICHAR(160)," ")),'worker file'!$D$2:$D$406,"Not found")} -> NY | D31: {=_xlfn.XLOOKUP($A31,TRIM(SUBSTITUTE('worker file'!$A$2:$A$406,_xlfn.UNICHAR(160)," ")),'worker file'!$Q$2:$Q$406,"Not found")} -> On Leave(unpaid) | E31: 401K_EE | F31: =_xlfn.XLOOKUP($E31,$A$5:$A$8,$B$5:$B$8,"") -> 401(k) Employee Deferral | G31: =_xlfn.XLOOKUP($E31,$A$5:$A$8,$D$5:$D$8,"") -> Pre-tax (exempt from FIT/SIT; subject to FICA) | H31: =_xlfn.XLOOKUP($E31,$A$5:$A$8,$E$5:$E$8,"") -> Percent | I31: 0.04 | J31: =IF($H31="Flat",_xlfn.XLOOKUP($E31,$A$5:$A$8,$F$5:$F$8,""),"") | K31: =_xlfn.XLOOKUP($E31,$A$5:$A$8,$G$5:$G$8,"") -> Gross pay | L31: =_xlfn.XLOOKUP($E31,$A$5:$A$8,$H$5:$H$8,"") -> Every pay period (ongoing) | M31: {=MAX(_xlfn.XLOOKUP($A31,TRIM(SUBSTITUTE('worker file'!$A$2:$A$406,_xlfn.UNICHAR(160)," ")),'worker file'!$M$2:$M$406,0),_xlfn.XLOOKUP($B31,TRIM('pay group & schedule'!$A$2:$A$6),'pay group & schedule'!$D$2:$D$6,0))} -> 46311 | N31: {=_xlfn.LET(_xlpm.t,_xlfn.XLOOKUP($A31,TRIM(SUBSTITUTE('worker file'!$A$2:$A$406,_xlfn.UNICHAR(160)," ")),'worker file'!$N$2:$N$406,""),IF(N(_xlpm.t)=0,"",_xlpm.t))} | O31: Unpaid leave – no gross; deduction suspends, arrears per policy
A32: E0149 | B32: {=_xlfn.XLOOKUP($A32,TRIM(SUBSTITUTE('worker file'!$A$2:$A$406,_xlfn.UNICHAR(160)," ")),'worker file'!$L$2:$L$406,"Not found")} -> US Semi-monthly | C32: {=_xlfn.XLOOKUP($A32,TRIM(SUBSTITUTE('worker file'!$A$2:$A$406,_xlfn.UNICHAR(160)," ")),'worker file'!$D$2:$D$406,"Not found")} -> NY | D32: {=_xlfn.XLOOKUP($A32,TRIM(SUBSTITUTE('worker file'!$A$2:$A$406,_xlfn.UNICHAR(160)," ")),'worker file'!$Q$2:$Q$406,"Not found")} -> On Leave(unpaid) | E32: MED_EE | F32: =_xlfn.XLOOKUP($E32,$A$5:$A$8,$B$5:$B$8,"") -> Medical (Health) – Employee | G32: =_xlfn.XLOOKUP($E32,$A$5:$A$8,$D$5:$D$8,"") -> Pre-tax Section 125 (exempt from FIT/SIT/FICA) | H32: =_xlfn.XLOOKUP($E32,$A$5:$A$8,$E$5:$E$8,"") -> Flat | I32: =IF($H32="Percent",_xlfn.XLOOKUP($E32,$A$5:$A$8,$F$5:$F$8,""),"") | J32: =IF($H32="Flat",_xlfn.XLOOKUP($E32,$A$5:$A$8,$F$5:$F$8,""),"") -> 200 | K32: =_xlfn.XLOOKUP($E32,$A$5:$A$8,$G$5:$G$8,"") -> Per pay period | L32: =_xlfn.XLOOKUP($E32,$A$5:$A$8,$H$5:$H$8,"") -> Every pay period (ongoing) | M32: {=MAX(_xlfn.XLOOKUP($A32,TRIM(SUBSTITUTE('worker file'!$A$2:$A$406,_xlfn.UNICHAR(160)," ")),'worker file'!$M$2:$M$406,0),_xlfn.XLOOKUP($B32,TRIM('pay group & schedule'!$A$2:$A$6),'pay group & schedule'!$D$2:$D$6,0))} -> 46311 | N32: {=_xlfn.LET(_xlpm.t,_xlfn.XLOOKUP($A32,TRIM(SUBSTITUTE('worker file'!$A$2:$A$406,_xlfn.UNICHAR(160)," ")),'worker file'!$N$2:$N$406,""),IF(N(_xlpm.t)=0,"",_xlpm.t))} | O32: Unpaid leave – no gross; deduction suspends, arrears per policy
A33: E0149 | B33: {=_xlfn.XLOOKUP($A33,TRIM(SUBSTITUTE('worker file'!$A$2:$A$406,_xlfn.UNICHAR(160)," ")),'worker file'!$L$2:$L$406,"Not found")} -> US Semi-monthly | C33: {=_xlfn.XLOOKUP($A33,TRIM(SUBSTITUTE('worker file'!$A$2:$A$406,_xlfn.UNICHAR(160)," ")),'worker file'!$D$2:$D$406,"Not found")} -> NY | D33: {=_xlfn.XLOOKUP($A33,TRIM(SUBSTITUTE('worker file'!$A$2:$A$406,_xlfn.UNICHAR(160)," ")),'worker file'!$Q$2:$Q$406,"Not found")} -> On Leave(unpaid) | E33: DEN_EE | F33: =_xlfn.XLOOKUP($E33,$A$5:$A$8,$B$5:$B$8,"") -> Dental – Employee | G33: =_xlfn.XLOOKUP($E33,$A$5:$A$8,$D$5:$D$8,"") -> Pre-tax Section 125 (exempt from FIT/SIT/FICA) | H33: =_xlfn.XLOOKUP($E33,$A$5:$A$8,$E$5:$E$8,"") -> Flat | I33: =IF($H33="Percent",_xlfn.XLOOKUP($E33,$A$5:$A$8,$F$5:$F$8,""),"") | J33: =IF($H33="Flat",_xlfn.XLOOKUP($E33,$A$5:$A$8,$F$5:$F$8,""),"") -> 44 | K33: =_xlfn.XLOOKUP($E33,$A$5:$A$8,$G$5:$G$8,"") -> Per pay period | L33: =_xlfn.XLOOKUP($E33,$A$5:$A$8,$H$5:$H$8,"") -> Every pay period (ongoing) | M33: {=MAX(_xlfn.XLOOKUP($A33,TRIM(SUBSTITUTE('worker file'!$A$2:$A$406,_xlfn.UNICHAR(160)," ")),'worker file'!$M$2:$M$406,0),_xlfn.XLOOKUP($B33,TRIM('pay group & schedule'!$A$2:$A$6),'pay group & schedule'!$D$2:$D$6,0))} -> 46311 | N33: {=_xlfn.LET(_xlpm.t,_xlfn.XLOOKUP($A33,TRIM(SUBSTITUTE('worker file'!$A$2:$A$406,_xlfn.UNICHAR(160)," ")),'worker file'!$N$2:$N$406,""),IF(N(_xlpm.t)=0,"",_xlpm.t))} | O33: Unpaid leave – no gross; deduction suspends, arrears per policy
A34: E0149 | B34: {=_xlfn.XLOOKUP($A34,TRIM(SUBSTITUTE('worker file'!$A$2:$A$406,_xlfn.UNICHAR(160)," ")),'worker file'!$L$2:$L$406,"Not found")} -> US Semi-monthly | C34: {=_xlfn.XLOOKUP($A34,TRIM(SUBSTITUTE('worker file'!$A$2:$A$406,_xlfn.UNICHAR(160)," ")),'worker file'!$D$2:$D$406,"Not found")} -> NY | D34: {=_xlfn.XLOOKUP($A34,TRIM(SUBSTITUTE('worker file'!$A$2:$A$406,_xlfn.UNICHAR(160)," ")),'worker file'!$Q$2:$Q$406,"Not found")} -> On Leave(unpaid) | E34: VIS_EE | F34: =_xlfn.XLOOKUP($E34,$A$5:$A$8,$B$5:$B$8,"") -> Vision – Employee | G34: =_xlfn.XLOOKUP($E34,$A$5:$A$8,$D$5:$D$8,"") -> Pre-tax Section 125 (exempt from FIT/SIT/FICA) | H34: =_xlfn.XLOOKUP($E34,$A$5:$A$8,$E$5:$E$8,"") -> Flat | I34: =IF($H34="Percent",_xlfn.XLOOKUP($E34,$A$5:$A$8,$F$5:$F$8,""),"") | J34: =IF($H34="Flat",_xlfn.XLOOKUP($E34,$A$5:$A$8,$F$5:$F$8,""),"") -> 30 | K34: =_xlfn.XLOOKUP($E34,$A$5:$A$8,$G$5:$G$8,"") -> Per pay period | L34: =_xlfn.XLOOKUP($E34,$A$5:$A$8,$H$5:$H$8,"") -> Every pay period (ongoing) | M34: {=MAX(_xlfn.XLOOKUP($A34,TRIM(SUBSTITUTE('worker file'!$A$2:$A$406,_xlfn.UNICHAR(160)," ")),'worker file'!$M$2:$M$406,0),_xlfn.XLOOKUP($B34,TRIM('pay group & schedule'!$A$2:$A$6),'pay group & schedule'!$D$2:$D$6,0))} -> 46311 | N34: {=_xlfn.LET(_xlpm.t,_xlfn.XLOOKUP($A34,TRIM(SUBSTITUTE('worker file'!$A$2:$A$406,_xlfn.UNICHAR(160)," ")),'worker file'!$N$2:$N$406,""),IF(N(_xlpm.t)=0,"",_xlpm.t))} | O34: Unpaid leave – no gross; deduction suspends, arrears per policy
A35: E0203 | B35: {=_xlfn.XLOOKUP($A35,TRIM(SUBSTITUTE('worker file'!$A$2:$A$406,_xlfn.UNICHAR(160)," ")),'worker file'!$L$2:$L$406,"Not found")} -> US Semi-monthly | C35: {=_xlfn.XLOOKUP($A35,TRIM(SUBSTITUTE('worker file'!$A$2:$A$406,_xlfn.UNICHAR(160)," ")),'worker file'!$D$2:$D$406,"Not found")} -> CA | D35: {=_xlfn.XLOOKUP($A35,TRIM(SUBSTITUTE('worker file'!$A$2:$A$406,_xlfn.UNICHAR(160)," ")),'worker file'!$Q$2:$Q$406,"Not found")} -> New Hire | E35: 401K_EE | F35: =_xlfn.XLOOKUP($E35,$A$5:$A$8,$B$5:$B$8,"") -> 401(k) Employee Deferral | G35: =_xlfn.XLOOKUP($E35,$A$5:$A$8,$D$5:$D$8,"") -> Pre-tax (exempt from FIT/SIT; subject to FICA) | H35: =_xlfn.XLOOKUP($E35,$A$5:$A$8,$E$5:$E$8,"") -> Percent | I35: 0.01 | J35: =IF($H35="Flat",_xlfn.XLOOKUP($E35,$A$5:$A$8,$F$5:$F$8,""),"") | K35: =_xlfn.XLOOKUP($E35,$A$5:$A$8,$G$5:$G$8,"") -> Gross pay | L35: =_xlfn.XLOOKUP($E35,$A$5:$A$8,$H$5:$H$8,"") -> Every pay period (ongoing) | M35: {=MAX(_xlfn.XLOOKUP($A35,TRIM(SUBSTITUTE('worker file'!$A$2:$A$406,_xlfn.UNICHAR(160)," ")),'worker file'!$M$2:$M$406,0),_xlfn.XLOOKUP($B35,TRIM('pay group & schedule'!$A$2:$A$6),'pay group & schedule'!$D$2:$D$6,0))} -> 46316 | N35: {=_xlfn.LET(_xlpm.t,_xlfn.XLOOKUP($A35,TRIM(SUBSTITUTE('worker file'!$A$2:$A$406,_xlfn.UNICHAR(160)," ")),'worker file'!$N$2:$N$406,""),IF(N(_xlpm.t)=0,"",_xlpm.t))} | O35: New hire – start with first paycheck
A36: E0203 | B36: {=_xlfn.XLOOKUP($A36,TRIM(SUBSTITUTE('worker file'!$A$2:$A$406,_xlfn.UNICHAR(160)," ")),'worker file'!$L$2:$L$406,"Not found")} -> US Semi-monthly | C36: {=_xlfn.XLOOKUP($A36,TRIM(SUBSTITUTE('worker file'!$A$2:$A$406,_xlfn.UNICHAR(160)," ")),'worker file'!$D$2:$D$406,"Not found")} -> CA | D36: {=_xlfn.XLOOKUP($A36,TRIM(SUBSTITUTE('worker file'!$A$2:$A$406,_xlfn.UNICHAR(160)," ")),'worker file'!$Q$2:$Q$406,"Not found")} -> New Hire | E36: MED_EE | F36: =_xlfn.XLOOKUP($E36,$A$5:$A$8,$B$5:$B$8,"") -> Medical (Health) – Employee | G36: =_xlfn.XLOOKUP($E36,$A$5:$A$8,$D$5:$D$8,"") -> Pre-tax Section 125 (exempt from FIT/SIT/FICA) | H36: =_xlfn.XLOOKUP($E36,$A$5:$A$8,$E$5:$E$8,"") -> Flat | I36: =IF($H36="Percent",_xlfn.XLOOKUP($E36,$A$5:$A$8,$F$5:$F$8,""),"") | J36: =IF($H36="Flat",_xlfn.XLOOKUP($E36,$A$5:$A$8,$F$5:$F$8,""),"") -> 200 | K36: =_xlfn.XLOOKUP($E36,$A$5:$A$8,$G$5:$G$8,"") -> Per pay period | L36: =_xlfn.XLOOKUP($E36,$A$5:$A$8,$H$5:$H$8,"") -> Every pay period (ongoing) | M36: {=MAX(_xlfn.XLOOKUP($A36,TRIM(SUBSTITUTE('worker file'!$A$2:$A$406,_xlfn.UNICHAR(160)," ")),'worker file'!$M$2:$M$406,0),_xlfn.XLOOKUP($B36,TRIM('pay group & schedule'!$A$2:$A$6),'pay group & schedule'!$D$2:$D$6,0))} -> 46316 | N36: {=_xlfn.LET(_xlpm.t,_xlfn.XLOOKUP($A36,TRIM(SUBSTITUTE('worker file'!$A$2:$A$406,_xlfn.UNICHAR(160)," ")),'worker file'!$N$2:$N$406,""),IF(N(_xlpm.t)=0,"",_xlpm.t))} | O36: New hire – start with first paycheck
A37: E0203 | B37: {=_xlfn.XLOOKUP($A37,TRIM(SUBSTITUTE('worker file'!$A$2:$A$406,_xlfn.UNICHAR(160)," ")),'worker file'!$L$2:$L$406,"Not found")} -> US Semi-monthly | C37: {=_xlfn.XLOOKUP($A37,TRIM(SUBSTITUTE('worker file'!$A$2:$A$406,_xlfn.UNICHAR(160)," ")),'worker file'!$D$2:$D$406,"Not found")} -> CA | D37: {=_xlfn.XLOOKUP($A37,TRIM(SUBSTITUTE('worker file'!$A$2:$A$406,_xlfn.UNICHAR(160)," ")),'worker file'!$Q$2:$Q$406,"Not found")} -> New Hire | E37: DEN_EE | F37: =_xlfn.XLOOKUP($E37,$A$5:$A$8,$B$5:$B$8,"") -> Dental – Employee | G37: =_xlfn.XLOOKUP($E37,$A$5:$A$8,$D$5:$D$8,"") -> Pre-tax Section 125 (exempt from FIT/SIT/FICA) | H37: =_xlfn.XLOOKUP($E37,$A$5:$A$8,$E$5:$E$8,"") -> Flat | I37: =IF($H37="Percent",_xlfn.XLOOKUP($E37,$A$5:$A$8,$F$5:$F$8,""),"") | J37: =IF($H37="Flat",_xlfn.XLOOKUP($E37,$A$5:$A$8,$F$5:$F$8,""),"") -> 44 | K37: =_xlfn.XLOOKUP($E37,$A$5:$A$8,$G$5:$G$8,"") -> Per pay period | L37: =_xlfn.XLOOKUP($E37,$A$5:$A$8,$H$5:$H$8,"") -> Every pay period (ongoing) | M37: {=MAX(_xlfn.XLOOKUP($A37,TRIM(SUBSTITUTE('worker file'!$A$2:$A$406,_xlfn.UNICHAR(160)," ")),'worker file'!$M$2:$M$406,0),_xlfn.XLOOKUP($B37,TRIM('pay group & schedule'!$A$2:$A$6),'pay group & schedule'!$D$2:$D$6,0))} -> 46316 | N37: {=_xlfn.LET(_xlpm.t,_xlfn.XLOOKUP($A37,TRIM(SUBSTITUTE('worker file'!$A$2:$A$406,_xlfn.UNICHAR(160)," ")),'worker file'!$N$2:$N$406,""),IF(N(_xlpm.t)=0,"",_xlpm.t))} | O37: New hire – start with first paycheck
A38: E0203 | B38: {=_xlfn.XLOOKUP($A38,TRIM(SUBSTITUTE('worker file'!$A$2:$A$406,_xlfn.UNICHAR(160)," ")),'worker file'!$L$2:$L$406,"Not found")} -> US Semi-monthly | C38: {=_xlfn.XLOOKUP($A38,TRIM(SUBSTITUTE('worker file'!$A$2:$A$406,_xlfn.UNICHAR(160)," ")),'worker file'!$D$2:$D$406,"Not found")} -> CA | D38: {=_xlfn.XLOOKUP($A38,TRIM(SUBSTITUTE('worker file'!$A$2:$A$406,_xlfn.UNICHAR(160)," ")),'worker file'!$Q$2:$Q$406,"Not found")} -> New Hire | E38: VIS_EE | F38: =_xlfn.XLOOKUP($E38,$A$5:$A$8,$B$5:$B$8,"") -> Vision – Employee | G38: =_xlfn.XLOOKUP($E38,$A$5:$A$8,$D$5:$D$8,"") -> Pre-tax Section 125 (exempt from FIT/SIT/FICA) | H38: =_xlfn.XLOOKUP($E38,$A$5:$A$8,$E$5:$E$8,"") -> Flat | I38: =IF($H38="Percent",_xlfn.XLOOKUP($E38,$A$5:$A$8,$F$5:$F$8,""),"") | J38: =IF($H38="Flat",_xlfn.XLOOKUP($E38,$A$5:$A$8,$F$5:$F$8,""),"") -> 30 | K38: =_xlfn.XLOOKUP($E38,$A$5:$A$8,$G$5:$G$8,"") -> Per pay period | L38: =_xlfn.XLOOKUP($E38,$A$5:$A$8,$H$5:$H$8,"") -> Every pay period (ongoing) | M38: {=MAX(_xlfn.XLOOKUP($A38,TRIM(SUBSTITUTE('worker file'!$A$2:$A$406,_xlfn.UNICHAR(160)," ")),'worker file'!$M$2:$M$406,0),_xlfn.XLOOKUP($B38,TRIM('pay group & schedule'!$A$2:$A$6),'pay group & schedule'!$D$2:$D$6,0))} -> 46316 | N38: {=_xlfn.LET(_xlpm.t,_xlfn.XLOOKUP($A38,TRIM(SUBSTITUTE('worker file'!$A$2:$A$406,_xlfn.UNICHAR(160)," ")),'worker file'!$N$2:$N$406,""),IF(N(_xlpm.t)=0,"",_xlpm.t))} | O38: New hire – start with first paycheck
A39: E0000 | B39: {=_xlfn.XLOOKUP($A39,TRIM(SUBSTITUTE('worker file'!$A$2:$A$406,_xlfn.UNICHAR(160)," ")),'worker file'!$L$2:$L$406,"Not found")} -> US Semi-monthly | C39: {=_xlfn.XLOOKUP($A39,TRIM(SUBSTITUTE('worker file'!$A$2:$A$406,_xlfn.UNICHAR(160)," ")),'worker file'!$D$2:$D$406,"Not found")} -> CA | D39: {=_xlfn.XLOOKUP($A39,TRIM(SUBSTITUTE('worker file'!$A$2:$A$406,_xlfn.UNICHAR(160)," ")),'worker file'!$Q$2:$Q$406,"Not found")} -> Active | E39: 401K_EE | F39: =_xlfn.XLOOKUP($E39,$A$5:$A$8,$B$5:$B$8,"") -> 401(k) Employee Deferral | G39: =_xlfn.XLOOKUP($E39,$A$5:$A$8,$D$5:$D$8,"") -> Pre-tax (exempt from FIT/SIT; subject to FICA) | H39: =_xlfn.XLOOKUP($E39,$A$5:$A$8,$E$5:$E$8,"") -> Percent | I39: 0.06 | J39: =IF($H39="Flat",_xlfn.XLOOKUP($E39,$A$5:$A$8,$F$5:$F$8,""),"") | K39: =_xlfn.XLOOKUP($E39,$A$5:$A$8,$G$5:$G$8,"") -> Gross pay | L39: =_xlfn.XLOOKUP($E39,$A$5:$A$8,$H$5:$H$8,"") -> Every pay period (ongoing) | M39: {=MAX(_xlfn.XLOOKUP($A39,TRIM(SUBSTITUTE('worker file'!$A$2:$A$406,_xlfn.UNICHAR(160)," ")),'worker file'!$M$2:$M$406,0),_xlfn.XLOOKUP($B39,TRIM('pay group & schedule'!$A$2:$A$6),'pay group & schedule'!$D$2:$D$6,0))} -> 46311 | N39: {=_xlfn.LET(_xlpm.t,_xlfn.XLOOKUP($A39,TRIM(SUBSTITUTE('worker file'!$A$2:$A$406,_xlfn.UNICHAR(160)," ")),'worker file'!$N$2:$N$406,""),IF(N(_xlpm.t)=0,"",_xlpm.t))}
A40: E0000 | B40: {=_xlfn.XLOOKUP($A40,TRIM(SUBSTITUTE('worker file'!$A$2:$A$406,_xlfn.UNICHAR(160)," ")),'worker file'!$L$2:$L$406,"Not found")} -> US Semi-monthly | C40: {=_xlfn.XLOOKUP($A40,TRIM(SUBSTITUTE('worker file'!$A$2:$A$406,_xlfn.UNICHAR(160)," ")),'worker file'!$D$2:$D$406,"Not found")} -> CA | D40: {=_xlfn.XLOOKUP($A40,TRIM(SUBSTITUTE('worker file'!$A$2:$A$406,_xlfn.UNICHAR(160)," ")),'worker file'!$Q$2:$Q$406,"Not found")} -> Active | E40: MED_EE | F40: =_xlfn.XLOOKUP($E40,$A$5:$A$8,$B$5:$B$8,"") -> Medical (Health) – Employee | G40: =_xlfn.XLOOKUP($E40,$A$5:$A$8,$D$5:$D$8,"") -> Pre-tax Section 125 (exempt from FIT/SIT/FICA) | H40: =_xlfn.XLOOKUP($E40,$A$5:$A$8,$E$5:$E$8,"") -> Flat | I40: =IF($H40="Percent",_xlfn.XLOOKUP($E40,$A$5:$A$8,$F$5:$F$8,""),"") | J40: =IF($H40="Flat",_xlfn.XLOOKUP($E40,$A$5:$A$8,$F$5:$F$8,""),"") -> 200 | K40: =_xlfn.XLOOKUP($E40,$A$5:$A$8,$G$5:$G$8,"") -> Per pay period | L40: =_xlfn.XLOOKUP($E40,$A$5:$A$8,$H$5:$H$8,"") -> Every pay period (ongoing) | M40: {=MAX(_xlfn.XLOOKUP($A40,TRIM(SUBSTITUTE('worker file'!$A$2:$A$406,_xlfn.UNICHAR(160)," ")),'worker file'!$M$2:$M$406,0),_xlfn.XLOOKUP($B40,TRIM('pay group & schedule'!$A$2:$A$6),'pay group & schedule'!$D$2:$D$6,0))} -> 46311 | N40: {=_xlfn.LET(_xlpm.t,_xlfn.XLOOKUP($A40,TRIM(SUBSTITUTE('worker file'!$A$2:$A$406,_xlfn.UNICHAR(160)," ")),'worker file'!$N$2:$N$406,""),IF(N(_xlpm.t)=0,"",_xlpm.t))}
A41: E0000 | B41: {=_xlfn.XLOOKUP($A41,TRIM(SUBSTITUTE('worker file'!$A$2:$A$406,_xlfn.UNICHAR(160)," ")),'worker file'!$L$2:$L$406,"Not found")} -> US Semi-monthly | C41: {=_xlfn.XLOOKUP($A41,TRIM(SUBSTITUTE('worker file'!$A$2:$A$406,_xlfn.UNICHAR(160)," ")),'worker file'!$D$2:$D$406,"Not found")} -> CA | D41: {=_xlfn.XLOOKUP($A41,TRIM(SUBSTITUTE('worker file'!$A$2:$A$406,_xlfn.UNICHAR(160)," ")),'worker file'!$Q$2:$Q$406,"Not found")} -> Active | E41: DEN_EE | F41: =_xlfn.XLOOKUP($E41,$A$5:$A$8,$B$5:$B$8,"") -> Dental – Employee | G41: =_xlfn.XLOOKUP($E41,$A$5:$A$8,$D$5:$D$8,"") -> Pre-tax Section 125 (exempt from FIT/SIT/FICA) | H41: =_xlfn.XLOOKUP($E41,$A$5:$A$8,$E$5:$E$8,"") -> Flat | I41: =IF($H41="Percent",_xlfn.XLOOKUP($E41,$A$5:$A$8,$F$5:$F$8,""),"") | J41: =IF($H41="Flat",_xlfn.XLOOKUP($E41,$A$5:$A$8,$F$5:$F$8,""),"") -> 44 | K41: =_xlfn.XLOOKUP($E41,$A$5:$A$8,$G$5:$G$8,"") -> Per pay period | L41: =_xlfn.XLOOKUP($E41,$A$5:$A$8,$H$5:$H$8,"") -> Every pay period (ongoing) | M41: {=MAX(_xlfn.XLOOKUP($A41,TRIM(SUBSTITUTE('worker file'!$A$2:$A$406,_xlfn.UNICHAR(160)," ")),'worker file'!$M$2:$M$406,0),_xlfn.XLOOKUP($B41,TRIM('pay group & schedule'!$A$2:$A$6),'pay group & schedule'!$D$2:$D$6,0))} -> 46311 | N41: {=_xlfn.LET(_xlpm.t,_xlfn.XLOOKUP($A41,TRIM(SUBSTITUTE('worker file'!$A$2:$A$406,_xlfn.UNICHAR(160)," ")),'worker file'!$N$2:$N$406,""),IF(N(_xlpm.t)=0,"",_xlpm.t))}
A42: E0000 | B42: {=_xlfn.XLOOKUP($A42,TRIM(SUBSTITUTE('worker file'!$A$2:$A$406,_xlfn.UNICHAR(160)," ")),'worker file'!$L$2:$L$406,"Not found")} -> US Semi-monthly | C42: {=_xlfn.XLOOKUP($A42,TRIM(SUBSTITUTE('worker file'!$A$2:$A$406,_xlfn.UNICHAR(160)," ")),'worker file'!$D$2:$D$406,"Not found")} -> CA | D42: {=_xlfn.XLOOKUP($A42,TRIM(SUBSTITUTE('worker file'!$A$2:$A$406,_xlfn.UNICHAR(160)," ")),'worker file'!$Q$2:$Q$406,"Not found")} -> Active | E42: VIS_EE | F42: =_xlfn.XLOOKUP($E42,$A$5:$A$8,$B$5:$B$8,"") -> Vision – Employee | G42: =_xlfn.XLOOKUP($E42,$A$5:$A$8,$D$5:$D$8,"") -> Pre-tax Section 125 (exempt from FIT/SIT/FICA) | H42: =_xlfn.XLOOKUP($E42,$A$5:$A$8,$E$5:$E$8,"") -> Flat | I42: =IF($H42="Percent",_xlfn.XLOOKUP($E42,$A$5:$A$8,$F$5:$F$8,""),"") | J42: =IF($H42="Flat",_xlfn.XLOOKUP($E42,$A$5:$A$8,$F$5:$F$8,""),"") -> 30 | K42: =_xlfn.XLOOKUP($E42,$A$5:$A$8,$G$5:$G$8,"") -> Per pay period | L42: =_xlfn.XLOOKUP($E42,$A$5:$A$8,$H$5:$H$8,"") -> Every pay period (ongoing) | M42: {=MAX(_xlfn.XLOOKUP($A42,TRIM(SUBSTITUTE('worker file'!$A$2:$A$406,_xlfn.UNICHAR(160)," ")),'worker file'!$M$2:$M$406,0),_xlfn.XLOOKUP($B42,TRIM('pay group & schedule'!$A$2:$A$6),'pay group & schedule'!$D$2:$D$6,0))} -> 46311 | N42: {=_xlfn.LET(_xlpm.t,_xlfn.XLOOKUP($A42,TRIM(SUBSTITUTE('worker file'!$A$2:$A$406,_xlfn.UNICHAR(160)," ")),'worker file'!$N$2:$N$406,""),IF(N(_xlpm.t)=0,"",_xlpm.t))}
A43: E0002 | B43: {=_xlfn.XLOOKUP($A43,TRIM(SUBSTITUTE('worker file'!$A$2:$A$406,_xlfn.UNICHAR(160)," ")),'worker file'!$L$2:$L$406,"Not found")} -> US Semi-monthly | C43: {=_xlfn.XLOOKUP($A43,TRIM(SUBSTITUTE('worker file'!$A$2:$A$406,_xlfn.UNICHAR(160)," ")),'worker file'!$D$2:$D$406,"Not found")} -> CA | D43: {=_xlfn.XLOOKUP($A43,TRIM(SUBSTITUTE('worker file'!$A$2:$A$406,_xlfn.UNICHAR(160)," ")),'worker file'!$Q$2:$Q$406,"Not found")} -> Active | E43: 401K_EE | F43: =_xlfn.XLOOKUP($E43,$A$5:$A$8,$B$5:$B$8,"") -> 401(k) Employee Deferral | G43: =_xlfn.XLOOKUP($E43,$A$5:$A$8,$D$5:$D$8,"") -> Pre-tax (exempt from FIT/SIT; subject to FICA) | H43: =_xlfn.XLOOKUP($E43,$A$5:$A$8,$E$5:$E$8,"") -> Percent | I43: 0.03 | J43: =IF($H43="Flat",_xlfn.XLOOKUP($E43,$A$5:$A$8,$F$5:$F$8,""),"") | K43: =_xlfn.XLOOKUP($E43,$A$5:$A$8,$G$5:$G$8,"") -> Gross pay | L43: =_xlfn.XLOOKUP($E43,$A$5:$A$8,$H$5:$H$8,"") -> Every pay period (ongoing) | M43: {=MAX(_xlfn.XLOOKUP($A43,TRIM(SUBSTITUTE('worker file'!$A$2:$A$406,_xlfn.UNICHAR(160)," ")),'worker file'!$M$2:$M$406,0),_xlfn.XLOOKUP($B43,TRIM('pay group & schedule'!$A$2:$A$6),'pay group & schedule'!$D$2:$D$6,0))} -> 46311 | N43: {=_xlfn.LET(_xlpm.t,_xlfn.XLOOKUP($A43,TRIM(SUBSTITUTE('worker file'!$A$2:$A$406,_xlfn.UNICHAR(160)," ")),'worker file'!$N$2:$N$406,""),IF(N(_xlpm.t)=0,"",_xlpm.t))}
A44: E0002 | B44: {=_xlfn.XLOOKUP($A44,TRIM(SUBSTITUTE('worker file'!$A$2:$A$406,_xlfn.UNICHAR(160)," ")),'worker file'!$L$2:$L$406,"Not found")} -> US Semi-monthly | C44: {=_xlfn.XLOOKUP($A44,TRIM(SUBSTITUTE('worker file'!$A$2:$A$406,_xlfn.UNICHAR(160)," ")),'worker file'!$D$2:$D$406,"Not found")} -> CA | D44: {=_xlfn.XLOOKUP($A44,TRIM(SUBSTITUTE('worker file'!$A$2:$A$406,_xlfn.UNICHAR(160)," ")),'worker file'!$Q$2:$Q$406,"Not found")} -> Active | E44: MED_EE | F44: =_xlfn.XLOOKUP($E44,$A$5:$A$8,$B$5:$B$8,"") -> Medical (Health) – Employee | G44: =_xlfn.XLOOKUP($E44,$A$5:$A$8,$D$5:$D$8,"") -> Pre-tax Section 125 (exempt from FIT/SIT/FICA) | H44: =_xlfn.XLOOKUP($E44,$A$5:$A$8,$E$5:$E$8,"") -> Flat | I44: =IF($H44="Percent",_xlfn.XLOOKUP($E44,$A$5:$A$8,$F$5:$F$8,""),"") | J44: =IF($H44="Flat",_xlfn.XLOOKUP($E44,$A$5:$A$8,$F$5:$F$8,""),"") -> 200 | K44: =_xlfn.XLOOKUP($E44,$A$5:$A$8,$G$5:$G$8,"") -> Per pay period | L44: =_xlfn.XLOOKUP($E44,$A$5:$A$8,$H$5:$H$8,"") -> Every pay period (ongoing) | M44: {=MAX(_xlfn.XLOOKUP($A44,TRIM(SUBSTITUTE('worker file'!$A$2:$A$406,_xlfn.UNICHAR(160)," ")),'worker file'!$M$2:$M$406,0),_xlfn.XLOOKUP($B44,TRIM('pay group & schedule'!$A$2:$A$6),'pay group & schedule'!$D$2:$D$6,0))} -> 46311 | N44: {=_xlfn.LET(_xlpm.t,_xlfn.XLOOKUP($A44,TRIM(SUBSTITUTE('worker file'!$A$2:$A$406,_xlfn.UNICHAR(160)," ")),'worker file'!$N$2:$N$406,""),IF(N(_xlpm.t)=0,"",_xlpm.t))}
A45: E0002 | B45: {=_xlfn.XLOOKUP($A45,TRIM(SUBSTITUTE('worker file'!$A$2:$A$406,_xlfn.UNICHAR(160)," ")),'worker file'!$L$2:$L$406,"Not found")} -> US Semi-monthly | C45: {=_xlfn.XLOOKUP($A45,TRIM(SUBSTITUTE('worker file'!$A$2:$A$406,_xlfn.UNICHAR(160)," ")),'worker file'!$D$2:$D$406,"Not found")} -> CA | D45: {=_xlfn.XLOOKUP($A45,TRIM(SUBSTITUTE('worker file'!$A$2:$A$406,_xlfn.UNICHAR(160)," ")),'worker file'!$Q$2:$Q$406,"Not found")} -> Active | E45: DEN_EE | F45: =_xlfn.XLOOKUP($E45,$A$5:$A$8,$B$5:$B$8,"") -> Dental – Employee | G45: =_xlfn.XLOOKUP($E45,$A$5:$A$8,$D$5:$D$8,"") -> Pre-tax Section 125 (exempt from FIT/SIT/FICA) | H45: =_xlfn.XLOOKUP($E45,$A$5:$A$8,$E$5:$E$8,"") -> Flat | I45: =IF($H45="Percent",_xlfn.XLOOKUP($E45,$A$5:$A$8,$F$5:$F$8,""),"") | J45: =IF($H45="Flat",_xlfn.XLOOKUP($E45,$A$5:$A$8,$F$5:$F$8,""),"") -> 44 | K45: =_xlfn.XLOOKUP($E45,$A$5:$A$8,$G$5:$G$8,"") -> Per pay period | L45: =_xlfn.XLOOKUP($E45,$A$5:$A$8,$H$5:$H$8,"") -> Every pay period (ongoing) | M45: {=MAX(_xlfn.XLOOKUP($A45,TRIM(SUBSTITUTE('worker file'!$A$2:$A$406,_xlfn.UNICHAR(160)," ")),'worker file'!$M$2:$M$406,0),_xlfn.XLOOKUP($B45,TRIM('pay group & schedule'!$A$2:$A$6),'pay group & schedule'!$D$2:$D$6,0))} -> 46311 | N45: {=_xlfn.LET(_xlpm.t,_xlfn.XLOOKUP($A45,TRIM(SUBSTITUTE('worker file'!$A$2:$A$406,_xlfn.UNICHAR(160)," ")),'worker file'!$N$2:$N$406,""),IF(N(_xlpm.t)=0,"",_xlpm.t))}
A46: E0002 | B46: {=_xlfn.XLOOKUP($A46,TRIM(SUBSTITUTE('worker file'!$A$2:$A$406,_xlfn.UNICHAR(160)," ")),'worker file'!$L$2:$L$406,"Not found")} -> US Semi-monthly | C46: {=_xlfn.XLOOKUP($A46,TRIM(SUBSTITUTE('worker file'!$A$2:$A$406,_xlfn.UNICHAR(160)," ")),'worker file'!$D$2:$D$406,"Not found")} -> CA | D46: {=_xlfn.XLOOKUP($A46,TRIM(SUBSTITUTE('worker file'!$A$2:$A$406,_xlfn.UNICHAR(160)," ")),'worker file'!$Q$2:$Q$406,"Not found")} -> Active | E46: VIS_EE | F46: =_xlfn.XLOOKUP($E46,$A$5:$A$8,$B$5:$B$8,"") -> Vision – Employee | G46: =_xlfn.XLOOKUP($E46,$A$5:$A$8,$D$5:$D$8,"") -> Pre-tax Section 125 (exempt from FIT/SIT/FICA) | H46: =_xlfn.XLOOKUP($E46,$A$5:$A$8,$E$5:$E$8,"") -> Flat | I46: =IF($H46="Percent",_xlfn.XLOOKUP($E46,$A$5:$A$8,$F$5:$F$8,""),"") | J46: =IF($H46="Flat",_xlfn.XLOOKUP($E46,$A$5:$A$8,$F$5:$F$8,""),"") -> 30 | K46: =_xlfn.XLOOKUP($E46,$A$5:$A$8,$G$5:$G$8,"") -> Per pay period | L46: =_xlfn.XLOOKUP($E46,$A$5:$A$8,$H$5:$H$8,"") -> Every pay period (ongoing) | M46: {=MAX(_xlfn.XLOOKUP($A46,TRIM(SUBSTITUTE('worker file'!$A$2:$A$406,_xlfn.UNICHAR(160)," ")),'worker file'!$M$2:$M$406,0),_xlfn.XLOOKUP($B46,TRIM('pay group & schedule'!$A$2:$A$6),'pay group & schedule'!$D$2:$D$6,0))} -> 46311 | N46: {=_xlfn.LET(_xlpm.t,_xlfn.XLOOKUP($A46,TRIM(SUBSTITUTE('worker file'!$A$2:$A$406,_xlfn.UNICHAR(160)," ")),'worker file'!$N$2:$N$406,""),IF(N(_xlpm.t)=0,"",_xlpm.t))}
A47: E0003 | B47: {=_xlfn.XLOOKUP($A47,TRIM(SUBSTITUTE('worker file'!$A$2:$A$406,_xlfn.UNICHAR(160)," ")),'worker file'!$L$2:$L$406,"Not found")} -> US Semi-monthly | C47: {=_xlfn.XLOOKUP($A47,TRIM(SUBSTITUTE('worker file'!$A$2:$A$406,_xlfn.UNICHAR(160)," ")),'worker file'!$D$2:$D$406,"Not found")} -> WA | D47: {=_xlfn.XLOOKUP($A47,TRIM(SUBSTITUTE('worker file'!$A$2:$A$406,_xlfn.UNICHAR(160)," ")),'worker file'!$Q$2:$Q$406,"Not found")} -> Active | E47: 401K_EE | F47: =_xlfn.XLOOKUP($E47,$A$5:$A$8,$B$5:$B$8,"") -> 401(k) Employee Deferral | G47: =_xlfn.XLOOKUP($E47,$A$5:$A$8,$D$5:$D$8,"") -> Pre-tax (exempt from FIT/SIT; subject to FICA) | H47: =_xlfn.XLOOKUP($E47,$A$5:$A$8,$E$5:$E$8,"") -> Percent | I47: 0 | J47: =IF($H47="Flat",_xlfn.XLOOKUP($E47,$A$5:$A$8,$F$5:$F$8,""),"") | K47: =_xlfn.XLOOKUP($E47,$A$5:$A$8,$G$5:$G$8,"") -> Gross pay | L47: =_xlfn.XLOOKUP($E47,$A$5:$A$8,$H$5:$H$8,"") -> Every pay period (ongoing) | M47: {=MAX(_xlfn.XLOOKUP($A47,TRIM(SUBSTITUTE('worker file'!$A$2:$A$406,_xlfn.UNICHAR(160)," ")),'worker file'!$M$2:$M$406,0),_xlfn.XLOOKUP($B47,TRIM('pay group & schedule'!$A$2:$A$6),'pay group & schedule'!$D$2:$D$6,0))} -> 46311 | N47: {=_xlfn.LET(_xlpm.t,_xlfn.XLOOKUP($A47,TRIM(SUBSTITUTE('worker file'!$A$2:$A$406,_xlfn.UNICHAR(160)," ")),'worker file'!$N$2:$N$406,""),IF(N(_xlpm.t)=0,"",_xlpm.t))}
A48: E0003 | B48: {=_xlfn.XLOOKUP($A48,TRIM(SUBSTITUTE('worker file'!$A$2:$A$406,_xlfn.UNICHAR(160)," ")),'worker file'!$L$2:$L$406,"Not found")} -> US Semi-monthly | C48: {=_xlfn.XLOOKUP($A48,TRIM(SUBSTITUTE('worker file'!$A$2:$A$406,_xlfn.UNICHAR(160)," ")),'worker file'!$D$2:$D$406,"Not found")} -> WA | D48: {=_xlfn.XLOOKUP($A48,TRIM(SUBSTITUTE('worker file'!$A$2:$A$406,_xlfn.UNICHAR(160)," ")),'worker file'!$Q$2:$Q$406,"Not found")} -> Active | E48: MED_EE | F48: =_xlfn.XLOOKUP($E48,$A$5:$A$8,$B$5:$B$8,"") -> Medical (Health) – Employee | G48: =_xlfn.XLOOKUP($E48,$A$5:$A$8,$D$5:$D$8,"") -> Pre-tax Section 125 (exempt from FIT/SIT/FICA) | H48: =_xlfn.XLOOKUP($E48,$A$5:$A$8,$E$5:$E$8,"") -> Flat | I48: =IF($H48="Percent",_xlfn.XLOOKUP($E48,$A$5:$A$8,$F$5:$F$8,""),"") | J48: =IF($H48="Flat",_xlfn.XLOOKUP($E48,$A$5:$A$8,$F$5:$F$8,""),"") -> 200 | K48: =_xlfn.XLOOKUP($E48,$A$5:$A$8,$G$5:$G$8,"") -> Per pay period | L48: =_xlfn.XLOOKUP($E48,$A$5:$A$8,$H$5:$H$8,"") -> Every pay period (ongoing) | M48: {=MAX(_xlfn.XLOOKUP($A48,TRIM(SUBSTITUTE('worker file'!$A$2:$A$406,_xlfn.UNICHAR(160)," ")),'worker file'!$M$2:$M$406,0),_xlfn.XLOOKUP($B48,TRIM('pay group & schedule'!$A$2:$A$6),'pay group & schedule'!$D$2:$D$6,0))} -> 46311 | N48: {=_xlfn.LET(_xlpm.t,_xlfn.XLOOKUP($A48,TRIM(SUBSTITUTE('worker file'!$A$2:$A$406,_xlfn.UNICHAR(160)," ")),'worker file'!$N$2:$N$406,""),IF(N(_xlpm.t)=0,"",_xlpm.t))}
A49: E0003 | B49: {=_xlfn.XLOOKUP($A49,TRIM(SUBSTITUTE('worker file'!$A$2:$A$406,_xlfn.UNICHAR(160)," ")),'worker file'!$L$2:$L$406,"Not found")} -> US Semi-monthly | C49: {=_xlfn.XLOOKUP($A49,TRIM(SUBSTITUTE('worker file'!$A$2:$A$406,_xlfn.UNICHAR(160)," ")),'worker file'!$D$2:$D$406,"Not found")} -> WA | D49: {=_xlfn.XLOOKUP($A49,TRIM(SUBSTITUTE('worker file'!$A$2:$A$406,_xlfn.UNICHAR(160)," ")),'worker file'!$Q$2:$Q$406,"Not found")} -> Active | E49: DEN_EE | F49: =_xlfn.XLOOKUP($E49,$A$5:$A$8,$B$5:$B$8,"") -> Dental – Employee | G49: =_xlfn.XLOOKUP($E49,$A$5:$A$8,$D$5:$D$8,"") -> Pre-tax Section 125 (exempt from FIT/SIT/FICA) | H49: =_xlfn.XLOOKUP($E49,$A$5:$A$8,$E$5:$E$8,"") -> Flat | I49: =IF($H49="Percent",_xlfn.XLOOKUP($E49,$A$5:$A$8,$F$5:$F$8,""),"") | J49: =IF($H49="Flat",_xlfn.XLOOKUP($E49,$A$5:$A$8,$F$5:$F$8,""),"") -> 44 | K49: =_xlfn.XLOOKUP($E49,$A$5:$A$8,$G$5:$G$8,"") -> Per pay period | L49: =_xlfn.XLOOKUP($E49,$A$5:$A$8,$H$5:$H$8,"") -> Every pay period (ongoing) | M49: {=MAX(_xlfn.XLOOKUP($A49,TRIM(SUBSTITUTE('worker file'!$A$2:$A$406,_xlfn.UNICHAR(160)," ")),'worker file'!$M$2:$M$406,0),_xlfn.XLOOKUP($B49,TRIM('pay group & schedule'!$A$2:$A$6),'pay group & schedule'!$D$2:$D$6,0))} -> 46311 | N49: {=_xlfn.LET(_xlpm.t,_xlfn.XLOOKUP($A49,TRIM(SUBSTITUTE('worker file'!$A$2:$A$406,_xlfn.UNICHAR(160)," ")),'worker file'!$N$2:$N$406,""),IF(N(_xlpm.t)=0,"",_xlpm.t))}
A50: E0003 | B50: {=_xlfn.XLOOKUP($A50,TRIM(SUBSTITUTE('worker file'!$A$2:$A$406,_xlfn.UNICHAR(160)," ")),'worker file'!$L$2:$L$406,"Not found")} -> US Semi-monthly | C50: {=_xlfn.XLOOKUP($A50,TRIM(SUBSTITUTE('worker file'!$A$2:$A$406,_xlfn.UNICHAR(160)," ")),'worker file'!$D$2:$D$406,"Not found")} -> WA | D50: {=_xlfn.XLOOKUP($A50,TRIM(SUBSTITUTE('worker file'!$A$2:$A$406,_xlfn.UNICHAR(160)," ")),'worker file'!$Q$2:$Q$406,"Not found")} -> Active | E50: VIS_EE | F50: =_xlfn.XLOOKUP($E50,$A$5:$A$8,$B$5:$B$8,"") -> Vision – Employee | G50: =_xlfn.XLOOKUP($E50,$A$5:$A$8,$D$5:$D$8,"") -> Pre-tax Section 125 (exempt from FIT/SIT/FICA) | H50: =_xlfn.XLOOKUP($E50,$A$5:$A$8,$E$5:$E$8,"") -> Flat | I50: =IF($H50="Percent",_xlfn.XLOOKUP($E50,$A$5:$A$8,$F$5:$F$8,""),"") | J50: =IF($H50="Flat",_xlfn.XLOOKUP($E50,$A$5:$A$8,$F$5:$F$8,""),"") -> 30 | K50: =_xlfn.XLOOKUP($E50,$A$5:$A$8,$G$5:$G$8,"") -> Per pay period | L50: =_xlfn.XLOOKUP($E50,$A$5:$A$8,$H$5:$H$8,"") -> Every pay period (ongoing) | M50: {=MAX(_xlfn.XLOOKUP($A50,TRIM(SUBSTITUTE('worker file'!$A$2:$A$406,_xlfn.UNICHAR(160)," ")),'worker file'!$M$2:$M$406,0),_xlfn.XLOOKUP($B50,TRIM('pay group & schedule'!$A$2:$A$6),'pay group & schedule'!$D$2:$D$6,0))} -> 46311 | N50: {=_xlfn.LET(_xlpm.t,_xlfn.XLOOKUP($A50,TRIM(SUBSTITUTE('worker file'!$A$2:$A$406,_xlfn.UNICHAR(160)," ")),'worker file'!$N$2:$N$406,""),IF(N(_xlpm.t)=0,"",_xlpm.t))}
A51: E0005 | B51: {=_xlfn.XLOOKUP($A51,TRIM(SUBSTITUTE('worker file'!$A$2:$A$406,_xlfn.UNICHAR(160)," ")),'worker file'!$L$2:$L$406,"Not found")} -> US Semi-monthly | C51: {=_xlfn.XLOOKUP($A51,TRIM(SUBSTITUTE('worker file'!$A$2:$A$406,_xlfn.UNICHAR(160)," ")),'worker file'!$D$2:$D$406,"Not found")} -> TX | D51: {=_xlfn.XLOOKUP($A51,TRIM(SUBSTITUTE('worker file'!$A$2:$A$406,_xlfn.UNICHAR(160)," ")),'worker file'!$Q$2:$Q$406,"Not found")} -> Active | E51: 401K_EE | F51: =_xlfn.XLOOKUP($E51,$A$5:$A$8,$B$5:$B$8,"") -> 401(k) Employee Deferral | G51: =_xlfn.XLOOKUP($E51,$A$5:$A$8,$D$5:$D$8,"") -> Pre-tax (exempt from FIT/SIT; subject to FICA) | H51: =_xlfn.XLOOKUP($E51,$A$5:$A$8,$E$5:$E$8,"") -> Percent | I51: 0.05 | J51: =IF($H51="Flat",_xlfn.XLOOKUP($E51,$A$5:$A$8,$F$5:$F$8,""),"") | K51: =_xlfn.XLOOKUP($E51,$A$5:$A$8,$G$5:$G$8,"") -> Gross pay | L51: =_xlfn.XLOOKUP($E51,$A$5:$A$8,$H$5:$H$8,"") -> Every pay period (ongoing) | M51: {=MAX(_xlfn.XLOOKUP($A51,TRIM(SUBSTITUTE('worker file'!$A$2:$A$406,_xlfn.UNICHAR(160)," ")),'worker file'!$M$2:$M$406,0),_xlfn.XLOOKUP($B51,TRIM('pay group & schedule'!$A$2:$A$6),'pay group & schedule'!$D$2:$D$6,0))} -> 46311 | N51: {=_xlfn.LET(_xlpm.t,_xlfn.XLOOKUP($A51,TRIM(SUBSTITUTE('worker file'!$A$2:$A$406,_xlfn.UNICHAR(160)," ")),'worker file'!$N$2:$N$406,""),IF(N(_xlpm.t)=0,"",_xlpm.t))}
A52: E0005 | B52: {=_xlfn.XLOOKUP($A52,TRIM(SUBSTITUTE('worker file'!$A$2:$A$406,_xlfn.UNICHAR(160)," ")),'worker file'!$L$2:$L$406,"Not found")} -> US Semi-monthly | C52: {=_xlfn.XLOOKUP($A52,TRIM(SUBSTITUTE('worker file'!$A$2:$A$406,_xlfn.UNICHAR(160)," ")),'worker file'!$D$2:$D$406,"Not found")} -> TX | D52: {=_xlfn.XLOOKUP($A52,TRIM(SUBSTITUTE('worker file'!$A$2:$A$406,_xlfn.UNICHAR(160)," ")),'worker file'!$Q$2:$Q$406,"Not found")} -> Active | E52: MED_EE | F52: =_xlfn.XLOOKUP($E52,$A$5:$A$8,$B$5:$B$8,"") -> Medical (Health) – Employee | G52: =_xlfn.XLOOKUP($E52,$A$5:$A$8,$D$5:$D$8,"") -> Pre-tax Section 125 (exempt from FIT/SIT/FICA) | H52: =_xlfn.XLOOKUP($E52,$A$5:$A$8,$E$5:$E$8,"") -> Flat | I52: =IF($H52="Percent",_xlfn.XLOOKUP($E52,$A$5:$A$8,$F$5:$F$8,""),"") | J52: =IF($H52="Flat",_xlfn.XLOOKUP($E52,$A$5:$A$8,$F$5:$F$8,""),"") -> 200 | K52: =_xlfn.XLOOKUP($E52,$A$5:$A$8,$G$5:$G$8,"") -> Per pay period | L52: =_xlfn.XLOOKUP($E52,$A$5:$A$8,$H$5:$H$8,"") -> Every pay period (ongoing) | M52: {=MAX(_xlfn.XLOOKUP($A52,TRIM(SUBSTITUTE('worker file'!$A$2:$A$406,_xlfn.UNICHAR(160)," ")),'worker file'!$M$2:$M$406,0),_xlfn.XLOOKUP($B52,TRIM('pay group & schedule'!$A$2:$A$6),'pay group & schedule'!$D$2:$D$6,0))} -> 46311 | N52: {=_xlfn.LET(_xlpm.t,_xlfn.XLOOKUP($A52,TRIM(SUBSTITUTE('worker file'!$A$2:$A$406,_xlfn.UNICHAR(160)," ")),'worker file'!$N$2:$N$406,""),IF(N(_xlpm.t)=0,"",_xlpm.t))}
A53: E0005 | B53: {=_xlfn.XLOOKUP($A53,TRIM(SUBSTITUTE('worker file'!$A$2:$A$406,_xlfn.UNICHAR(160)," ")),'worker file'!$L$2:$L$406,"Not found")} -> US Semi-monthly | C53: {=_xlfn.XLOOKUP($A53,TRIM(SUBSTITUTE('worker file'!$A$2:$A$406,_xlfn.UNICHAR(160)," ")),'worker file'!$D$2:$D$406,"Not found")} -> TX | D53: {=_xlfn.XLOOKUP($A53,TRIM(SUBSTITUTE('worker file'!$A$2:$A$406,_xlfn.UNICHAR(160)," ")),'worker file'!$Q$2:$Q$406,"Not found")} -> Active | E53: DEN_EE | F53: =_xlfn.XLOOKUP($E53,$A$5:$A$8,$B$5:$B$8,"") -> Dental – Employee | G53: =_xlfn.XLOOKUP($E53,$A$5:$A$8,$D$5:$D$8,"") -> Pre-tax Section 125 (exempt from FIT/SIT/FICA) | H53: =_xlfn.XLOOKUP($E53,$A$5:$A$8,$E$5:$E$8,"") -> Flat | I53: =IF($H53="Percent",_xlfn.XLOOKUP($E53,$A$5:$A$8,$F$5:$F$8,""),"") | J53: =IF($H53="Flat",_xlfn.XLOOKUP($E53,$A$5:$A$8,$F$5:$F$8,""),"") -> 44 | K53: =_xlfn.XLOOKUP($E53,$A$5:$A$8,$G$5:$G$8,"") -> Per pay period | L53: =_xlfn.XLOOKUP($E53,$A$5:$A$8,$H$5:$H$8,"") -> Every pay period (ongoing) | M53: {=MAX(_xlfn.XLOOKUP($A53,TRIM(SUBSTITUTE('worker file'!$A$2:$A$406,_xlfn.UNICHAR(160)," ")),'worker file'!$M$2:$M$406,0),_xlfn.XLOOKUP($B53,TRIM('pay group & schedule'!$A$2:$A$6),'pay group & schedule'!$D$2:$D$6,0))} -> 46311 | N53: {=_xlfn.LET(_xlpm.t,_xlfn.XLOOKUP($A53,TRIM(SUBSTITUTE('worker file'!$A$2:$A$406,_xlfn.UNICHAR(160)," ")),'worker file'!$N$2:$N$406,""),IF(N(_xlpm.t)=0,"",_xlpm.t))}
A54: E0005 | B54: {=_xlfn.XLOOKUP($A54,TRIM(SUBSTITUTE('worker file'!$A$2:$A$406,_xlfn.UNICHAR(160)," ")),'worker file'!$L$2:$L$406,"Not found")} -> US Semi-monthly | C54: {=_xlfn.XLOOKUP($A54,TRIM(SUBSTITUTE('worker file'!$A$2:$A$406,_xlfn.UNICHAR(160)," ")),'worker file'!$D$2:$D$406,"Not found")} -> TX | D54: {=_xlfn.XLOOKUP($A54,TRIM(SUBSTITUTE('worker file'!$A$2:$A$406,_xlfn.UNICHAR(160)," ")),'worker file'!$Q$2:$Q$406,"Not found")} -> Active | E54: VIS_EE | F54: =_xlfn.XLOOKUP($E54,$A$5:$A$8,$B$5:$B$8,"") -> Vision – Employee | G54: =_xlfn.XLOOKUP($E54,$A$5:$A$8,$D$5:$D$8,"") -> Pre-tax Section 125 (exempt from FIT/SIT/FICA) | H54: =_xlfn.XLOOKUP($E54,$A$5:$A$8,$E$5:$E$8,"") -> Flat | I54: =IF($H54="Percent",_xlfn.XLOOKUP($E54,$A$5:$A$8,$F$5:$F$8,""),"") | J54: =IF($H54="Flat",_xlfn.XLOOKUP($E54,$A$5:$A$8,$F$5:$F$8,""),"") -> 30 | K54: =_xlfn.XLOOKUP($E54,$A$5:$A$8,$G$5:$G$8,"") -> Per pay period | L54: =_xlfn.XLOOKUP($E54,$A$5:$A$8,$H$5:$H$8,"") -> Every pay period (ongoing) | M54: {=MAX(_xlfn.XLOOKUP($A54,TRIM(SUBSTITUTE('worker file'!$A$2:$A$406,_xlfn.UNICHAR(160)," ")),'worker file'!$M$2:$M$406,0),_xlfn.XLOOKUP($B54,TRIM('pay group & schedule'!$A$2:$A$6),'pay group & schedule'!$D$2:$D$6,0))} -> 46311 | N54: {=_xlfn.LET(_xlpm.t,_xlfn.XLOOKUP($A54,TRIM(SUBSTITUTE('worker file'!$A$2:$A$406,_xlfn.UNICHAR(160)," ")),'worker file'!$N$2:$N$406,""),IF(N(_xlpm.t)=0,"",_xlpm.t))}
A55: E0007 | B55: {=_xlfn.XLOOKUP($A55,TRIM(SUBSTITUTE('worker file'!$A$2:$A$406,_xlfn.UNICHAR(160)," ")),'worker file'!$L$2:$L$406,"Not found")} -> US Semi-monthly | C55: {=_xlfn.XLOOKUP($A55,TRIM(SUBSTITUTE('worker file'!$A$2:$A$406,_xlfn.UNICHAR(160)," ")),'worker file'!$D$2:$D$406,"Not found")} -> TX | D55: {=_xlfn.XLOOKUP($A55,TRIM(SUBSTITUTE('worker file'!$A$2:$A$406,_xlfn.UNICHAR(160)," ")),'worker file'!$Q$2:$Q$406,"Not found")} -> Active | E55: MED_EE | F55: =_xlfn.XLOOKUP($E55,$A$5:$A$8,$B$5:$B$8,"") -> Medical (Health) – Employee | G55: =_xlfn.XLOOKUP($E55,$A$5:$A$8,$D$5:$D$8,"") -> Pre-tax Section 125 (exempt from FIT/SIT/FICA) | H55: =_xlfn.XLOOKUP($E55,$A$5:$A$8,$E$5:$E$8,"") -> Flat | I55: =IF($H55="Percent",_xlfn.XLOOKUP($E55,$A$5:$A$8,$F$5:$F$8,""),"") | J55: =IF($H55="Flat",_xlfn.XLOOKUP($E55,$A$5:$A$8,$F$5:$F$8,""),"") -> 200 | K55: =_xlfn.XLOOKUP($E55,$A$5:$A$8,$G$5:$G$8,"") -> Per pay period | L55: =_xlfn.XLOOKUP($E55,$A$5:$A$8,$H$5:$H$8,"") -> Every pay period (ongoing) | M55: {=MAX(_xlfn.XLOOKUP($A55,TRIM(SUBSTITUTE('worker file'!$A$2:$A$406,_xlfn.UNICHAR(160)," ")),'worker file'!$M$2:$M$406,0),_xlfn.XLOOKUP($B55,TRIM('pay group & schedule'!$A$2:$A$6),'pay group & schedule'!$D$2:$D$6,0))} -> 46311 | N55: {=_xlfn.LET(_xlpm.t,_xlfn.XLOOKUP($A55,TRIM(SUBSTITUTE('worker file'!$A$2:$A$406,_xlfn.UNICHAR(160)," ")),'worker file'!$N$2:$N$406,""),IF(N(_xlpm.t)=0,"",_xlpm.t))}
A56: E0007 | B56: {=_xlfn.XLOOKUP($A56,TRIM(SUBSTITUTE('worker file'!$A$2:$A$406,_xlfn.UNICHAR(160)," ")),'worker file'!$L$2:$L$406,"Not found")} -> US Semi-monthly | C56: {=_xlfn.XLOOKUP($A56,TRIM(SUBSTITUTE('worker file'!$A$2:$A$406,_xlfn.UNICHAR(160)," ")),'worker file'!$D$2:$D$406,"Not found")} -> TX | D56: {=_xlfn.XLOOKUP($A56,TRIM(SUBSTITUTE('worker file'!$A$2:$A$406,_xlfn.UNICHAR(160)," ")),'worker file'!$Q$2:$Q$406,"Not found")} -> Active | E56: DEN_EE | F56: =_xlfn.XLOOKUP($E56,$A$5:$A$8,$B$5:$B$8,"") -> Dental – Employee | G56: =_xlfn.XLOOKUP($E56,$A$5:$A$8,$D$5:$D$8,"") -> Pre-tax Section 125 (exempt from FIT/SIT/FICA) | H56: =_xlfn.XLOOKUP($E56,$A$5:$A$8,$E$5:$E$8,"") -> Flat | I56: =IF($H56="Percent",_xlfn.XLOOKUP($E56,$A$5:$A$8,$F$5:$F$8,""),"") | J56: =IF($H56="Flat",_xlfn.XLOOKUP($E56,$A$5:$A$8,$F$5:$F$8,""),"") -> 44 | K56: =_xlfn.XLOOKUP($E56,$A$5:$A$8,$G$5:$G$8,"") -> Per pay period | L56: =_xlfn.XLOOKUP($E56,$A$5:$A$8,$H$5:$H$8,"") -> Every pay period (ongoing) | M56: {=MAX(_xlfn.XLOOKUP($A56,TRIM(SUBSTITUTE('worker file'!$A$2:$A$406,_xlfn.UNICHAR(160)," ")),'worker file'!$M$2:$M$406,0),_xlfn.XLOOKUP($B56,TRIM('pay group & schedule'!$A$2:$A$6),'pay group & schedule'!$D$2:$D$6,0))} -> 46311 | N56: {=_xlfn.LET(_xlpm.t,_xlfn.XLOOKUP($A56,TRIM(SUBSTITUTE('worker file'!$A$2:$A$406,_xlfn.UNICHAR(160)," ")),'worker file'!$N$2:$N$406,""),IF(N(_xlpm.t)=0,"",_xlpm.t))}
A57: E0007 | B57: {=_xlfn.XLOOKUP($A57,TRIM(SUBSTITUTE('worker file'!$A$2:$A$406,_xlfn.UNICHAR(160)," ")),'worker file'!$L$2:$L$406,"Not found")} -> US Semi-monthly | C57: {=_xlfn.XLOOKUP($A57,TRIM(SUBSTITUTE('worker file'!$A$2:$A$406,_xlfn.UNICHAR(160)," ")),'worker file'!$D$2:$D$406,"Not found")} -> TX | D57: {=_xlfn.XLOOKUP($A57,TRIM(SUBSTITUTE('worker file'!$A$2:$A$406,_xlfn.UNICHAR(160)," ")),'worker file'!$Q$2:$Q$406,"Not found")} -> Active | E57: VIS_EE | F57: =_xlfn.XLOOKUP($E57,$A$5:$A$8,$B$5:$B$8,"") -> Vision – Employee | G57: =_xlfn.XLOOKUP($E57,$A$5:$A$8,$D$5:$D$8,"") -> Pre-tax Section 125 (exempt from FIT/SIT/FICA) | H57: =_xlfn.XLOOKUP($E57,$A$5:$A$8,$E$5:$E$8,"") -> Flat | I57: =IF($H57="Percent",_xlfn.XLOOKUP($E57,$A$5:$A$8,$F$5:$F$8,""),"") | J57: =IF($H57="Flat",_xlfn.XLOOKUP($E57,$A$5:$A$8,$F$5:$F$8,""),"") -> 30 | K57: =_xlfn.XLOOKUP($E57,$A$5:$A$8,$G$5:$G$8,"") -> Per pay period | L57: =_xlfn.XLOOKUP($E57,$A$5:$A$8,$H$5:$H$8,"") -> Every pay period (ongoing) | M57: {=MAX(_xlfn.XLOOKUP($A57,TRIM(SUBSTITUTE('worker file'!$A$2:$A$406,_xlfn.UNICHAR(160)," ")),'worker file'!$M$2:$M$406,0),_xlfn.XLOOKUP($B57,TRIM('pay group & schedule'!$A$2:$A$6),'pay group & schedule'!$D$2:$D$6,0))} -> 46311 | N57: {=_xlfn.LET(_xlpm.t,_xlfn.XLOOKUP($A57,TRIM(SUBSTITUTE('worker file'!$A$2:$A$406,_xlfn.UNICHAR(160)," ")),'worker file'!$N$2:$N$406,""),IF(N(_xlpm.t)=0,"",_xlpm.t))}
A58: E0010 | B58: {=_xlfn.XLOOKUP($A58,TRIM(SUBSTITUTE('worker file'!$A$2:$A$406,_xlfn.UNICHAR(160)," ")),'worker file'!$L$2:$L$406,"Not found")} -> US Semi-monthly | C58: {=_xlfn.XLOOKUP($A58,TRIM(SUBSTITUTE('worker file'!$A$2:$A$406,_xlfn.UNICHAR(160)," ")),'worker file'!$D$2:$D$406,"Not found")} -> CA | D58: {=_xlfn.XLOOKUP($A58,TRIM(SUBSTITUTE('worker file'!$A$2:$A$406,_xlfn.UNICHAR(160)," ")),'worker file'!$Q$2:$Q$406,"Not found")} -> Active | E58: 401K_EE | F58: =_xlfn.XLOOKUP($E58,$A$5:$A$8,$B$5:$B$8,"") -> 401(k) Employee Deferral | G58: =_xlfn.XLOOKUP($E58,$A$5:$A$8,$D$5:$D$8,"") -> Pre-tax (exempt from FIT/SIT; subject to FICA) | H58: =_xlfn.XLOOKUP($E58,$A$5:$A$8,$E$5:$E$8,"") -> Percent | I58: 0.07 | J58: =IF($H58="Flat",_xlfn.XLOOKUP($E58,$A$5:$A$8,$F$5:$F$8,""),"") | K58: =_xlfn.XLOOKUP($E58,$A$5:$A$8,$G$5:$G$8,"") -> Gross pay | L58: =_xlfn.XLOOKUP($E58,$A$5:$A$8,$H$5:$H$8,"") -> Every pay period (ongoing) | M58: {=MAX(_xlfn.XLOOKUP($A58,TRIM(SUBSTITUTE('worker file'!$A$2:$A$406,_xlfn.UNICHAR(160)," ")),'worker file'!$M$2:$M$406,0),_xlfn.XLOOKUP($B58,TRIM('pay group & schedule'!$A$2:$A$6),'pay group & schedule'!$D$2:$D$6,0))} -> 46311 | N58: {=_xlfn.LET(_xlpm.t,_xlfn.XLOOKUP($A58,TRIM(SUBSTITUTE('worker file'!$A$2:$A$406,_xlfn.UNICHAR(160)," ")),'worker file'!$N$2:$N$406,""),IF(N(_xlpm.t)=0,"",_xlpm.t))}
A59: E0010 | B59: {=_xlfn.XLOOKUP($A59,TRIM(SUBSTITUTE('worker file'!$A$2:$A$406,_xlfn.UNICHAR(160)," ")),'worker file'!$L$2:$L$406,"Not found")} -> US Semi-monthly | C59: {=_xlfn.XLOOKUP($A59,TRIM(SUBSTITUTE('worker file'!$A$2:$A$406,_xlfn.UNICHAR(160)," ")),'worker file'!$D$2:$D$406,"Not found")} -> CA | D59: {=_xlfn.XLOOKUP($A59,TRIM(SUBSTITUTE('worker file'!$A$2:$A$406,_xlfn.UNICHAR(160)," ")),'worker file'!$Q$2:$Q$406,"Not found")} -> Active | E59: MED_EE | F59: =_xlfn.XLOOKUP($E59,$A$5:$A$8,$B$5:$B$8,"") -> Medical (Health) – Employee | G59: =_xlfn.XLOOKUP($E59,$A$5:$A$8,$D$5:$D$8,"") -> Pre-tax Section 125 (exempt from FIT/SIT/FICA) | H59: =_xlfn.XLOOKUP($E59,$A$5:$A$8,$E$5:$E$8,"") -> Flat | I59: =IF($H59="Percent",_xlfn.XLOOKUP($E59,$A$5:$A$8,$F$5:$F$8,""),"") | J59: =IF($H59="Flat",_xlfn.XLOOKUP($E59,$A$5:$A$8,$F$5:$F$8,""),"") -> 200 | K59: =_xlfn.XLOOKUP($E59,$A$5:$A$8,$G$5:$G$8,"") -> Per pay period | L59: =_xlfn.XLOOKUP($E59,$A$5:$A$8,$H$5:$H$8,"") -> Every pay period (ongoing) | M59: {=MAX(_xlfn.XLOOKUP($A59,TRIM(SUBSTITUTE('worker file'!$A$2:$A$406,_xlfn.UNICHAR(160)," ")),'worker file'!$M$2:$M$406,0),_xlfn.XLOOKUP($B59,TRIM('pay group & schedule'!$A$2:$A$6),'pay group & schedule'!$D$2:$D$6,0))} -> 46311 | N59: {=_xlfn.LET(_xlpm.t,_xlfn.XLOOKUP($A59,TRIM(SUBSTITUTE('worker file'!$A$2:$A$406,_xlfn.UNICHAR(160)," ")),'worker file'!$N$2:$N$406,""),IF(N(_xlpm.t)=0,"",_xlpm.t))}
A60: E0010 | B60: {=_xlfn.XLOOKUP($A60,TRIM(SUBSTITUTE('worker file'!$A$2:$A$406,_xlfn.UNICHAR(160)," ")),'worker file'!$L$2:$L$406,"Not found")} -> US Semi-monthly | C60: {=_xlfn.XLOOKUP($A60,TRIM(SUBSTITUTE('worker file'!$A$2:$A$406,_xlfn.UNICHAR(160)," ")),'worker file'!$D$2:$D$406,"Not found")} -> CA | D60: {=_xlfn.XLOOKUP($A60,TRIM(SUBSTITUTE('worker file'!$A$2:$A$406,_xlfn.UNICHAR(160)," ")),'worker file'!$Q$2:$Q$406,"Not found")} -> Active | E60: DEN_EE | F60: =_xlfn.XLOOKUP($E60,$A$5:$A$8,$B$5:$B$8,"") -> Dental – Employee | G60: =_xlfn.XLOOKUP($E60,$A$5:$A$8,$D$5:$D$8,"") -> Pre-tax Section 125 (exempt from FIT/SIT/FICA) | H60: =_xlfn.XLOOKUP($E60,$A$5:$A$8,$E$5:$E$8,"") -> Flat | I60: =IF($H60="Percent",_xlfn.XLOOKUP($E60,$A$5:$A$8,$F$5:$F$8,""),"") | J60: =IF($H60="Flat",_xlfn.XLOOKUP($E60,$A$5:$A$8,$F$5:$F$8,""),"") -> 44 | K60: =_xlfn.XLOOKUP($E60,$A$5:$A$8,$G$5:$G$8,"") -> Per pay period | L60: =_xlfn.XLOOKUP($E60,$A$5:$A$8,$H$5:$H$8,"") -> Every pay period (ongoing) | M60: {=MAX(_xlfn.XLOOKUP($A60,TRIM(SUBSTITUTE('worker file'!$A$2:$A$406,_xlfn.UNICHAR(160)," ")),'worker file'!$M$2:$M$406,0),_xlfn.XLOOKUP($B60,TRIM('pay group & schedule'!$A$2:$A$6),'pay group & schedule'!$D$2:$D$6,0))} -> 46311 | N60: {=_xlfn.LET(_xlpm.t,_xlfn.XLOOKUP($A60,TRIM(SUBSTITUTE('worker file'!$A$2:$A$406,_xlfn.UNICHAR(160)," ")),'worker file'!$N$2:$N$406,""),IF(N(_xlpm.t)=0,"",_xlpm.t))}
A61: E0010 | B61: {=_xlfn.XLOOKUP($A61,TRIM(SUBSTITUTE('worker file'!$A$2:$A$406,_xlfn.UNICHAR(160)," ")),'worker file'!$L$2:$L$406,"Not found")} -> US Semi-monthly | C61: {=_xlfn.XLOOKUP($A61,TRIM(SUBSTITUTE('worker file'!$A$2:$A$406,_xlfn.UNICHAR(160)," ")),'worker file'!$D$2:$D$406,"Not found")} -> CA | D61: {=_xlfn.XLOOKUP($A61,TRIM(SUBSTITUTE('worker file'!$A$2:$A$406,_xlfn.UNICHAR(160)," ")),'worker file'!$Q$2:$Q$406,"Not found")} -> Active | E61: VIS_EE | F61: =_xlfn.XLOOKUP($E61,$A$5:$A$8,$B$5:$B$8,"") -> Vision – Employee | G61: =_xlfn.XLOOKUP($E61,$A$5:$A$8,$D$5:$D$8,"") -> Pre-tax Section 125 (exempt from FIT/SIT/FICA) | H61: =_xlfn.XLOOKUP($E61,$A$5:$A$8,$E$5:$E$8,"") -> Flat | I61: =IF($H61="Percent",_xlfn.XLOOKUP($E61,$A$5:$A$8,$F$5:$F$8,""),"") | J61: =IF($H61="Flat",_xlfn.XLOOKUP($E61,$A$5:$A$8,$F$5:$F$8,""),"") -> 30 | K61: =_xlfn.XLOOKUP($E61,$A$5:$A$8,$G$5:$G$8,"") -> Per pay period | L61: =_xlfn.XLOOKUP($E61,$A$5:$A$8,$H$5:$H$8,"") -> Every pay period (ongoing) | M61: {=MAX(_xlfn.XLOOKUP($A61,TRIM(SUBSTITUTE('worker file'!$A$2:$A$406,_xlfn.UNICHAR(160)," ")),'worker file'!$M$2:$M$406,0),_xlfn.XLOOKUP($B61,TRIM('pay group & schedule'!$A$2:$A$6),'pay group & schedule'!$D$2:$D$6,0))} -> 46311 | N61: {=_xlfn.LET(_xlpm.t,_xlfn.XLOOKUP($A61,TRIM(SUBSTITUTE('worker file'!$A$2:$A$406,_xlfn.UNICHAR(160)," ")),'worker file'!$N$2:$N$406,""),IF(N(_xlpm.t)=0,"",_xlpm.t))}
A62: E0011 | B62: {=_xlfn.XLOOKUP($A62,TRIM(SUBSTITUTE('worker file'!$A$2:$A$406,_xlfn.UNICHAR(160)," ")),'worker file'!$L$2:$L$406,"Not found")} -> US Semi-monthly | C62: {=_xlfn.XLOOKUP($A62,TRIM(SUBSTITUTE('worker file'!$A$2:$A$406,_xlfn.UNICHAR(160)," ")),'worker file'!$D$2:$D$406,"Not found")} -> CA | D62: {=_xlfn.XLOOKUP($A62,TRIM(SUBSTITUTE('worker file'!$A$2:$A$406,_xlfn.UNICHAR(160)," ")),'worker file'!$Q$2:$Q$406,"Not found")} -> Active | E62: 401K_EE | F62: =_xlfn.XLOOKUP($E62,$A$5:$A$8,$B$5:$B$8,"") -> 401(k) Employee Deferral | G62: =_xlfn.XLOOKUP($E62,$A$5:$A$8,$D$5:$D$8,"") -> Pre-tax (exempt from FIT/SIT; subject to FICA) | H62: =_xlfn.XLOOKUP($E62,$A$5:$A$8,$E$5:$E$8,"") -> Percent | I62: 0.04 | J62: =IF($H62="Flat",_xlfn.XLOOKUP($E62,$A$5:$A$8,$F$5:$F$8,""),"") | K62: =_xlfn.XLOOKUP($E62,$A$5:$A$8,$G$5:$G$8,"") -> Gross pay | L62: =_xlfn.XLOOKUP($E62,$A$5:$A$8,$H$5:$H$8,"") -> Every pay period (ongoing) | M62: {=MAX(_xlfn.XLOOKUP($A62,TRIM(SUBSTITUTE('worker file'!$A$2:$A$406,_xlfn.UNICHAR(160)," ")),'worker file'!$M$2:$M$406,0),_xlfn.XLOOKUP($B62,TRIM('pay group & schedule'!$A$2:$A$6),'pay group & schedule'!$D$2:$D$6,0))} -> 46311 | N62: {=_xlfn.LET(_xlpm.t,_xlfn.XLOOKUP($A62,TRIM(SUBSTITUTE('worker file'!$A$2:$A$406,_xlfn.UNICHAR(160)," ")),'worker file'!$N$2:$N$406,""),IF(N(_xlpm.t)=0,"",_xlpm.t))}
A63: E0011 | B63: {=_xlfn.XLOOKUP($A63,TRIM(SUBSTITUTE('worker file'!$A$2:$A$406,_xlfn.UNICHAR(160)," ")),'worker file'!$L$2:$L$406,"Not found")} -> US Semi-monthly | C63: {=_xlfn.XLOOKUP($A63,TRIM(SUBSTITUTE('worker file'!$A$2:$A$406,_xlfn.UNICHAR(160)," ")),'worker file'!$D$2:$D$406,"Not found")} -> CA | D63: {=_xlfn.XLOOKUP($A63,TRIM(SUBSTITUTE('worker file'!$A$2:$A$406,_xlfn.UNICHAR(160)," ")),'worker file'!$Q$2:$Q$406,"Not found")} -> Active | E63: MED_EE | F63: =_xlfn.XLOOKUP($E63,$A$5:$A$8,$B$5:$B$8,"") -> Medical (Health) – Employee | G63: =_xlfn.XLOOKUP($E63,$A$5:$A$8,$D$5:$D$8,"") -> Pre-tax Section 125 (exempt from FIT/SIT/FICA) | H63: =_xlfn.XLOOKUP($E63,$A$5:$A$8,$E$5:$E$8,"") -> Flat | I63: =IF($H63="Percent",_xlfn.XLOOKUP($E63,$A$5:$A$8,$F$5:$F$8,""),"") | J63: =IF($H63="Flat",_xlfn.XLOOKUP($E63,$A$5:$A$8,$F$5:$F$8,""),"") -> 200 | K63: =_xlfn.XLOOKUP($E63,$A$5:$A$8,$G$5:$G$8,"") -> Per pay period | L63: =_xlfn.XLOOKUP($E63,$A$5:$A$8,$H$5:$H$8,"") -> Every pay period (ongoing) | M63: {=MAX(_xlfn.XLOOKUP($A63,TRIM(SUBSTITUTE('worker file'!$A$2:$A$406,_xlfn.UNICHAR(160)," ")),'worker file'!$M$2:$M$406,0),_xlfn.XLOOKUP($B63,TRIM('pay group & schedule'!$A$2:$A$6),'pay group & schedule'!$D$2:$D$6,0))} -> 46311 | N63: {=_xlfn.LET(_xlpm.t,_xlfn.XLOOKUP($A63,TRIM(SUBSTITUTE('worker file'!$A$2:$A$406,_xlfn.UNICHAR(160)," ")),'worker file'!$N$2:$N$406,""),IF(N(_xlpm.t)=0,"",_xlpm.t))}
A64: E0011 | B64: {=_xlfn.XLOOKUP($A64,TRIM(SUBSTITUTE('worker file'!$A$2:$A$406,_xlfn.UNICHAR(160)," ")),'worker file'!$L$2:$L$406,"Not found")} -> US Semi-monthly | C64: {=_xlfn.XLOOKUP($A64,TRIM(SUBSTITUTE('worker file'!$A$2:$A$406,_xlfn.UNICHAR(160)," ")),'worker file'!$D$2:$D$406,"Not found")} -> CA | D64: {=_xlfn.XLOOKUP($A64,TRIM(SUBSTITUTE('worker file'!$A$2:$A$406,_xlfn.UNICHAR(160)," ")),'worker file'!$Q$2:$Q$406,"Not found")} -> Active | E64: DEN_EE | F64: =_xlfn.XLOOKUP($E64,$A$5:$A$8,$B$5:$B$8,"") -> Dental – Employee | G64: =_xlfn.XLOOKUP($E64,$A$5:$A$8,$D$5:$D$8,"") -> Pre-tax Section 125 (exempt from FIT/SIT/FICA) | H64: =_xlfn.XLOOKUP($E64,$A$5:$A$8,$E$5:$E$8,"") -> Flat | I64: =IF($H64="Percent",_xlfn.XLOOKUP($E64,$A$5:$A$8,$F$5:$F$8,""),"") | J64: =IF($H64="Flat",_xlfn.XLOOKUP($E64,$A$5:$A$8,$F$5:$F$8,""),"") -> 44 | K64: =_xlfn.XLOOKUP($E64,$A$5:$A$8,$G$5:$G$8,"") -> Per pay period | L64: =_xlfn.XLOOKUP($E64,$A$5:$A$8,$H$5:$H$8,"") -> Every pay period (ongoing) | M64: {=MAX(_xlfn.XLOOKUP($A64,TRIM(SUBSTITUTE('worker file'!$A$2:$A$406,_xlfn.UNICHAR(160)," ")),'worker file'!$M$2:$M$406,0),_xlfn.XLOOKUP($B64,TRIM('pay group & schedule'!$A$2:$A$6),'pay group & schedule'!$D$2:$D$6,0))} -> 46311 | N64: {=_xlfn.LET(_xlpm.t,_xlfn.XLOOKUP($A64,TRIM(SUBSTITUTE('worker file'!$A$2:$A$406,_xlfn.UNICHAR(160)," ")),'worker file'!$N$2:$N$406,""),IF(N(_xlpm.t)=0,"",_xlpm.t))}
A65: E0011 | B65: {=_xlfn.XLOOKUP($A65,TRIM(SUBSTITUTE('worker file'!$A$2:$A$406,_xlfn.UNICHAR(160)," ")),'worker file'!$L$2:$L$406,"Not found")} -> US Semi-monthly | C65: {=_xlfn.XLOOKUP($A65,TRIM(SUBSTITUTE('worker file'!$A$2:$A$406,_xlfn.UNICHAR(160)," ")),'worker file'!$D$2:$D$406,"Not found")} -> CA | D65: {=_xlfn.XLOOKUP($A65,TRIM(SUBSTITUTE('worker file'!$A$2:$A$406,_xlfn.UNICHAR(160)," ")),'worker file'!$Q$2:$Q$406,"Not found")} -> Active | E65: VIS_EE | F65: =_xlfn.XLOOKUP($E65,$A$5:$A$8,$B$5:$B$8,"") -> Vision – Employee | G65: =_xlfn.XLOOKUP($E65,$A$5:$A$8,$D$5:$D$8,"") -> Pre-tax Section 125 (exempt from FIT/SIT/FICA) | H65: =_xlfn.XLOOKUP($E65,$A$5:$A$8,$E$5:$E$8,"") -> Flat | I65: =IF($H65="Percent",_xlfn.XLOOKUP($E65,$A$5:$A$8,$F$5:$F$8,""),"") | J65: =IF($H65="Flat",_xlfn.XLOOKUP($E65,$A$5:$A$8,$F$5:$F$8,""),"") -> 30 | K65: =_xlfn.XLOOKUP($E65,$A$5:$A$8,$G$5:$G$8,"") -> Per pay period | L65: =_xlfn.XLOOKUP($E65,$A$5:$A$8,$H$5:$H$8,"") -> Every pay period (ongoing) | M65: {=MAX(_xlfn.XLOOKUP($A65,TRIM(SUBSTITUTE('worker file'!$A$2:$A$406,_xlfn.UNICHAR(160)," ")),'worker file'!$M$2:$M$406,0),_xlfn.XLOOKUP($B65,TRIM('pay group & schedule'!$A$2:$A$6),'pay group & schedule'!$D$2:$D$6,0))} -> 46311 | N65: {=_xlfn.LET(_xlpm.t,_xlfn.XLOOKUP($A65,TRIM(SUBSTITUTE('worker file'!$A$2:$A$406,_xlfn.UNICHAR(160)," ")),'worker file'!$N$2:$N$406,""),IF(N(_xlpm.t)=0,"",_xlpm.t))}
A66: E0012 | B66: {=_xlfn.XLOOKUP($A66,TRIM(SUBSTITUTE('worker file'!$A$2:$A$406,_xlfn.UNICHAR(160)," ")),'worker file'!$L$2:$L$406,"Not found")} -> US Semi-monthly | C66: {=_xlfn.XLOOKUP($A66,TRIM(SUBSTITUTE('worker file'!$A$2:$A$406,_xlfn.UNICHAR(160)," ")),'worker file'!$D$2:$D$406,"Not found")} -> CA | D66: {=_xlfn.XLOOKUP($A66,TRIM(SUBSTITUTE('worker file'!$A$2:$A$406,_xlfn.UNICHAR(160)," ")),'worker file'!$Q$2:$Q$406,"Not found")} -> Active | E66: 401K_EE | F66: =_xlfn.XLOOKUP($E66,$A$5:$A$8,$B$5:$B$8,"") -> 401(k) Employee Deferral | G66: =_xlfn.XLOOKUP($E66,$A$5:$A$8,$D$5:$D$8,"") -> Pre-tax (exempt from FIT/SIT; subject to FICA) | H66: =_xlfn.XLOOKUP($E66,$A$5:$A$8,$E$5:$E$8,"") -> Percent | I66: 0.01 | J66: =IF($H66="Flat",_xlfn.XLOOKUP($E66,$A$5:$A$8,$F$5:$F$8,""),"") | K66: =_xlfn.XLOOKUP($E66,$A$5:$A$8,$G$5:$G$8,"") -> Gross pay | L66: =_xlfn.XLOOKUP($E66,$A$5:$A$8,$H$5:$H$8,"") -> Every pay period (ongoing) | M66: {=MAX(_xlfn.XLOOKUP($A66,TRIM(SUBSTITUTE('worker file'!$A$2:$A$406,_xlfn.UNICHAR(160)," ")),'worker file'!$M$2:$M$406,0),_xlfn.XLOOKUP($B66,TRIM('pay group & schedule'!$A$2:$A$6),'pay group & schedule'!$D$2:$D$6,0))} -> 46311 | N66: {=_xlfn.LET(_xlpm.t,_xlfn.XLOOKUP($A66,TRIM(SUBSTITUTE('worker file'!$A$2:$A$406,_xlfn.UNICHAR(160)," ")),'worker file'!$N$2:$N$406,""),IF(N(_xlpm.t)=0,"",_xlpm.t))}
A67: E0012 | B67: {=_xlfn.XLOOKUP($A67,TRIM(SUBSTITUTE('worker file'!$A$2:$A$406,_xlfn.UNICHAR(160)," ")),'worker file'!$L$2:$L$406,"Not found")} -> US Semi-monthly | C67: {=_xlfn.XLOOKUP($A67,TRIM(SUBSTITUTE('worker file'!$A$2:$A$406,_xlfn.UNICHAR(160)," ")),'worker file'!$D$2:$D$406,"Not found")} -> CA | D67: {=_xlfn.XLOOKUP($A67,TRIM(SUBSTITUTE('worker file'!$A$2:$A$406,_xlfn.UNICHAR(160)," ")),'worker file'!$Q$2:$Q$406,"Not found")} -> Active | E67: MED_EE | F67: =_xlfn.XLOOKUP($E67,$A$5:$A$8,$B$5:$B$8,"") -> Medical (Health) – Employee | G67: =_xlfn.XLOOKUP($E67,$A$5:$A$8,$D$5:$D$8,"") -> Pre-tax Section 125 (exempt from FIT/SIT/FICA) | H67: =_xlfn.XLOOKUP($E67,$A$5:$A$8,$E$5:$E$8,"") -> Flat | I67: =IF($H67="Percent",_xlfn.XLOOKUP($E67,$A$5:$A$8,$F$5:$F$8,""),"") | J67: =IF($H67="Flat",_xlfn.XLOOKUP($E67,$A$5:$A$8,$F$5:$F$8,""),"") -> 200 | K67: =_xlfn.XLOOKUP($E67,$A$5:$A$8,$G$5:$G$8,"") -> Per pay period | L67: =_xlfn.XLOOKUP($E67,$A$5:$A$8,$H$5:$H$8,"") -> Every pay period (ongoing) | M67: {=MAX(_xlfn.XLOOKUP($A67,TRIM(SUBSTITUTE('worker file'!$A$2:$A$406,_xlfn.UNICHAR(160)," ")),'worker file'!$M$2:$M$406,0),_xlfn.XLOOKUP($B67,TRIM('pay group & schedule'!$A$2:$A$6),'pay group & schedule'!$D$2:$D$6,0))} -> 46311 | N67: {=_xlfn.LET(_xlpm.t,_xlfn.XLOOKUP($A67,TRIM(SUBSTITUTE('worker file'!$A$2:$A$406,_xlfn.UNICHAR(160)," ")),'worker file'!$N$2:$N$406,""),IF(N(_xlpm.t)=0,"",_xlpm.t))}
A68: E0012 | B68: {=_xlfn.XLOOKUP($A68,TRIM(SUBSTITUTE('worker file'!$A$2:$A$406,_xlfn.UNICHAR(160)," ")),'worker file'!$L$2:$L$406,"Not found")} -> US Semi-monthly | C68: {=_xlfn.XLOOKUP($A68,TRIM(SUBSTITUTE('worker file'!$A$2:$A$406,_xlfn.UNICHAR(160)," ")),'worker file'!$D$2:$D$406,"Not found")} -> CA | D68: {=_xlfn.XLOOKUP($A68,TRIM(SUBSTITUTE('worker file'!$A$2:$A$406,_xlfn.UNICHAR(160)," ")),'worker file'!$Q$2:$Q$406,"Not found")} -> Active | E68: DEN_EE | F68: =_xlfn.XLOOKUP($E68,$A$5:$A$8,$B$5:$B$8,"") -> Dental – Employee | G68: =_xlfn.XLOOKUP($E68,$A$5:$A$8,$D$5:$D$8,"") -> Pre-tax Section 125 (exempt from FIT/SIT/FICA) | H68: =_xlfn.XLOOKUP($E68,$A$5:$A$8,$E$5:$E$8,"") -> Flat | I68: =IF($H68="Percent",_xlfn.XLOOKUP($E68,$A$5:$A$8,$F$5:$F$8,""),"") | J68: =IF($H68="Flat",_xlfn.XLOOKUP($E68,$A$5:$A$8,$F$5:$F$8,""),"") -> 44 | K68: =_xlfn.XLOOKUP($E68,$A$5:$A$8,$G$5:$G$8,"") -> Per pay period | L68: =_xlfn.XLOOKUP($E68,$A$5:$A$8,$H$5:$H$8,"") -> Every pay period (ongoing) | M68: {=MAX(_xlfn.XLOOKUP($A68,TRIM(SUBSTITUTE('worker file'!$A$2:$A$406,_xlfn.UNICHAR(160)," ")),'worker file'!$M$2:$M$406,0),_xlfn.XLOOKUP($B68,TRIM('pay group & schedule'!$A$2:$A$6),'pay group & schedule'!$D$2:$D$6,0))} -> 46311 | N68: {=_xlfn.LET(_xlpm.t,_xlfn.XLOOKUP($A68,TRIM(SUBSTITUTE('worker file'!$A$2:$A$406,_xlfn.UNICHAR(160)," ")),'worker file'!$N$2:$N$406,""),IF(N(_xlpm.t)=0,"",_xlpm.t))}
A69: E0012 | B69: {=_xlfn.XLOOKUP($A69,TRIM(SUBSTITUTE('worker file'!$A$2:$A$406,_xlfn.UNICHAR(160)," ")),'worker file'!$L$2:$L$406,"Not found")} -> US Semi-monthly | C69: {=_xlfn.XLOOKUP($A69,TRIM(SUBSTITUTE('worker file'!$A$2:$A$406,_xlfn.UNICHAR(160)," ")),'worker file'!$D$2:$D$406,"Not found")} -> CA | D69: {=_xlfn.XLOOKUP($A69,TRIM(SUBSTITUTE('worker file'!$A$2:$A$406,_xlfn.UNICHAR(160)," ")),'worker file'!$Q$2:$Q$406,"Not found")} -> Active | E69: VIS_EE | F69: =_xlfn.XLOOKUP($E69,$A$5:$A$8,$B$5:$B$8,"") -> Vision – Employee | G69: =_xlfn.XLOOKUP($E69,$A$5:$A$8,$D$5:$D$8,"") -> Pre-tax Section 125 (exempt from FIT/SIT/FICA) | H69: =_xlfn.XLOOKUP($E69,$A$5:$A$8,$E$5:$E$8,"") -> Flat | I69: =IF($H69="Percent",_xlfn.XLOOKUP($E69,$A$5:$A$8,$F$5:$F$8,""),"") | J69: =IF($H69="Flat",_xlfn.XLOOKUP($E69,$A$5:$A$8,$F$5:$F$8,""),"") -> 30 | K69: =_xlfn.XLOOKUP($E69,$A$5:$A$8,$G$5:$G$8,"") -> Per pay period | L69: =_xlfn.XLOOKUP($E69,$A$5:$A$8,$H$5:$H$8,"") -> Every pay period (ongoing) | M69: {=MAX(_xlfn.XLOOKUP($A69,TRIM(SUBSTITUTE('worker file'!$A$2:$A$406,_xlfn.UNICHAR(160)," ")),'worker file'!$M$2:$M$406,0),_xlfn.XLOOKUP($B69,TRIM('pay group & schedule'!$A$2:$A$6),'pay group & schedule'!$D$2:$D$6,0))} -> 46311 | N69: {=_xlfn.LET(_xlpm.t,_xlfn.XLOOKUP($A69,TRIM(SUBSTITUTE('worker file'!$A$2:$A$406,_xlfn.UNICHAR(160)," ")),'worker file'!$N$2:$N$406,""),IF(N(_xlpm.t)=0,"",_xlpm.t))}
A70: E0013 | B70: {=_xlfn.XLOOKUP($A70,TRIM(SUBSTITUTE('worker file'!$A$2:$A$406,_xlfn.UNICHAR(160)," ")),'worker file'!$L$2:$L$406,"Not found")} -> US Semi-monthly | C70: {=_xlfn.XLOOKUP($A70,TRIM(SUBSTITUTE('worker file'!$A$2:$A$406,_xlfn.UNICHAR(160)," ")),'worker file'!$D$2:$D$406,"Not found")} -> CA | D70: {=_xlfn.XLOOKUP($A70,TRIM(SUBSTITUTE('worker file'!$A$2:$A$406,_xlfn.UNICHAR(160)," ")),'worker file'!$Q$2:$Q$406,"Not found")} -> Active | E70: 401K_EE | F70: =_xlfn.XLOOKUP($E70,$A$5:$A$8,$B$5:$B$8,"") -> 401(k) Employee Deferral | G70: =_xlfn.XLOOKUP($E70,$A$5:$A$8,$D$5:$D$8,"") -> Pre-tax (exempt from FIT/SIT; subject to FICA) | H70: =_xlfn.XLOOKUP($E70,$A$5:$A$8,$E$5:$E$8,"") -> Percent | I70: 0.06 | J70: =IF($H70="Flat",_xlfn.XLOOKUP($E70,$A$5:$A$8,$F$5:$F$8,""),"") | K70: =_xlfn.XLOOKUP($E70,$A$5:$A$8,$G$5:$G$8,"") -> Gross pay | L70: =_xlfn.XLOOKUP($E70,$A$5:$A$8,$H$5:$H$8,"") -> Every pay period (ongoing) | M70: {=MAX(_xlfn.XLOOKUP($A70,TRIM(SUBSTITUTE('worker file'!$A$2:$A$406,_xlfn.UNICHAR(160)," ")),'worker file'!$M$2:$M$406,0),_xlfn.XLOOKUP($B70,TRIM('pay group & schedule'!$A$2:$A$6),'pay group & schedule'!$D$2:$D$6,0))} -> 46311 | N70: {=_xlfn.LET(_xlpm.t,_xlfn.XLOOKUP($A70,TRIM(SUBSTITUTE('worker file'!$A$2:$A$406,_xlfn.UNICHAR(160)," ")),'worker file'!$N$2:$N$406,""),IF(N(_xlpm.t)=0,"",_xlpm.t))}
A71: E0013 | B71: {=_xlfn.XLOOKUP($A71,TRIM(SUBSTITUTE('worker file'!$A$2:$A$406,_xlfn.UNICHAR(160)," ")),'worker file'!$L$2:$L$406,"Not found")} -> US Semi-monthly | C71: {=_xlfn.XLOOKUP($A71,TRIM(SUBSTITUTE('worker file'!$A$2:$A$406,_xlfn.UNICHAR(160)," ")),'worker file'!$D$2:$D$406,"Not found")} -> CA | D71: {=_xlfn.XLOOKUP($A71,TRIM(SUBSTITUTE('worker file'!$A$2:$A$406,_xlfn.UNICHAR(160)," ")),'worker file'!$Q$2:$Q$406,"Not found")} -> Active | E71: MED_EE | F71: =_xlfn.XLOOKUP($E71,$A$5:$A$8,$B$5:$B$8,"") -> Medical (Health) – Employee | G71: =_xlfn.XLOOKUP($E71,$A$5:$A$8,$D$5:$D$8,"") -> Pre-tax Section 125 (exempt from FIT/SIT/FICA) | H71: =_xlfn.XLOOKUP($E71,$A$5:$A$8,$E$5:$E$8,"") -> Flat | I71: =IF($H71="Percent",_xlfn.XLOOKUP($E71,$A$5:$A$8,$F$5:$F$8,""),"") | J71: =IF($H71="Flat",_xlfn.XLOOKUP($E71,$A$5:$A$8,$F$5:$F$8,""),"") -> 200 | K71: =_xlfn.XLOOKUP($E71,$A$5:$A$8,$G$5:$G$8,"") -> Per pay period | L71: =_xlfn.XLOOKUP($E71,$A$5:$A$8,$H$5:$H$8,"") -> Every pay period (ongoing) | M71: {=MAX(_xlfn.XLOOKUP($A71,TRIM(SUBSTITUTE('worker file'!$A$2:$A$406,_xlfn.UNICHAR(160)," ")),'worker file'!$M$2:$M$406,0),_xlfn.XLOOKUP($B71,TRIM('pay group & schedule'!$A$2:$A$6),'pay group & schedule'!$D$2:$D$6,0))} -> 46311 | N71: {=_xlfn.LET(_xlpm.t,_xlfn.XLOOKUP($A71,TRIM(SUBSTITUTE('worker file'!$A$2:$A$406,_xlfn.UNICHAR(160)," ")),'worker file'!$N$2:$N$406,""),IF(N(_xlpm.t)=0,"",_xlpm.t))}
A72: E0013 | B72: {=_xlfn.XLOOKUP($A72,TRIM(SUBSTITUTE('worker file'!$A$2:$A$406,_xlfn.UNICHAR(160)," ")),'worker file'!$L$2:$L$406,"Not found")} -> US Semi-monthly | C72: {=_xlfn.XLOOKUP($A72,TRIM(SUBSTITUTE('worker file'!$A$2:$A$406,_xlfn.UNICHAR(160)," ")),'worker file'!$D$2:$D$406,"Not found")} -> CA | D72: {=_xlfn.XLOOKUP($A72,TRIM(SUBSTITUTE('worker file'!$A$2:$A$406,_xlfn.UNICHAR(160)," ")),'worker file'!$Q$2:$Q$406,"Not found")} -> Active | E72: DEN_EE | F72: =_xlfn.XLOOKUP($E72,$A$5:$A$8,$B$5:$B$8,"") -> Dental – Employee | G72: =_xlfn.XLOOKUP($E72,$A$5:$A$8,$D$5:$D$8,"") -> Pre-tax Section 125 (exempt from FIT/SIT/FICA) | H72: =_xlfn.XLOOKUP($E72,$A$5:$A$8,$E$5:$E$8,"") -> Flat | I72: =IF($H72="Percent",_xlfn.XLOOKUP($E72,$A$5:$A$8,$F$5:$F$8,""),"") | J72: =IF($H72="Flat",_xlfn.XLOOKUP($E72,$A$5:$A$8,$F$5:$F$8,""),"") -> 44 | K72: =_xlfn.XLOOKUP($E72,$A$5:$A$8,$G$5:$G$8,"") -> Per pay period | L72: =_xlfn.XLOOKUP($E72,$A$5:$A$8,$H$5:$H$8,"") -> Every pay period (ongoing) | M72: {=MAX(_xlfn.XLOOKUP($A72,TRIM(SUBSTITUTE('worker file'!$A$2:$A$406,_xlfn.UNICHAR(160)," ")),'worker file'!$M$2:$M$406,0),_xlfn.XLOOKUP($B72,TRIM('pay group & schedule'!$A$2:$A$6),'pay group & schedule'!$D$2:$D$6,0))} -> 46311 | N72: {=_xlfn.LET(_xlpm.t,_xlfn.XLOOKUP($A72,TRIM(SUBSTITUTE('worker file'!$A$2:$A$406,_xlfn.UNICHAR(160)," ")),'worker file'!$N$2:$N$406,""),IF(N(_xlpm.t)=0,"",_xlpm.t))}
A73: E0013 | B73: {=_xlfn.XLOOKUP($A73,TRIM(SUBSTITUTE('worker file'!$A$2:$A$406,_xlfn.UNICHAR(160)," ")),'worker file'!$L$2:$L$406,"Not found")} -> US Semi-monthly | C73: {=_xlfn.XLOOKUP($A73,TRIM(SUBSTITUTE('worker file'!$A$2:$A$406,_xlfn.UNICHAR(160)," ")),'worker file'!$D$2:$D$406,"Not found")} -> CA | D73: {=_xlfn.XLOOKUP($A73,TRIM(SUBSTITUTE('worker file'!$A$2:$A$406,_xlfn.UNICHAR(160)," ")),'worker file'!$Q$2:$Q$406,"Not found")} -> Active | E73: VIS_EE | F73: =_xlfn.XLOOKUP($E73,$A$5:$A$8,$B$5:$B$8,"") -> Vision – Employee | G73: =_xlfn.XLOOKUP($E73,$A$5:$A$8,$D$5:$D$8,"") -> Pre-tax Section 125 (exempt from FIT/SIT/FICA) | H73: =_xlfn.XLOOKUP($E73,$A$5:$A$8,$E$5:$E$8,"") -> Flat | I73: =IF($H73="Percent",_xlfn.XLOOKUP($E73,$A$5:$A$8,$F$5:$F$8,""),"") | J73: =IF($H73="Flat",_xlfn.XLOOKUP($E73,$A$5:$A$8,$F$5:$F$8,""),"") -> 30 | K73: =_xlfn.XLOOKUP($E73,$A$5:$A$8,$G$5:$G$8,"") -> Per pay period | L73: =_xlfn.XLOOKUP($E73,$A$5:$A$8,$H$5:$H$8,"") -> Every pay period (ongoing) | M73: {=MAX(_xlfn.XLOOKUP($A73,TRIM(SUBSTITUTE('worker file'!$A$2:$A$406,_xlfn.UNICHAR(160)," ")),'worker file'!$M$2:$M$406,0),_xlfn.XLOOKUP($B73,TRIM('pay group & schedule'!$A$2:$A$6),'pay group & schedule'!$D$2:$D$6,0))} -> 46311 | N73: {=_xlfn.LET(_xlpm.t,_xlfn.XLOOKUP($A73,TRIM(SUBSTITUTE('worker file'!$A$2:$A$406,_xlfn.UNICHAR(160)," ")),'worker file'!$N$2:$N$406,""),IF(N(_xlpm.t)=0,"",_xlpm.t))}
A74: E0014 | B74: {=_xlfn.XLOOKUP($A74,TRIM(SUBSTITUTE('worker file'!$A$2:$A$406,_xlfn.UNICHAR(160)," ")),'worker file'!$L$2:$L$406,"Not found")} -> US Semi-monthly | C74: {=_xlfn.XLOOKUP($A74,TRIM(SUBSTITUTE('worker file'!$A$2:$A$406,_xlfn.UNICHAR(160)," ")),'worker file'!$D$2:$D$406,"Not found")} -> CA | D74: {=_xlfn.XLOOKUP($A74,TRIM(SUBSTITUTE('worker file'!$A$2:$A$406,_xlfn.UNICHAR(160)," ")),'worker file'!$Q$2:$Q$406,"Not found")} -> Active | E74: 401K_EE | F74: =_xlfn.XLOOKUP($E74,$A$5:$A$8,$B$5:$B$8,"") -> 401(k) Employee Deferral | G74: =_xlfn.XLOOKUP($E74,$A$5:$A$8,$D$5:$D$8,"") -> Pre-tax (exempt from FIT/SIT; subject to FICA) | H74: =_xlfn.XLOOKUP($E74,$A$5:$A$8,$E$5:$E$8,"") -> Percent | I74: 0.03 | J74: =IF($H74="Flat",_xlfn.XLOOKUP($E74,$A$5:$A$8,$F$5:$F$8,""),"") | K74: =_xlfn.XLOOKUP($E74,$A$5:$A$8,$G$5:$G$8,"") -> Gross pay | L74: =_xlfn.XLOOKUP($E74,$A$5:$A$8,$H$5:$H$8,"") -> Every pay period (ongoing) | M74: {=MAX(_xlfn.XLOOKUP($A74,TRIM(SUBSTITUTE('worker file'!$A$2:$A$406,_xlfn.UNICHAR(160)," ")),'worker file'!$M$2:$M$406,0),_xlfn.XLOOKUP($B74,TRIM('pay group & schedule'!$A$2:$A$6),'pay group & schedule'!$D$2:$D$6,0))} -> 46311 | N74: {=_xlfn.LET(_xlpm.t,_xlfn.XLOOKUP($A74,TRIM(SUBSTITUTE('worker file'!$A$2:$A$406,_xlfn.UNICHAR(160)," ")),'worker file'!$N$2:$N$406,""),IF(N(_xlpm.t)=0,"",_xlpm.t))}
A75: E0014 | B75: {=_xlfn.XLOOKUP($A75,TRIM(SUBSTITUTE('worker file'!$A$2:$A$406,_xlfn.UNICHAR(160)," ")),'worker file'!$L$2:$L$406,"Not found")} -> US Semi-monthly | C75: {=_xlfn.XLOOKUP($A75,TRIM(SUBSTITUTE('worker file'!$A$2:$A$406,_xlfn.UNICHAR(160)," ")),'worker file'!$D$2:$D$406,"Not found")} -> CA | D75: {=_xlfn.XLOOKUP($A75,TRIM(SUBSTITUTE('worker file'!$A$2:$A$406,_xlfn.UNICHAR(160)," ")),'worker file'!$Q$2:$Q$406,"Not found")} -> Active | E75: MED_EE | F75: =_xlfn.XLOOKUP($E75,$A$5:$A$8,$B$5:$B$8,"") -> Medical (Health) – Employee | G75: =_xlfn.XLOOKUP($E75,$A$5:$A$8,$D$5:$D$8,"") -> Pre-tax Section 125 (exempt from FIT/SIT/FICA) | H75: =_xlfn.XLOOKUP($E75,$A$5:$A$8,$E$5:$E$8,"") -> Flat | I75: =IF($H75="Percent",_xlfn.XLOOKUP($E75,$A$5:$A$8,$F$5:$F$8,""),"") | J75: =IF($H75="Flat",_xlfn.XLOOKUP($E75,$A$5:$A$8,$F$5:$F$8,""),"") -> 200 | K75: =_xlfn.XLOOKUP($E75,$A$5:$A$8,$G$5:$G$8,"") -> Per pay period | L75: =_xlfn.XLOOKUP($E75,$A$5:$A$8,$H$5:$H$8,"") -> Every pay period (ongoing) | M75: {=MAX(_xlfn.XLOOKUP($A75,TRIM(SUBSTITUTE('worker file'!$A$2:$A$406,_xlfn.UNICHAR(160)," ")),'worker file'!$M$2:$M$406,0),_xlfn.XLOOKUP($B75,TRIM('pay group & schedule'!$A$2:$A$6),'pay group & schedule'!$D$2:$D$6,0))} -> 46311 | N75: {=_xlfn.LET(_xlpm.t,_xlfn.XLOOKUP($A75,TRIM(SUBSTITUTE('worker file'!$A$2:$A$406,_xlfn.UNICHAR(160)," ")),'worker file'!$N$2:$N$406,""),IF(N(_xlpm.t)=0,"",_xlpm.t))}
A76: E0014 | B76: {=_xlfn.XLOOKUP($A76,TRIM(SUBSTITUTE('worker file'!$A$2:$A$406,_xlfn.UNICHAR(160)," ")),'worker file'!$L$2:$L$406,"Not found")} -> US Semi-monthly | C76: {=_xlfn.XLOOKUP($A76,TRIM(SUBSTITUTE('worker file'!$A$2:$A$406,_xlfn.UNICHAR(160)," ")),'worker file'!$D$2:$D$406,"Not found")} -> CA | D76: {=_xlfn.XLOOKUP($A76,TRIM(SUBSTITUTE('worker file'!$A$2:$A$406,_xlfn.UNICHAR(160)," ")),'worker file'!$Q$2:$Q$406,"Not found")} -> Active | E76: DEN_EE | F76: =_xlfn.XLOOKUP($E76,$A$5:$A$8,$B$5:$B$8,"") -> Dental – Employee | G76: =_xlfn.XLOOKUP($E76,$A$5:$A$8,$D$5:$D$8,"") -> Pre-tax Section 125 (exempt from FIT/SIT/FICA) | H76: =_xlfn.XLOOKUP($E76,$A$5:$A$8,$E$5:$E$8,"") -> Flat | I76: =IF($H76="Percent",_xlfn.XLOOKUP($E76,$A$5:$A$8,$F$5:$F$8,""),"") | J76: =IF($H76="Flat",_xlfn.XLOOKUP($E76,$A$5:$A$8,$F$5:$F$8,""),"") -> 44 | K76: =_xlfn.XLOOKUP($E76,$A$5:$A$8,$G$5:$G$8,"") -> Per pay period | L76: =_xlfn.XLOOKUP($E76,$A$5:$A$8,$H$5:$H$8,"") -> Every pay period (ongoing) | M76: {=MAX(_xlfn.XLOOKUP($A76,TRIM(SUBSTITUTE('worker file'!$A$2:$A$406,_xlfn.UNICHAR(160)," ")),'worker file'!$M$2:$M$406,0),_xlfn.XLOOKUP($B76,TRIM('pay group & schedule'!$A$2:$A$6),'pay group & schedule'!$D$2:$D$6,0))} -> 46311 | N76: {=_xlfn.LET(_xlpm.t,_xlfn.XLOOKUP($A76,TRIM(SUBSTITUTE('worker file'!$A$2:$A$406,_xlfn.UNICHAR(160)," ")),'worker file'!$N$2:$N$406,""),IF(N(_xlpm.t)=0,"",_xlpm.t))}
A77: E0014 | B77: {=_xlfn.XLOOKUP($A77,TRIM(SUBSTITUTE('worker file'!$A$2:$A$406,_xlfn.UNICHAR(160)," ")),'worker file'!$L$2:$L$406,"Not found")} -> US Semi-monthly | C77: {=_xlfn.XLOOKUP($A77,TRIM(SUBSTITUTE('worker file'!$A$2:$A$406,_xlfn.UNICHAR(160)," ")),'worker file'!$D$2:$D$406,"Not found")} -> CA | D77: {=_xlfn.XLOOKUP($A77,TRIM(SUBSTITUTE('worker file'!$A$2:$A$406,_xlfn.UNICHAR(160)," ")),'worker file'!$Q$2:$Q$406,"Not found")} -> Active | E77: VIS_EE | F77: =_xlfn.XLOOKUP($E77,$A$5:$A$8,$B$5:$B$8,"") -> Vision – Employee | G77: =_xlfn.XLOOKUP($E77,$A$5:$A$8,$D$5:$D$8,"") -> Pre-tax Section 125 (exempt from FIT/SIT/FICA) | H77: =_xlfn.XLOOKUP($E77,$A$5:$A$8,$E$5:$E$8,"") -> Flat | I77: =IF($H77="Percent",_xlfn.XLOOKUP($E77,$A$5:$A$8,$F$5:$F$8,""),"") | J77: =IF($H77="Flat",_xlfn.XLOOKUP($E77,$A$5:$A$8,$F$5:$F$8,""),"") -> 30 | K77: =_xlfn.XLOOKUP($E77,$A$5:$A$8,$G$5:$G$8,"") -> Per pay period | L77: =_xlfn.XLOOKUP($E77,$A$5:$A$8,$H$5:$H$8,"") -> Every pay period (ongoing) | M77: {=MAX(_xlfn.XLOOKUP($A77,TRIM(SUBSTITUTE('worker file'!$A$2:$A$406,_xlfn.UNICHAR(160)," ")),'worker file'!$M$2:$M$406,0),_xlfn.XLOOKUP($B77,TRIM('pay group & schedule'!$A$2:$A$6),'pay group & schedule'!$D$2:$D$6,0))} -> 46311 | N77: {=_xlfn.LET(_xlpm.t,_xlfn.XLOOKUP($A77,TRIM(SUBSTITUTE('worker file'!$A$2:$A$406,_xlfn.UNICHAR(160)," ")),'worker file'!$N$2:$N$406,""),IF(N(_xlpm.t)=0,"",_xlpm.t))}
A78: E0015 | B78: {=_xlfn.XLOOKUP($A78,TRIM(SUBSTITUTE('worker file'!$A$2:$A$406,_xlfn.UNICHAR(160)," ")),'worker file'!$L$2:$L$406,"Not found")} -> US Biweekly | C78: {=_xlfn.XLOOKUP($A78,TRIM(SUBSTITUTE('worker file'!$A$2:$A$406,_xlfn.UNICHAR(160)," ")),'worker file'!$D$2:$D$406,"Not found")} -> TX | D78: {=_xlfn.XLOOKUP($A78,TRIM(SUBSTITUTE('worker file'!$A$2:$A$406,_xlfn.UNICHAR(160)," ")),'worker file'!$Q$2:$Q$406,"Not found")} -> Active | E78: 401K_EE | F78: =_xlfn.XLOOKUP($E78,$A$5:$A$8,$B$5:$B$8,"") -> 401(k) Employee Deferral | G78: =_xlfn.XLOOKUP($E78,$A$5:$A$8,$D$5:$D$8,"") -> Pre-tax (exempt from FIT/SIT; subject to FICA) | H78: =_xlfn.XLOOKUP($E78,$A$5:$A$8,$E$5:$E$8,"") -> Percent | I78: 0 | J78: =IF($H78="Flat",_xlfn.XLOOKUP($E78,$A$5:$A$8,$F$5:$F$8,""),"") | K78: =_xlfn.XLOOKUP($E78,$A$5:$A$8,$G$5:$G$8,"") -> Gross pay | L78: =_xlfn.XLOOKUP($E78,$A$5:$A$8,$H$5:$H$8,"") -> Every pay period (ongoing) | M78: {=MAX(_xlfn.XLOOKUP($A78,TRIM(SUBSTITUTE('worker file'!$A$2:$A$406,_xlfn.UNICHAR(160)," ")),'worker file'!$M$2:$M$406,0),_xlfn.XLOOKUP($B78,TRIM('pay group & schedule'!$A$2:$A$6),'pay group & schedule'!$D$2:$D$6,0))} -> 46299 | N78: {=_xlfn.LET(_xlpm.t,_xlfn.XLOOKUP($A78,TRIM(SUBSTITUTE('worker file'!$A$2:$A$406,_xlfn.UNICHAR(160)," ")),'worker file'!$N$2:$N$406,""),IF(N(_xlpm.t)=0,"",_xlpm.t))}
A79: E0015 | B79: {=_xlfn.XLOOKUP($A79,TRIM(SUBSTITUTE('worker file'!$A$2:$A$406,_xlfn.UNICHAR(160)," ")),'worker file'!$L$2:$L$406,"Not found")} -> US Biweekly | C79: {=_xlfn.XLOOKUP($A79,TRIM(SUBSTITUTE('worker file'!$A$2:$A$406,_xlfn.UNICHAR(160)," ")),'worker file'!$D$2:$D$406,"Not found")} -> TX | D79: {=_xlfn.XLOOKUP($A79,TRIM(SUBSTITUTE('worker file'!$A$2:$A$406,_xlfn.UNICHAR(160)," ")),'worker file'!$Q$2:$Q$406,"Not found")} -> Active | E79: MED_EE | F79: =_xlfn.XLOOKUP($E79,$A$5:$A$8,$B$5:$B$8,"") -> Medical (Health) – Employee | G79: =_xlfn.XLOOKUP($E79,$A$5:$A$8,$D$5:$D$8,"") -> Pre-tax Section 125 (exempt from FIT/SIT/FICA) | H79: =_xlfn.XLOOKUP($E79,$A$5:$A$8,$E$5:$E$8,"") -> Flat | I79: =IF($H79="Percent",_xlfn.XLOOKUP($E79,$A$5:$A$8,$F$5:$F$8,""),"") | J79: =IF($H79="Flat",_xlfn.XLOOKUP($E79,$A$5:$A$8,$F$5:$F$8,""),"") -> 200 | K79: =_xlfn.XLOOKUP($E79,$A$5:$A$8,$G$5:$G$8,"") -> Per pay period | L79: =_xlfn.XLOOKUP($E79,$A$5:$A$8,$H$5:$H$8,"") -> Every pay period (ongoing) | M79: {=MAX(_xlfn.XLOOKUP($A79,TRIM(SUBSTITUTE('worker file'!$A$2:$A$406,_xlfn.UNICHAR(160)," ")),'worker file'!$M$2:$M$406,0),_xlfn.XLOOKUP($B79,TRIM('pay group & schedule'!$A$2:$A$6),'pay group & schedule'!$D$2:$D$6,0))} -> 46299 | N79: {=_xlfn.LET(_xlpm.t,_xlfn.XLOOKUP($A79,TRIM(SUBSTITUTE('worker file'!$A$2:$A$406,_xlfn.UNICHAR(160)," ")),'worker file'!$N$2:$N$406,""),IF(N(_xlpm.t)=0,"",_xlpm.t))}
A80: E0015 | B80: {=_xlfn.XLOOKUP($A80,TRIM(SUBSTITUTE('worker file'!$A$2:$A$406,_xlfn.UNICHAR(160)," ")),'worker file'!$L$2:$L$406,"Not found")} -> US Biweekly | C80: {=_xlfn.XLOOKUP($A80,TRIM(SUBSTITUTE('worker file'!$A$2:$A$406,_xlfn.UNICHAR(160)," ")),'worker file'!$D$2:$D$406,"Not found")} -> TX | D80: {=_xlfn.XLOOKUP($A80,TRIM(SUBSTITUTE('worker file'!$A$2:$A$406,_xlfn.UNICHAR(160)," ")),'worker file'!$Q$2:$Q$406,"Not found")} -> Active | E80: DEN_EE | F80: =_xlfn.XLOOKUP($E80,$A$5:$A$8,$B$5:$B$8,"") -> Dental – Employee | G80: =_xlfn.XLOOKUP($E80,$A$5:$A$8,$D$5:$D$8,"") -> Pre-tax Section 125 (exempt from FIT/SIT/FICA) | H80: =_xlfn.XLOOKUP($E80,$A$5:$A$8,$E$5:$E$8,"") -> Flat | I80: =IF($H80="Percent",_xlfn.XLOOKUP($E80,$A$5:$A$8,$F$5:$F$8,""),"") | J80: =IF($H80="Flat",_xlfn.XLOOKUP($E80,$A$5:$A$8,$F$5:$F$8,""),"") -> 44 | K80: =_xlfn.XLOOKUP($E80,$A$5:$A$8,$G$5:$G$8,"") -> Per pay period | L80: =_xlfn.XLOOKUP($E80,$A$5:$A$8,$H$5:$H$8,"") -> Every pay period (ongoing) | M80: {=MAX(_xlfn.XLOOKUP($A80,TRIM(SUBSTITUTE('worker file'!$A$2:$A$406,_xlfn.UNICHAR(160)," ")),'worker file'!$M$2:$M$406,0),_xlfn.XLOOKUP($B80,TRIM('pay group & schedule'!$A$2:$A$6),'pay group & schedule'!$D$2:$D$6,0))} -> 46299 | N80: {=_xlfn.LET(_xlpm.t,_xlfn.XLOOKUP($A80,TRIM(SUBSTITUTE('worker file'!$A$2:$A$406,_xlfn.UNICHAR(160)," ")),'worker file'!$N$2:$N$406,""),IF(N(_xlpm.t)=0,"",_xlpm.t))}
A81: E0015 | B81: {=_xlfn.XLOOKUP($A81,TRIM(SUBSTITUTE('worker file'!$A$2:$A$406,_xlfn.UNICHAR(160)," ")),'worker file'!$L$2:$L$406,"Not found")} -> US Biweekly | C81: {=_xlfn.XLOOKUP($A81,TRIM(SUBSTITUTE('worker file'!$A$2:$A$406,_xlfn.UNICHAR(160)," ")),'worker file'!$D$2:$D$406,"Not found")} -> TX | D81: {=_xlfn.XLOOKUP($A81,TRIM(SUBSTITUTE('worker file'!$A$2:$A$406,_xlfn.UNICHAR(160)," ")),'worker file'!$Q$2:$Q$406,"Not found")} -> Active | E81: VIS_EE | F81: =_xlfn.XLOOKUP($E81,$A$5:$A$8,$B$5:$B$8,"") -> Vision – Employee | G81: =_xlfn.XLOOKUP($E81,$A$5:$A$8,$D$5:$D$8,"") -> Pre-tax Section 125 (exempt from FIT/SIT/FICA) | H81: =_xlfn.XLOOKUP($E81,$A$5:$A$8,$E$5:$E$8,"") -> Flat | I81: =IF($H81="Percent",_xlfn.XLOOKUP($E81,$A$5:$A$8,$F$5:$F$8,""),"") | J81: =IF($H81="Flat",_xlfn.XLOOKUP($E81,$A$5:$A$8,$F$5:$F$8,""),"") -> 30 | K81: =_xlfn.XLOOKUP($E81,$A$5:$A$8,$G$5:$G$8,"") -> Per pay period | L81: =_xlfn.XLOOKUP($E81,$A$5:$A$8,$H$5:$H$8,"") -> Every pay period (ongoing) | M81: {=MAX(_xlfn.XLOOKUP($A81,TRIM(SUBSTITUTE('worker file'!$A$2:$A$406,_xlfn.UNICHAR(160)," ")),'worker file'!$M$2:$M$406,0),_xlfn.XLOOKUP($B81,TRIM('pay group & schedule'!$A$2:$A$6),'pay group & schedule'!$D$2:$D$6,0))} -> 46299 | N81: {=_xlfn.LET(_xlpm.t,_xlfn.XLOOKUP($A81,TRIM(SUBSTITUTE('worker file'!$A$2:$A$406,_xlfn.UNICHAR(160)," ")),'worker file'!$N$2:$N$406,""),IF(N(_xlpm.t)=0,"",_xlpm.t))}
A82: E0016 | B82: {=_xlfn.XLOOKUP($A82,TRIM(SUBSTITUTE('worker file'!$A$2:$A$406,_xlfn.UNICHAR(160)," ")),'worker file'!$L$2:$L$406,"Not found")} -> US Semi-monthly | C82: {=_xlfn.XLOOKUP($A82,TRIM(SUBSTITUTE('worker file'!$A$2:$A$406,_xlfn.UNICHAR(160)," ")),'worker file'!$D$2:$D$406,"Not found")} -> WA | D82: {=_xlfn.XLOOKUP($A82,TRIM(SUBSTITUTE('worker file'!$A$2:$A$406,_xlfn.UNICHAR(160)," ")),'worker file'!$Q$2:$Q$406,"Not found")} -> Active | E82: 401K_EE | F82: =_xlfn.XLOOKUP($E82,$A$5:$A$8,$B$5:$B$8,"") -> 401(k) Employee Deferral | G82: =_xlfn.XLOOKUP($E82,$A$5:$A$8,$D$5:$D$8,"") -> Pre-tax (exempt from FIT/SIT; subject to FICA) | H82: =_xlfn.XLOOKUP($E82,$A$5:$A$8,$E$5:$E$8,"") -> Percent | I82: 0.05 | J82: =IF($H82="Flat",_xlfn.XLOOKUP($E82,$A$5:$A$8,$F$5:$F$8,""),"") | K82: =_xlfn.XLOOKUP($E82,$A$5:$A$8,$G$5:$G$8,"") -> Gross pay | L82: =_xlfn.XLOOKUP($E82,$A$5:$A$8,$H$5:$H$8,"") -> Every pay period (ongoing) | M82: {=MAX(_xlfn.XLOOKUP($A82,TRIM(SUBSTITUTE('worker file'!$A$2:$A$406,_xlfn.UNICHAR(160)," ")),'worker file'!$M$2:$M$406,0),_xlfn.XLOOKUP($B82,TRIM('pay group & schedule'!$A$2:$A$6),'pay group & schedule'!$D$2:$D$6,0))} -> 46311 | N82: {=_xlfn.LET(_xlpm.t,_xlfn.XLOOKUP($A82,TRIM(SUBSTITUTE('worker file'!$A$2:$A$406,_xlfn.UNICHAR(160)," ")),'worker file'!$N$2:$N$406,""),IF(N(_xlpm.t)=0,"",_xlpm.t))}
A83: E0016 | B83: {=_xlfn.XLOOKUP($A83,TRIM(SUBSTITUTE('worker file'!$A$2:$A$406,_xlfn.UNICHAR(160)," ")),'worker file'!$L$2:$L$406,"Not found")} -> US Semi-monthly | C83: {=_xlfn.XLOOKUP($A83,TRIM(SUBSTITUTE('worker file'!$A$2:$A$406,_xlfn.UNICHAR(160)," ")),'worker file'!$D$2:$D$406,"Not found")} -> WA | D83: {=_xlfn.XLOOKUP($A83,TRIM(SUBSTITUTE('worker file'!$A$2:$A$406,_xlfn.UNICHAR(160)," ")),'worker file'!$Q$2:$Q$406,"Not found")} -> Active | E83: MED_EE | F83: =_xlfn.XLOOKUP($E83,$A$5:$A$8,$B$5:$B$8,"") -> Medical (Health) – Employee | G83: =_xlfn.XLOOKUP($E83,$A$5:$A$8,$D$5:$D$8,"") -> Pre-tax Section 125 (exempt from FIT/SIT/FICA) | H83: =_xlfn.XLOOKUP($E83,$A$5:$A$8,$E$5:$E$8,"") -> Flat | I83: =IF($H83="Percent",_xlfn.XLOOKUP($E83,$A$5:$A$8,$F$5:$F$8,""),"") | J83: =IF($H83="Flat",_xlfn.XLOOKUP($E83,$A$5:$A$8,$F$5:$F$8,""),"") -> 200 | K83: =_xlfn.XLOOKUP($E83,$A$5:$A$8,$G$5:$G$8,"") -> Per pay period | L83: =_xlfn.XLOOKUP($E83,$A$5:$A$8,$H$5:$H$8,"") -> Every pay period (ongoing) | M83: {=MAX(_xlfn.XLOOKUP($A83,TRIM(SUBSTITUTE('worker file'!$A$2:$A$406,_xlfn.UNICHAR(160)," ")),'worker file'!$M$2:$M$406,0),_xlfn.XLOOKUP($B83,TRIM('pay group & schedule'!$A$2:$A$6),'pay group & schedule'!$D$2:$D$6,0))} -> 46311 | N83: {=_xlfn.LET(_xlpm.t,_xlfn.XLOOKUP($A83,TRIM(SUBSTITUTE('worker file'!$A$2:$A$406,_xlfn.UNICHAR(160)," ")),'worker file'!$N$2:$N$406,""),IF(N(_xlpm.t)=0,"",_xlpm.t))}
A84: E0016 | B84: {=_xlfn.XLOOKUP($A84,TRIM(SUBSTITUTE('worker file'!$A$2:$A$406,_xlfn.UNICHAR(160)," ")),'worker file'!$L$2:$L$406,"Not found")} -> US Semi-monthly | C84: {=_xlfn.XLOOKUP($A84,TRIM(SUBSTITUTE('worker file'!$A$2:$A$406,_xlfn.UNICHAR(160)," ")),'worker file'!$D$2:$D$406,"Not found")} -> WA | D84: {=_xlfn.XLOOKUP($A84,TRIM(SUBSTITUTE('worker file'!$A$2:$A$406,_xlfn.UNICHAR(160)," ")),'worker file'!$Q$2:$Q$406,"Not found")} -> Active | E84: DEN_EE | F84: =_xlfn.XLOOKUP($E84,$A$5:$A$8,$B$5:$B$8,"") -> Dental – Employee | G84: =_xlfn.XLOOKUP($E84,$A$5:$A$8,$D$5:$D$8,"") -> Pre-tax Section 125 (exempt from FIT/SIT/FICA) | H84: =_xlfn.XLOOKUP($E84,$A$5:$A$8,$E$5:$E$8,"") -> Flat | I84: =IF($H84="Percent",_xlfn.XLOOKUP($E84,$A$5:$A$8,$F$5:$F$8,""),"") | J84: =IF($H84="Flat",_xlfn.XLOOKUP($E84,$A$5:$A$8,$F$5:$F$8,""),"") -> 44 | K84: =_xlfn.XLOOKUP($E84,$A$5:$A$8,$G$5:$G$8,"") -> Per pay period | L84: =_xlfn.XLOOKUP($E84,$A$5:$A$8,$H$5:$H$8,"") -> Every pay period (ongoing) | M84: {=MAX(_xlfn.XLOOKUP($A84,TRIM(SUBSTITUTE('worker file'!$A$2:$A$406,_xlfn.UNICHAR(160)," ")),'worker file'!$M$2:$M$406,0),_xlfn.XLOOKUP($B84,TRIM('pay group & schedule'!$A$2:$A$6),'pay group & schedule'!$D$2:$D$6,0))} -> 46311 | N84: {=_xlfn.LET(_xlpm.t,_xlfn.XLOOKUP($A84,TRIM(SUBSTITUTE('worker file'!$A$2:$A$406,_xlfn.UNICHAR(160)," ")),'worker file'!$N$2:$N$406,""),IF(N(_xlpm.t)=0,"",_xlpm.t))}
A85: E0016 | B85: {=_xlfn.XLOOKUP($A85,TRIM(SUBSTITUTE('worker file'!$A$2:$A$406,_xlfn.UNICHAR(160)," ")),'worker file'!$L$2:$L$406,"Not found")} -> US Semi-monthly | C85: {=_xlfn.XLOOKUP($A85,TRIM(SUBSTITUTE('worker file'!$A$2:$A$406,_xlfn.UNICHAR(160)," ")),'worker file'!$D$2:$D$406,"Not found")} -> WA | D85: {=_xlfn.XLOOKUP($A85,TRIM(SUBSTITUTE('worker file'!$A$2:$A$406,_xlfn.UNICHAR(160)," ")),'worker file'!$Q$2:$Q$406,"Not found")} -> Active | E85: VIS_EE | F85: =_xlfn.XLOOKUP($E85,$A$5:$A$8,$B$5:$B$8,"") -> Vision – Employee | G85: =_xlfn.XLOOKUP($E85,$A$5:$A$8,$D$5:$D$8,"") -> Pre-tax Section 125 (exempt from FIT/SIT/FICA) | H85: =_xlfn.XLOOKUP($E85,$A$5:$A$8,$E$5:$E$8,"") -> Flat | I85: =IF($H85="Percent",_xlfn.XLOOKUP($E85,$A$5:$A$8,$F$5:$F$8,""),"") | J85: =IF($H85="Flat",_xlfn.XLOOKUP($E85,$A$5:$A$8,$F$5:$F$8,""),"") -> 30 | K85: =_xlfn.XLOOKUP($E85,$A$5:$A$8,$G$5:$G$8,"") -> Per pay period | L85: =_xlfn.XLOOKUP($E85,$A$5:$A$8,$H$5:$H$8,"") -> Every pay period (ongoing) | M85: {=MAX(_xlfn.XLOOKUP($A85,TRIM(SUBSTITUTE('worker file'!$A$2:$A$406,_xlfn.UNICHAR(160)," ")),'worker file'!$M$2:$M$406,0),_xlfn.XLOOKUP($B85,TRIM('pay group & schedule'!$A$2:$A$6),'pay group & schedule'!$D$2:$D$6,0))} -> 46311 | N85: {=_xlfn.LET(_xlpm.t,_xlfn.XLOOKUP($A85,TRIM(SUBSTITUTE('worker file'!$A$2:$A$406,_xlfn.UNICHAR(160)," ")),'worker file'!$N$2:$N$406,""),IF(N(_xlpm.t)=0,"",_xlpm.t))}
A86: E0017 | B86: {=_xlfn.XLOOKUP($A86,TRIM(SUBSTITUTE('worker file'!$A$2:$A$406,_xlfn.UNICHAR(160)," ")),'worker file'!$L$2:$L$406,"Not found")} -> US Semi-monthly | C86: {=_xlfn.XLOOKUP($A86,TRIM(SUBSTITUTE('worker file'!$A$2:$A$406,_xlfn.UNICHAR(160)," ")),'worker file'!$D$2:$D$406,"Not found")} -> WA | D86: {=_xlfn.XLOOKUP($A86,TRIM(SUBSTITUTE('worker file'!$A$2:$A$406,_xlfn.UNICHAR(160)," ")),'worker file'!$Q$2:$Q$406,"Not found")} -> Termination pending | E86: 401K_EE | F86: =_xlfn.XLOOKUP($E86,$A$5:$A$8,$B$5:$B$8,"") -> 401(k) Employee Deferral | G86: =_xlfn.XLOOKUP($E86,$A$5:$A$8,$D$5:$D$8,"") -> Pre-tax (exempt from FIT/SIT; subject to FICA) | H86: =_xlfn.XLOOKUP($E86,$A$5:$A$8,$E$5:$E$8,"") -> Percent | I86: 0.02 | J86: =IF($H86="Flat",_xlfn.XLOOKUP($E86,$A$5:$A$8,$F$5:$F$8,""),"") | K86: =_xlfn.XLOOKUP($E86,$A$5:$A$8,$G$5:$G$8,"") -> Gross pay | L86: =_xlfn.XLOOKUP($E86,$A$5:$A$8,$H$5:$H$8,"") -> Every pay period (ongoing) | M86: {=MAX(_xlfn.XLOOKUP($A86,TRIM(SUBSTITUTE('worker file'!$A$2:$A$406,_xlfn.UNICHAR(160)," ")),'worker file'!$M$2:$M$406,0),_xlfn.XLOOKUP($B86,TRIM('pay group & schedule'!$A$2:$A$6),'pay group & schedule'!$D$2:$D$6,0))} -> 46311 | N86: {=_xlfn.LET(_xlpm.t,_xlfn.XLOOKUP($A86,TRIM(SUBSTITUTE('worker file'!$A$2:$A$406,_xlfn.UNICHAR(160)," ")),'worker file'!$N$2:$N$406,""),IF(N(_xlpm.t)=0,"",_xlpm.t))} -> 46318 | O86: Ongoing until term date; stop after final pay
A87: E0017 | B87: {=_xlfn.XLOOKUP($A87,TRIM(SUBSTITUTE('worker file'!$A$2:$A$406,_xlfn.UNICHAR(160)," ")),'worker file'!$L$2:$L$406,"Not found")} -> US Semi-monthly | C87: {=_xlfn.XLOOKUP($A87,TRIM(SUBSTITUTE('worker file'!$A$2:$A$406,_xlfn.UNICHAR(160)," ")),'worker file'!$D$2:$D$406,"Not found")} -> WA | D87: {=_xlfn.XLOOKUP($A87,TRIM(SUBSTITUTE('worker file'!$A$2:$A$406,_xlfn.UNICHAR(160)," ")),'worker file'!$Q$2:$Q$406,"Not found")} -> Termination pending | E87: MED_EE | F87: =_xlfn.XLOOKUP($E87,$A$5:$A$8,$B$5:$B$8,"") -> Medical (Health) – Employee | G87: =_xlfn.XLOOKUP($E87,$A$5:$A$8,$D$5:$D$8,"") -> Pre-tax Section 125 (exempt from FIT/SIT/FICA) | H87: =_xlfn.XLOOKUP($E87,$A$5:$A$8,$E$5:$E$8,"") -> Flat | I87: =IF($H87="Percent",_xlfn.XLOOKUP($E87,$A$5:$A$8,$F$5:$F$8,""),"") | J87: =IF($H87="Flat",_xlfn.XLOOKUP($E87,$A$5:$A$8,$F$5:$F$8,""),"") -> 200 | K87: =_xlfn.XLOOKUP($E87,$A$5:$A$8,$G$5:$G$8,"") -> Per pay period | L87: =_xlfn.XLOOKUP($E87,$A$5:$A$8,$H$5:$H$8,"") -> Every pay period (ongoing) | M87: {=MAX(_xlfn.XLOOKUP($A87,TRIM(SUBSTITUTE('worker file'!$A$2:$A$406,_xlfn.UNICHAR(160)," ")),'worker file'!$M$2:$M$406,0),_xlfn.XLOOKUP($B87,TRIM('pay group & schedule'!$A$2:$A$6),'pay group & schedule'!$D$2:$D$6,0))} -> 46311 | N87: {=_xlfn.LET(_xlpm.t,_xlfn.XLOOKUP($A87,TRIM(SUBSTITUTE('worker file'!$A$2:$A$406,_xlfn.UNICHAR(160)," ")),'worker file'!$N$2:$N$406,""),IF(N(_xlpm.t)=0,"",_xlpm.t))} -> 46318 | O87: Ongoing until term date; stop after final pay
